Workbook
Name 切片器_二级费项2: #N/A
Name 切片器_月份: #N/A
Name 切片器_二级费项: #N/A

Sheet 财务映射表
A1: 财务费项 | C1: 成本费项
A2: 编码 | B2: 费项名称 | C2: 编码 | D2: 费项名称
A3: 6400 | B3: （二）营业成本
A4: 6401 | B4: 主营业务成本
A5: 6401.03 | B5: 物业管理业务成本
A6: 6401.03.01 | B6: 材料费用 | C6: 1.2 | D6: 物耗成本
A7: 6401.03.02 | B7: 外包费用
A8: 6401.03.02.01 | B8: 保洁外包 | C8: 1.1.1.3.3 | D8: 专业外包（人员）
A9: 6401.03.02.02 | B9: 安全外包 | C9: 1.1.1.1.3 | D9: 专业外包
A10: 6401.03.02.03 | B10: 绿化外包 | C10: 1.1.1.6.3 | D10: 专业外包（岗位）
C11: 1.1.1.6.4 | D11: 专业外包（面积）
A12: 6401.03.02.04 | B12: 消杀外包 | C12: 1.1.2.7.1 | D12: 消杀服务
A13: 6401.03.02.05 | B13: 电梯维保外保 | C13: 1.1.2.1 | D13: 电梯维保
A14: 6401.03.02.06 | B14: 设备设施维保外包 | C14: 1.1.2.3 | D14: 暖通维护
C15: 1.1.2.4 | D15: 弱电维护
C16: 1.1.2.5 | D16: 给排水维护
C17: 1.1.2.6 | D17: 设备维护
A18: 6401.03.02.07 | B18: 消防保外包 | C18: 1.1.2.2 | D18: 消防维保
A19: 6401.03.02.08 | B19: 装修垃圾清运外包 | C19: 1.1.2.7.2.4 | D19: 建筑/大件垃圾清运（新项目首次）
C20: 1.1.2.7.2.5 | D20: 建筑/大件垃圾清运（旧项目）
A21: 6401.03.02.09 | B21: 生活垃圾清运外包 | C21: 1.1.2.7.2.1 | D21: 生活垃圾清运（按240L桶）
C22: 1.1.2.7.2.2 | D22: 生活垃圾清运（按立方）
C23: 1.1.2.7.2.3 | D23: 生活垃圾清运（按户）
A24: 6401.03.02.10 | B24: 工程施工外包 | C24: 1.3 | D24: 维改成本
A25: 6401.03.02.11 | B25: 人事外包费 | C25: 1.1.1.1.2 | D25: 劳务派遣
C26: 1.1.1.2.2 | D26: 劳务派遣
C27: 1.1.1.3.2 | D27: 劳务派遣
C28: 1.1.1.4.2 | D28: 劳务派遣
C29: 1.1.1.5.2 | D29: 劳务派遣
C30: 1.1.1.6.2 | D30: 劳务派遣
C31: 1.1.1.7.2 | D31: 劳务派遣
C32: 1.1.1.8.2 | D32: 劳务派遣
A33: 6401.03.07 | B33: 业务支持费 | C33: 1.5.9 | D33: 业务招待费
A34: 6401.03.80 | B34: 能源成本类
A35: 6401.03.80.01 | B35: 水费 | C35: 1.4.1 | D35: 公共水费及相关费
A36: 6401.03.80.02 | B36: 电费 | C36: 1.4.2 | D36: 公共电费
A37: 6401.03.80.03 | B37: 暖气费 | C37: 1.4.4 | D37: 公共采暖费
A38: 6401.03.80.04 | B38: 燃气费 | C38: 1.4.3 | D38: 公共燃气费
A39: 6401.03.80.99 | B39: 其他能源成本 | C39: 1.4.5 | D39: 公共其他能源费
C40: 1.5.4 | D40: 物管能源费
A41: 6401.03.81 | B41: 人工费用类
A42: 6401.03.81.01 | B42: 工资 | C42: 1.1.1.1.1 | D42: 自有人员
A43: 6401.03.81.02 | B43: 奖金 | C43: 1.1.1.2.1 | D43: 自有人员
A44: 6401.03.81.03 | B44: 福利费 | C44: 1.1.1.3.1 | D44: 自有人员
A45: 6401.03.81.04 | B45: 社会保险费 | C45: 1.1.1.4.1 | D45: 自有人员
A46: 6401.03.81.05 | B46: 住房公积金 | C46: 1.1.1.5.1 | D46: 自有人员
A47: 6401.03.81.06 | B47: 工会经费 | C47: 1.1.1.6.1 | D47: 自有人员
A48: 6401.03.81.07 | B48: 职工教育经费 | C48: 1.1.1.7.1 | D48: 自有人员
A49: 6401.03.81.99 | B49: 其他人工费 | C49: 1.1.1.8.1 | D49: 自有人员
A50: 6401.03.82 | B50: 办公事务类
A51: 6401.03.82.01 | B51: 办公费 | C51: 1.5.1 | D51: 打印机租赁
C52: 1.5.2 | D52: 办公耗材
A53: 6401.03.82.02 | B53: 租赁费 | C53: 1.5.3 | D53: 房租
C54: 1.5.5 | D54: 网费
A55: 6401.03.82.04 | B55: 通讯费 | C55: 1.5.6 | D55: 通讯费
A56: 6401.03.83 | B56: 业务活动类
A57: 6401.03.83.01 | B57: 差旅费 | C57: 1.5.7 | D57: 差旅费
A58: 6401.03.83.03 | B58: 交通费 | C58: 1.5.8 | D58: 交通费
A59: 6401.03.83.04 | B59: 咨询服务费
A60: 6401.03.83.05 | B60: 劳务费
A61: 6401.03.83.06 | B61: 招聘费
A62: 6401.03.83.07 | B62: 行业协会费
A63: 6401.03.83.99 | B63: 其他业务费

Sheet 运营成本管理看板
B2: 运营成本管理看板
B3: 项目名称 | D3: ='1-1 项目基础信息'!D8 -> 深圳区域公司深圳金地中心物业管理服务中心 | I3: 年度 | J3: 2025 | K3: 月度 | L3: 8 | M3: 月 | O3: 预算目标中主要人工人数情况
B4: 年度总目标成本 A（万元） | D4: ='2 过程管理表单'!H4/10000 -> 1235.5034 | F4: 时间进度 月份/12 | H4: =L3/12 -> 0.66666667 | J4: =H4 -> 0.66666667 | K4: =1-J4 -> 0.33333333 | O4: 自有人数 合计 （人） | P4: =SUM(P6:P10) -> 51 | Q4: 派遣人数 合计 （人） | R4: =SUM(Q6:Q10) -> 0 | S4: 外包人数 合计 （人） | T4: =SUM(R6:R10) -> 24
B5: 月累总目标成本 B（万元） | D5: =INDEX('4主要费项费项月累成本使用情况'!C38:N38,MATCH($L$3&"月",表3_3[[#Headers],[1月]:[12月]],0))/10000 -> 827.44693 | F5: 年度使用率 C/A | H5: =D6/D4 -> 0.87659339 | J5: =H5 -> 0.87659339 | K5: =1-J5 -> 0.12340661 | P5: 自有 | Q5: 派遣 | R5: 外包
B6: 月累已发生成本 C（万元） | D6: =INDEX('4主要费项费项月累成本使用情况'!C39:N39,MATCH($L$3&"月",表3_3[[#Headers],[1月]:[12月]],0))/10000 -> 1083.0342 | F6: 月累使用率 C/B | H6: =D6/D5 -> 1.3088865 | J6: =H6 -> 1.3088865 | K6: =1-J6 -> -0.30888655 | O6: 保安 | P6: ='1-2 人员岗位信息'!D7 -> 15 | Q6: ='1-2 人员岗位信息'!D8 -> 0 | R6: ='1-2 人员岗位信息'!D9 -> 0
B7: 二级费项【月累】 超成本数量 | D7: =INDEX('4主要费项费项月累成本使用情况'!C48:N48,MATCH($L$3&"月",表3_3[[#Headers],[1月]:[12月]],0)) -> 0 | E7: /6 | F7: 自有人工使用率 已发生/年度目标 | H7: =IFERROR(INDEX(自有人员计算表!C35:N35,MATCH($L$3&"月",自有人员计算表!C1:N1,0))/自有人员计算表!N37,"无目标值") -> 0.59912271 | J7: =H7 -> 0.59912271 | K7: =1-J7 -> 0.40087729 | O7: 保洁 | P7: ='1-2 人员岗位信息'!D71 -> 0 | Q7: ='1-2 人员岗位信息'!D72 -> 0 | R7: ='1-2 人员岗位信息'!D73 -> 24
B8: 三级费项【月累】 超成本数量 | D8: =INDEX(三级费项月累表格!C195:N195,MATCH($L$3&"月",表3_3[[#Headers],[1月]:[12月]],0)) -> 108 | E8: /456 | F8: 劳务派遣使用率 已发生/年度目标 | H8: =IFERROR(INDEX(劳务派遣统计表!C35:N35,MATCH($L$3&"月",劳务派遣统计表!C1:N1,0))/劳务派遣统计表!N37,"无目标值") -> 无目标值 | J8: =H8 -> 无目标值 | K8: =1-J8 -> #VALUE! | O8: 工程 | P8: ='1-2 人员岗位信息'!D115 -> 11 | Q8: ='1-2 人员岗位信息'!D116 -> 0 | R8: ='1-2 人员岗位信息'!D117 -> 0
B9: 主控费项【月累】 超成本数量 | D9: 35 | E9: /103 | F9: 劳务外包使用率 已发生/年度目标 | H9: =IFERROR(INDEX(劳务外包表!C47:N47,MATCH($L$3&"月",劳务外包表!C1:N1,0))/劳务外包表!N49,"无目标值") -> 0.42267755 | J9: =H9 -> 0.42267755 | K9: =1-J9 -> 0.57732245 | O9: 管家 | P9: ='1-2 人员岗位信息'!D155 -> 12 | Q9: ='1-2 人员岗位信息'!D156 -> 0 | R9: ='1-2 人员岗位信息'!D157 -> 0
B10: 已签约合同数量 （份） | D10: {=SUMPRODUCT((TEXT('2-2 引出数据_合同数据仓库'!$E:$E,"yyyymm")<=TEXT(DATE(2025,$L$3+1,0),"yyyymm"))*(('2-2 引出数据_合同数据仓库'!$C:$C="审核通过")))} -> 59 | F10: 金采易购下单量 （单） | H10: {=SUMPRODUCT(--(LEFT('2-1 采购订单物料明细表报表导出'!$K:$K,7)<>"")*--(LEFT('2-1 采购订单物料明细表报表导出'!$K:$K,7)<=TEXT(DATE(2025,$L$3,1),"yyyy-mm")))} -> 198 | J10: 报销单据数量 （笔） | L10: {=SUMPRODUCT((TEXT('2-3 引出列表'!$N:$N,"yyyymm")<=TEXT(DATE(2025,$L$3+1,0),"yyyymm"))*(('2-3 引出列表'!$L:$L="已审核")+('2-3 引出列表'!$L:$L="已付款")))} -> 275 | O10: 客服 | P10: ='1-2 人员岗位信息'!D35 -> 13 | Q10: ='1-2 人员岗位信息'!D36 -> 0 | R10: ='1-2 人员岗位信息'!D37 -> 0
B12: 1 月累成本使用情况
B25: 2 每月成本使用情况
B45: 3 主要费项费项月累成本使用情况
N46: 费项 编码 | O46: 费项 名称 | P46: 年度目标成本 （万元） | Q46: 月累目标成本（万元） | R46: 月累已发生（万元） | S46: 年度使用率 | T46: 月度使用率
N48: 1.1 | O48: 服务成本 | P48: ='2 过程管理表单'!H5/10000 -> 912.83627 | Q48: =INDEX('4主要费项费项月累成本使用情况'!C5:N5,MATCH($L$3&"月",表3_3[[#Headers],[1月]:[12月]],0))/10000 -> 612.33548 | R48: =INDEX('4主要费项费项月累成本使用情况'!C3:N3,MATCH($L$3&"月",表3_3[[#Headers],[1月]:[12月]],0))/10000 -> 618.31345 | S48: =IFERROR(R48/P48,"无年度目标") -> 0.67735417 | T48: =IFERROR(R48/Q48,"无月度目标") -> 1.0097626
N49: 1.2 | O49: 物耗成本 | P49: ='2 过程管理表单'!H519/10000 -> 41.858577 | Q49: =INDEX('4主要费项费项月累成本使用情况'!C9:N9,MATCH($L$3&"月",表3_3[[#Headers],[1月]:[12月]],0))/10000 -> 27.905718 | R49: =INDEX('4主要费项费项月累成本使用情况'!C7:N7,MATCH($L$3&"月",表3_3[[#Headers],[1月]:[12月]],0))/10000 -> 17.722646 | S49: =IFERROR(R49/P49,"无年度目标") -> 0.42339342 | T49: =IFERROR(R49/Q49,"无月度目标") -> 0.63509013
N50: 1.3 | O50: 维改成本 | P50: ='2 过程管理表单'!H547/10000 -> 38.528 | Q50: =INDEX('4主要费项费项月累成本使用情况'!C13:N13,MATCH($L$3&"月",表3_3[[#Headers],[1月]:[12月]],0))/10000 -> 25.685333 | R50: =INDEX('4主要费项费项月累成本使用情况'!C10:N10,MATCH($L$3&"月",表3_3[[#Headers],[1月]:[12月]],0))/10000 -> 1.5549944 | S50: =IFERROR(R50/P50,"无年度目标") -> 0.040360112 | T50: =IFERROR(R50/Q50,"无月度目标") -> 0.060540167
N51: 1.4 | O51: 能源成本 | P51: ='2 过程管理表单'!H630/10000 -> 211.90323 | Q51: =INDEX('4主要费项费项月累成本使用情况'!C17:N17,MATCH($L$3&"月",表3_3[[#Headers],[1月]:[12月]],0))/10000 -> 141.26882 | R51: =INDEX('4主要费项费项月累成本使用情况'!C15:N15,MATCH($L$3&"月",表3_3[[#Headers],[1月]:[12月]],0))/10000 -> 399.36891 | S51: =IFERROR(R51/P51,"无年度目标") -> 1.8846758 | T51: =IFERROR(R51/Q51,"无月度目标") -> 2.8270138
N52: 1.5 | O52: 行政办公 | P52: ='2 过程管理表单'!H636/10000 -> 3.5932 | Q52: =INDEX('4主要费项费项月累成本使用情况'!C21:N21,MATCH($L$3&"月",表3_3[[#Headers],[1月]:[12月]],0))/10000 -> 2.3954667 | R52: =INDEX('4主要费项费项月累成本使用情况'!C19:N19,MATCH($L$3&"月",表3_3[[#Headers],[1月]:[12月]],0))/10000 -> 34.729193 | S52: =IFERROR(R52/P52,"无年度目标") -> 9.6652546 | T52: =IFERROR(R52/Q52,"无月度目标") -> 14.497882
N53: 1.6 | O53: 前期投入 | P53: ='2 过程管理表单'!H649/10000 -> 26.784161 | Q53: =INDEX('4主要费项费项月累成本使用情况'!C25:N25,MATCH($L$3&"月",表3_3[[#Headers],[1月]:[12月]],0))/10000 -> 17.856108 | R53: =INDEX('4主要费项费项月累成本使用情况'!C23:N23,MATCH($L$3&"月",表3_3[[#Headers],[1月]:[12月]],0))/10000 -> 2.940071 | S53: =IFERROR(R53/P53,"无年度目标") -> 0.10976901 | T53: =IFERROR(R53/Q53,"无月度目标") -> 0.16465352
N54: 1.1.1 | O54: 人工服务 | P54: ='2 过程管理表单'!H6/10000 -> 854.24035 | Q54: =INDEX('4主要费项费项月累成本使用情况'!C29:N29,MATCH($L$3&"月",表3_3[[#Headers],[1月]:[12月]],0))/10000 -> 573.27153 | R54: =INDEX('4主要费项费项月累成本使用情况'!C27:N27,MATCH($L$3&"月",表3_3[[#Headers],[1月]:[12月]],0))/10000 -> 553.69166 | S54: =IFERROR(R54/P54,"无年度目标") -> 0.64816847 | T54: =IFERROR(R54/Q54,"无月度目标") -> 0.96584538
N55: 1.1.2 | O55: 维护服务 | P55: ='2 过程管理表单'!H184/10000 -> 58.595913 | Q55: =INDEX('4主要费项费项月累成本使用情况'!C33:N33,MATCH($L$3&"月",表3_3[[#Headers],[1月]:[12月]],0))/10000 -> 0 | R55: =INDEX('4主要费项费项月累成本使用情况'!C31:N31,MATCH($L$3&"月",表3_3[[#Headers],[1月]:[12月]],0))/10000 -> 1.8588339 | S55: =IFERROR(R55/P55,"无年度目标") -> 0.031722928 | T55: =IFERROR(R55/Q55,"无月度目标") -> 无月度目标
N56: 1.1.3 | O56: 检测服务 | P56: ='2 过程管理表单'!H439/10000 -> 0 | Q56: =INDEX('4主要费项费项月累成本使用情况'!C37:N37,MATCH($L$3&"月",表3_3[[#Headers],[1月]:[12月]],0))/10000 -> 39.063942 | R56: =INDEX('4主要费项费项月累成本使用情况'!C35:N35,MATCH($L$3&"月",表3_3[[#Headers],[1月]:[12月]],0))/10000 -> 63.498428 | S56: =IFERROR(R56/P56,"无年度目标") -> 无年度目标 | T56: =IFERROR(R56/Q56,"无月度目标") -> 1.6254998
L57: 0
B58: 4 二级费项目标成本每月使用情况
B71: 5 异常项统计表

Sheet 运营成本管理看板（2）
B2: 运营成本管理看板
B3: 项目名称 | D3: ='1-1 项目基础信息'!D8 -> 深圳区域公司深圳金地中心物业管理服务中心 | I3: 年度 | J3: 2025 | K3: 月度 | L3: 5 | M3: 月 | O3: 预算目标中主要人工人数情况
B4: 年度总目标成本 A（万元） | D4: ='4-1主要费项费项月累成本使用情况 '!N38/10000 -> 512.86222 | F4: 时间进度 月份/12 | H4: =L3/12 -> 0.41666667 | J4: =H4 -> 0.41666667 | K4: =1-J4 -> 0.58333333 | O4: 自有人数 合计 （人） | P4: =SUM(P6:P10) -> 51 | Q4: 派遣人数 合计 （人） | R4: =SUM(Q6:Q10) -> 0 | S4: 外包人数 合计 （人） | T4: =SUM(R6:R10) -> 24
B5: 月累总目标成本 B（万元） | D5: =INDEX('4-1主要费项费项月累成本使用情况 '!C38:N38,MATCH($L$3&"月",表3_3[[#Headers],[1月]:[12月]],0))/10000 -> 213.69259 | F5: 年度使用率 C/A | H5: =D6/D4 -> 0.62125195 | J5: =H5 -> 0.62125195 | K5: =1-J5 -> 0.37874805 | P5: 自有 | Q5: 派遣 | R5: 外包
B6: 月累已发生成本 C（万元） | D6: =INDEX('4-1主要费项费项月累成本使用情况 '!C39:N39,MATCH($L$3&"月",表3_3[[#Headers],[1月]:[12月]],0))/10000 -> 318.61665 | F6: 月累使用率 C/B | H6: =D6/D5 -> 1.4910047 | J6: =H6 -> 1.4910047 | K6: =1-J6 -> -0.49100468 | O6: 保安 | P6: ='1-2 人员岗位信息'!D7 -> 15 | Q6: ='1-2 人员岗位信息'!D8 -> 0 | R6: ='1-2 人员岗位信息'!D9 -> 0
B7: 二级费项【月累】 超成本数量 | D7: =INDEX('4-1主要费项费项月累成本使用情况 '!C48:N48,MATCH($L$3&"月",表3_3[[#Headers],[1月]:[12月]],0)) -> 1 | E7: /6 | F7: 自有人工使用率 已发生/年度目标 | H7: =IFERROR(INDEX(自有人员计算表!C35:N35,MATCH($L$3&"月",自有人员计算表!C1:N1,0))/自有人员计算表!N37,"无目标值") -> 0.40866895 | J7: =H7 -> 0.40866895 | K7: =1-J7 -> 0.59133105 | O7: 保洁 | P7: ='1-2 人员岗位信息'!D71 -> 0 | Q7: ='1-2 人员岗位信息'!D72 -> 0 | R7: ='1-2 人员岗位信息'!D73 -> 24
B8: 三级费项【月累】 超成本数量 | D8: =INDEX(三级费项月累表格!C195:N195,MATCH($L$3&"月",表3_3[[#Headers],[1月]:[12月]],0)) -> 63 | E8: /456 | F8: 劳务派遣使用率 已发生/年度目标 | H8: =IFERROR(INDEX(劳务派遣统计表!C35:N35,MATCH($L$3&"月",劳务派遣统计表!C1:N1,0))/劳务派遣统计表!N37,"无目标值") -> 无目标值 | J8: =H8 -> 无目标值 | K8: =1-J8 -> #VALUE! | O8: 工程 | P8: ='1-2 人员岗位信息'!D115 -> 11 | Q8: ='1-2 人员岗位信息'!D116 -> 0 | R8: ='1-2 人员岗位信息'!D117 -> 0
B9: 主控费项【月累】 超成本数量 | D9: =INDEX('4-1主要费项费项月累成本使用情况 '!C52:N52,MATCH($L$3&"月",表3_3[[#Headers],[1月]:[12月]],0)) -> 29 | E9: /103 | F9: 劳务外包使用率 已发生/年度目标 | H9: =IFERROR(INDEX(劳务外包表!C47:N47,MATCH($L$3&"月",劳务外包表!C1:N1,0))/劳务外包表!N49,"无目标值") -> 0.36159236 | J9: =H9 -> 0.36159236 | K9: =1-J9 -> 0.63840764 | O9: 管家 | P9: ='1-2 人员岗位信息'!D155 -> 12 | Q9: ='1-2 人员岗位信息'!D156 -> 0 | R9: ='1-2 人员岗位信息'!D157 -> 0
B10: 已签约合同数量 （份） | D10: {=SUMPRODUCT((TEXT('2-2 引出数据_合同数据仓库'!$E:$E,"yyyymm")<=TEXT(DATE(2025,$L$3+1,0),"yyyymm"))*(('2-2 引出数据_合同数据仓库'!$C:$C="审核通过")))} -> 47 | F10: 金采易购下单量 （单） | H10: {=SUMPRODUCT(--(LEFT('2-1 采购订单物料明细表报表导出'!$K:$K,7)<>"")*--(LEFT('2-1 采购订单物料明细表报表导出'!$K:$K,7)<=TEXT(DATE(2025,$L$3,1),"yyyy-mm")))} -> 105 | J10: 报销单据数量 （笔） | L10: {=SUMPRODUCT((TEXT('2-3 引出列表'!$N:$N,"yyyymm")<=TEXT(DATE(2025,$L$3+1,0),"yyyymm"))*(('2-3 引出列表'!$L:$L="已审核")+('2-3 引出列表'!$L:$L="已付款")))} -> 196 | O10: 客服 | P10: ='1-2 人员岗位信息'!D35 -> 13 | Q10: ='1-2 人员岗位信息'!D36 -> 0 | R10: ='1-2 人员岗位信息'!D37 -> 0
B12: 1 月累成本使用情况
B25: 2 每月成本使用情况
B45: 3 主要费项费项月累成本使用情况
N46: 费项 编码 | O46: 费项 名称 | P46: 年度目标成本 （万元） | Q46: 月累目标成本（万元） | R46: 月累已发生（万元） | S46: 年度使用率 | T46: 月度使用率
N48: 1.1 | O48: 服务成本 | P48: ='2 过程管理表单'!H5/10000 -> 912.83627 | Q48: =INDEX('4-1主要费项费项月累成本使用情况 '!C5:N5,MATCH($L$3&"月",表3_3[[#Headers],[1月]:[12月]],0))/10000 -> 79.247935 | R48: =INDEX('4-1主要费项费项月累成本使用情况 '!C3:N3,MATCH($L$3&"月",表3_3[[#Headers],[1月]:[12月]],0))/10000 -> 126.59281 | S48: =IFERROR(R48/P48,"无年度目标") -> 0.13868074 | T48: =IFERROR(R48/Q48,"无月度目标") -> 1.5974272
N49: 1.2 | O49: 物耗成本 | P49: ='2 过程管理表单'!H519/10000 -> 41.858577 | Q49: =INDEX('4-1主要费项费项月累成本使用情况 '!C9:N9,MATCH($L$3&"月",表3_3[[#Headers],[1月]:[12月]],0))/10000 -> 17.441074 | R49: =INDEX('4-1主要费项费项月累成本使用情况 '!C7:N7,MATCH($L$3&"月",表3_3[[#Headers],[1月]:[12月]],0))/10000 -> 7.643845 | S49: =IFERROR(R49/P49,"无年度目标") -> 0.1826112 | T49: =IFERROR(R49/Q49,"无月度目标") -> 0.43826688
N50: 1.3 | O50: 维改成本 | P50: ='2 过程管理表单'!H547/10000 -> 38.528 | Q50: =INDEX('4-1主要费项费项月累成本使用情况 '!C13:N13,MATCH($L$3&"月",表3_3[[#Headers],[1月]:[12月]],0))/10000 -> 16.053333 | R50: =INDEX('4-1主要费项费项月累成本使用情况 '!C10:N10,MATCH($L$3&"月",表3_3[[#Headers],[1月]:[12月]],0))/10000 -> 1.1745096 | S50: =IFERROR(R50/P50,"无年度目标") -> 0.030484571 | T50: =IFERROR(R50/Q50,"无月度目标") -> 0.073162971
N51: 1.4 | O51: 能源成本 | P51: ='2 过程管理表单'!H631/10000 -> 11.50353 | Q51: =INDEX('4-1主要费项费项月累成本使用情况 '!C17:N17,MATCH($L$3&"月",表3_3[[#Headers],[1月]:[12月]],0))/10000 -> 88.293014 | R51: =INDEX('4-1主要费项费项月累成本使用情况 '!C15:N15,MATCH($L$3&"月",表3_3[[#Headers],[1月]:[12月]],0))/10000 -> 142.13876 | S51: =IFERROR(R51/P51,"无年度目标") -> 12.3561 | T51: =IFERROR(R51/Q51,"无月度目标") -> 1.6098528
N52: 1.5 | O52: 行政办公 | P52: ='2 过程管理表单'!H637/10000 -> 0 | Q52: =INDEX('4-1主要费项费项月累成本使用情况 '!C21:N21,MATCH($L$3&"月",表3_3[[#Headers],[1月]:[12月]],0))/10000 -> 1.4971667 | R52: =INDEX('4-1主要费项费项月累成本使用情况 '!C19:N19,MATCH($L$3&"月",表3_3[[#Headers],[1月]:[12月]],0))/10000 -> 34.113554 | S52: =IFERROR(R52/P52,"无年度目标") -> 无年度目标 | T52: =IFERROR(R52/Q52,"无月度目标") -> 22.785408
N53: 1.6 | O53: 前期投入 | P53: ='2 过程管理表单'!H650/10000 -> 4.74 | Q53: =INDEX('4-1主要费项费项月累成本使用情况 '!C25:N25,MATCH($L$3&"月",表3_3[[#Headers],[1月]:[12月]],0))/10000 -> 11.160067 | R53: =INDEX('4-1主要费项费项月累成本使用情况 '!C23:N23,MATCH($L$3&"月",表3_3[[#Headers],[1月]:[12月]],0))/10000 -> 1.7760845 | S53: =IFERROR(R53/P53,"无年度目标") -> 0.37470137 | T53: =IFERROR(R53/Q53,"无月度目标") -> 0.1591464
N54: 1.1.1 | O54: 人工服务 | P54: ='2 过程管理表单'!H6/10000 -> 854.24035 | Q54: =INDEX('4-1主要费项费项月累成本使用情况 '!C29:N29,MATCH($L$3&"月",表3_3[[#Headers],[1月]:[12月]],0))/10000 -> 303.26931 | R54: =INDEX('4-1主要费项费项月累成本使用情况 '!C27:N27,MATCH($L$3&"月",表3_3[[#Headers],[1月]:[12月]],0))/10000 -> 326.63229 | S54: =IFERROR(R54/P54,"无年度目标") -> 0.38236579 | T54: =IFERROR(R54/Q54,"无月度目标") -> 1.0770371
N55: 1.1.2 | O55: 维护服务 | P55: ='2 过程管理表单'!H184/10000 -> 58.595913 | Q55: =INDEX('4-1主要费项费项月累成本使用情况 '!C33:N33,MATCH($L$3&"月",表3_3[[#Headers],[1月]:[12月]],0))/10000 -> 0 | R55: =INDEX('4-1主要费项费项月累成本使用情况 '!C31:N31,MATCH($L$3&"月",表3_3[[#Headers],[1月]:[12月]],0))/10000 -> 1.2410959 | S55: =IFERROR(R55/P55,"无年度目标") -> 0.021180588 | T55: =IFERROR(R55/Q55,"无月度目标") -> 无月度目标
N56: 1.1.3 | O56: 检测服务 | P56: ='2 过程管理表单'!H439/10000 -> 0 | Q56: =INDEX('4-1主要费项费项月累成本使用情况 '!C37:N37,MATCH($L$3&"月",表3_3[[#Headers],[1月]:[12月]],0))/10000 -> 24.414964 | R56: =INDEX('4-1主要费项费项月累成本使用情况 '!C35:N35,MATCH($L$3&"月",表3_3[[#Headers],[1月]:[12月]],0))/10000 -> 41.741291 | S56: =IFERROR(R56/P56,"无年度目标") -> 无年度目标 | T56: =IFERROR(R56/Q56,"无月度目标") -> 1.7096602
L57: 0
B58: 4 二级费项目标成本每月使用情况
B71: 5 异常项统计表

Sheet 预算主表
A1: 02经营数据明细表
A2: 科目编码 | B2: 科目名称 | C2: 2024年实际 | D2: 1月实际 | E2: 2月实际 | F2: 3月实际 | G2: 4月实际 | H2: 5月实际 | I2: 6月实际 | J2: 7月实际 | K2: 8月实际 | L2: 9月实际 | M2: 10月实际 | N2: 11月实际 | O2: 12月实际 | P2: 2025年预算 | Q2: 1月预算 | R2: 2月预算 | S2: 3月预算 | T2: 4月预算 | U2: 5月预算 | V2: 6月预算 | W2: 7月预算 | X2: 8月预算 | Y2: 9月预算 | Z2: 10月预算 | AA2: 11月预算 | AB2: 12月预算
A3: 6000 | B3: （一）营业收入 | C3: 21558224 | D3: 1570864.5 | E3: 1751568.1 | F3: 2115678.3 | G3: 1484751.8 | H3: 1473544.6 | I3: 1993105.6 | J3: 1589348.5 | K3: 1686218.1 | L3: 2015157.2 | M3: 1564690.5 | N3: 1757259.1 | O3: 2556037.9 | P3: 21574149 | Q3: 1782613 | R3: 1775757.6 | S3: 1797226.5 | T3: 1776323.7 | U3: 1805443.2 | V3: 1814616.4 | W3: 1804311.1 | X3: 1800852 | Y3: 1822320.9 | Z3: 1796606.7 | AA3: 1797455.7 | AB3: 1800622.7
A4: 6001 | B4: 主营业务收入 | C4: 21558224 | D4: 1570864.5 | E4: 1751568.1 | F4: 2115678.3 | G4: 1484751.8 | H4: 1473544.6 | I4: 1993105.6 | J4: 1589348.5 | K4: 1686218.1 | L4: 2015157.2 | M4: 1564690.5 | N4: 1757259.1 | O4: 2556037.9 | P4: 21574149 | Q4: 1782613 | R4: 1775757.6 | S4: 1797226.5 | T4: 1776323.7 | U4: 1805443.2 | V4: 1814616.4 | W4: 1804311.1 | X4: 1800852 | Y4: 1822320.9 | Z4: 1796606.7 | AA4: 1797455.7 | AB4: 1800622.7
A5: 6001.03 | B5: 物业管理业务收入 | C5: 21558224 | D5: 1570864.5 | E5: 1751568.1 | F5: 2115678.3 | G5: 1484751.8 | H5: 1473544.6 | I5: 1993105.6 | J5: 1589348.5 | K5: 1686218.1 | L5: 2015157.2 | M5: 1564690.5 | N5: 1757259.1 | O5: 2556037.9 | P5: 21574149 | Q5: 1782613 | R5: 1775757.6 | S5: 1797226.5 | T5: 1776323.7 | U5: 1805443.2 | V5: 1814616.4 | W5: 1804311.1 | X5: 1800852 | Y5: 1822320.9 | Z5: 1796606.7 | AA5: 1797455.7 | AB5: 1800622.7
A6: 6001.03.01 | B6: 物业服务 | C6: 21558224 | D6: 1570864.5 | E6: 1751568.1 | F6: 2115678.3 | G6: 1484751.8 | H6: 1473544.6 | I6: 1993105.6 | J6: 1589348.5 | K6: 1686218.1 | L6: 2015157.2 | M6: 1564690.5 | N6: 1757259.1 | O6: 2556037.9 | P6: 21574149 | Q6: 1782613 | R6: 1775757.6 | S6: 1797226.5 | T6: 1776323.7 | U6: 1805443.2 | V6: 1814616.4 | W6: 1804311.1 | X6: 1800852 | Y6: 1822320.9 | Z6: 1796606.7 | AA6: 1797455.7 | AB6: 1800622.7
A7: 6001.03.01.01 | B7: 项目物业服务费款 | C7: 19832559 | D7: 1426823.4 | E7: 1586944.2 | F7: 1955759 | G7: 1304737.1 | H7: 1480012.9 | I7: 1794315.4 | J7: 1457005.8 | K7: 1479251.6 | L7: 1733573 | M7: 1393976.3 | N7: 1725344.9 | O7: 2494815.9 | P7: 18684673 | Q7: 1557056.1 | R7: 1557056.1 | S7: 1557056.1 | T7: 1557056.1 | U7: 1557056.1 | V7: 1557056.1 | W7: 1557056.1 | X7: 1557056.1 | Y7: 1557056.1 | Z7: 1557056.1 | AA7: 1557056.1 | AB7: 1557056.1
A8: 6001.03.01.02 | B8: 车位服务费收入 | C8: 32802.76 | D8: 5045.87 | E8: 3633.03 | F8: 4403.67 | G8: 1559.63 | H8: 3853.21 | I8: 6233.94 | J8: 4311.93 | K8: 1834.87 | L8: 1009.18 | M8: 917.43 | N8: 0 | O8: 0 | P8: 0 | Q8: 0 | R8: 0 | S8: 0 | T8: 0 | U8: 0 | V8: 0 | W8: 0 | X8: 0 | Y8: 0 | Z8: 0 | AA8: 0 | AB8: 0
A9: 6001.03.01.03 | B9: 车位租赁费收入 | C9: 530723.93 | D9: 34760.09 | E9: 35251.37 | F9: 62060.64 | G9: 36752.75 | H9: 34180.73 | I9: 65300.93 | J9: 35175.68 | K9: 40969.26 | L9: 61222.02 | M9: 31914.22 | N9: 31914.22 | O9: 61222.02 | P9: 548917.43 | Q9: 45743.119 | R9: 45743.119 | S9: 45743.119 | T9: 45743.119 | U9: 45743.119 | V9: 45743.119 | W9: 45743.119 | X9: 45743.119 | Y9: 45743.119 | Z9: 45743.119 | AA9: 45743.119 | AB9: 45743.119
A10: 6001.03.01.04 | B10: 公共资源经营收益 | C10: -26702.69 | D10: 5501.17 | E10: 5501.17 | F10: 5828.06 | G10: 5828.06 | H10: -87613.4 | I10: 1503.63 | J10: 11478.64 | K10: 1958.4 | L10: 2142.72 | M10: 21168.86 | N10: 0 | O10: 0 | P10: 77133.44 | Q10: 0 | R10: 849.06 | S10: 14613.55 | T10: 1415.09 | U10: 1132.08 | V10: 18009.77 | W10: 0 | X10: 4245.29 | Y10: 18009.77 | Z10: 0 | AA10: 849.06 | AB10: 18009.77
A11: 6001.03.01.05 | B11: 设备设施使用费收入 | C11: 0 | P11: 0
A12: 6001.03.01.06 | B12: 项目酬金收入 | C12: 0 | P12: 0
A13: 6001.03.01.07 | B13: 代销能源收入 | C13: 0 | D13: 0 | E13: 0 | F13: 0 | G13: 0 | H13: 0 | I13: 0 | J13: 0 | K13: 0 | L13: 0 | M13: 0 | N13: 0 | O13: 0 | P13: 0 | Q13: 0 | R13: 0 | S13: 0 | T13: 0 | U13: 0 | V13: 0 | W13: 0 | X13: 0 | Y13: 0 | Z13: 0 | AA13: 0 | AB13: 0
A14: 6001.03.01.07.01 | B14: 供水收入 | C14: 0 | P14: 0
A15: 6001.03.01.07.02 | B15: 供电收入 | C15: 0 | P15: 0
A16: 6001.03.01.07.03 | B16: 暖气收入 | C16: 0 | P16: 0
A17: 6001.03.01.07.04 | B17: 燃气收入 | C17: 0 | P17: 0
A18: 6001.03.01.07.99 | B18: 其他代销能源收入 | C18: 0 | P18: 0
A19: 6001.03.01.99 | B19: 其他物业服务收入 | C19: 1188840.9 | D19: 98734.01 | E19: 120238.31 | F19: 87626.95 | G19: 135874.3 | H19: 43111.18 | I19: 125751.68 | J19: 81376.44 | K19: 162204.02 | L19: 217210.26 | M19: 116713.75 | P19: 2263425.5 | Q19: 179813.76 | R19: 172109.36 | S19: 179813.76 | T19: 172109.36 | U19: 201511.88 | V19: 193807.47 | W19: 201511.88 | X19: 193807.47 | Y19: 201511.88 | Z19: 193807.47 | AA19: 193807.47 | AB19: 179813.76
A20: 6001.03.02 | B20: 前期物业服务 | C20: 0 | D20: 0 | E20: 0 | F20: 0 | G20: 0 | H20: 0 | I20: 0 | J20: 0 | K20: 0 | L20: 0 | M20: 0 | N20: 0 | O20: 0 | P20: 0 | Q20: 0 | R20: 0 | S20: 0 | T20: 0 | U20: 0 | V20: 0 | W20: 0 | X20: 0 | Y20: 0 | Z20: 0 | AA20: 0 | AB20: 0
A21: 6001.03.02.01 | B21: 项目案场服务收入 | C21: 0 | P21: 0 | Q21: 0 | R21: 0 | S21: 0 | T21: 0 | U21: 0 | V21: 0 | W21: 0 | X21: 0 | Y21: 0 | Z21: 0 | AA21: 0 | AB21: 0
A22: 6001.03.02.02 | B22: 开办费收入 | C22: 0 | P22: 0 | Q22: 0 | R22: 0 | S22: 0 | T22: 0 | U22: 0 | V22: 0 | W22: 0 | X22: 0 | Y22: 0 | Z22: 0 | AA22: 0 | AB22: 0
A23: 6001.03.02.99 | B23: 其他前期物业服务收入 | C23: 0 | P23: 0 | Q23: 0 | R23: 0 | S23: 0 | T23: 0 | U23: 0 | V23: 0 | W23: 0 | X23: 0 | Y23: 0 | Z23: 0 | AA23: 0 | AB23: 0
A24: 6001.03.03 | B24: 社区商业 | C24: 0 | D24: 0 | E24: 0 | F24: 0 | G24: 0 | H24: 0 | I24: 0 | J24: 0 | K24: 0 | L24: 0 | M24: 0 | N24: 0 | O24: 0 | P24: 0 | Q24: 0 | R24: 0 | S24: 0 | T24: 0 | U24: 0 | V24: 0 | W24: 0 | X24: 0 | Y24: 0 | Z24: 0 | AA24: 0 | AB24: 0
A25: 6001.03.03.01 | B25: 自营商品销售收入 | C25: 0 | P25: 0 | Q25: 0 | R25: 0 | S25: 0 | T25: 0 | U25: 0 | V25: 0 | W25: 0 | X25: 0 | Y25: 0 | Z25: 0 | AA25: 0 | AB25: 0
A26: 6001.03.03.02 | B26: 自营生活服务收入 | C26: 0 | P26: 0 | Q26: 0 | R26: 0 | S26: 0 | T26: 0 | U26: 0 | V26: 0 | W26: 0 | X26: 0 | Y26: 0 | Z26: 0 | AA26: 0 | AB26: 0
A27: 6001.03.03.03 | B27: 平台佣金收入 | C27: 0 | P27: 0 | Q27: 0 | R27: 0 | S27: 0 | T27: 0 | U27: 0 | V27: 0 | W27: 0 | X27: 0 | Y27: 0 | Z27: 0 | AA27: 0 | AB27: 0
A28: 6001.03.04 | B28: 房屋配套升级款 | C28: 0 | D28: 0 | E28: 0 | F28: 0 | G28: 0 | H28: 0 | I28: 0 | J28: 0 | K28: 0 | L28: 0 | M28: 0 | N28: 0 | O28: 0 | P28: 0 | Q28: 0 | R28: 0 | S28: 0 | T28: 0 | U28: 0 | V28: 0 | W28: 0 | X28: 0 | Y28: 0 | Z28: 0 | AA28: 0 | AB28: 0
A29: 6001.03.04.01 | B29: 自营业务收入 | C29: 0 | P29: 0 | Q29: 0 | R29: 0 | S29: 0 | T29: 0 | U29: 0 | V29: 0 | W29: 0 | X29: 0 | Y29: 0 | Z29: 0 | AA29: 0 | AB29: 0
A30: 6001.03.04.02 | B30: 平台佣金收入 | C30: 0 | P30: 0 | Q30: 0 | R30: 0 | S30: 0 | T30: 0 | U30: 0 | V30: 0 | W30: 0 | X30: 0 | Y30: 0 | Z30: 0 | AA30: 0 | AB30: 0
A31: 6001.03.05 | B31: 房屋增值维修款 | C31: 0 | D31: 0 | E31: 0 | F31: 0 | G31: 0 | H31: 0 | I31: 0 | J31: 0 | K31: 0 | L31: 0 | M31: 0 | N31: 0 | O31: 0 | P31: 0 | Q31: 0 | R31: 0 | S31: 0 | T31: 0 | U31: 0 | V31: 0 | W31: 0 | X31: 0 | Y31: 0 | Z31: 0 | AA31: 0 | AB31: 0
A32: 6001.03.05.01 | B32: 自营维修业务收入 | C32: 0 | P32: 0 | Q32: 0 | R32: 0 | S32: 0 | T32: 0 | U32: 0 | V32: 0 | W32: 0 | X32: 0 | Y32: 0 | Z32: 0 | AA32: 0 | AB32: 0
A33: 6001.03.05.02 | B33: 联营维修业务收入 | C33: 0 | P33: 0 | Q33: 0 | R33: 0 | S33: 0 | T33: 0 | U33: 0 | V33: 0 | W33: 0 | X33: 0 | Y33: 0 | Z33: 0 | AA33: 0 | AB33: 0
A34: 6001.03.06 | B34: 城市物业服务 | C34: 0 | D34: 0 | E34: 0 | F34: 0 | G34: 0 | H34: 0 | I34: 0 | J34: 0 | K34: 0 | L34: 0 | M34: 0 | N34: 0 | O34: 0 | P34: 0 | Q34: 0 | R34: 0 | S34: 0 | T34: 0 | U34: 0 | V34: 0 | W34: 0 | X34: 0 | Y34: 0 | Z34: 0 | AA34: 0 | AB34: 0
A35: 6001.03.06.01 | B35: 保洁服务收入 | C35: 0 | P35: 0
A36: 6001.03.06.02 | B36: 环卫服务收入 | C36: 0 | P36: 0
A37: 6001.03.06.03 | B37: 其他城市服务收入 | C37: 0 | P37: 0
A38: 6001.03.07 | B38: 家政服务 | C38: 0 | D38: 0 | E38: 0 | F38: 0 | G38: 0 | H38: 0 | I38: 0 | J38: 0 | K38: 0 | L38: 0 | M38: 0 | N38: 0 | O38: 0 | P38: 0 | Q38: 0 | R38: 0 | S38: 0 | T38: 0 | U38: 0 | V38: 0 | W38: 0 | X38: 0 | Y38: 0 | Z38: 0 | AA38: 0 | AB38: 0
A39: 6001.03.07.01 | B39: 保洁服务收入 | C39: 0 | P39: 0
A40: 6001.03.07.02 | B40: 洗衣服务收入 | C40: 0 | P40: 0
A41: 6001.03.07.03 | B41: 车辆养护收入 | C41: 0 | P41: 0
A42: 6001.03.07.99 | B42: 其他服务收入 | C42: 0 | P42: 0
A43: 6001.03.08 | B43: 餐饮业务 | C43: 0 | D43: 0 | E43: 0 | F43: 0 | G43: 0 | H43: 0 | I43: 0 | J43: 0 | K43: 0 | L43: 0 | M43: 0 | N43: 0 | O43: 0 | P43: 0 | Q43: 0 | R43: 0 | S43: 0 | T43: 0 | U43: 0 | V43: 0 | W43: 0 | X43: 0 | Y43: 0 | Z43: 0 | AA43: 0 | AB43: 0
A44: 6001.03.08.01 | B44: 服务收入 | C44: 0 | P44: 0
A45: 6001.03.08.02 | B45: 商品收入 | C45: 0 | P45: 0
A46: 6001.1 | B46: 咨询服务业务收入 | C46: 0 | D46: 0 | E46: 0 | F46: 0 | G46: 0 | H46: 0 | I46: 0 | J46: 0 | K46: 0 | L46: 0 | M46: 0 | N46: 0 | O46: 0 | P46: 0 | Q46: 0 | R46: 0 | S46: 0 | T46: 0 | U46: 0 | V46: 0 | W46: 0 | X46: 0 | Y46: 0 | Z46: 0 | AA46: 0 | AB46: 0
A47: 6001.10.05 | B47: 物业管理咨询收入 | C47: 0 | P47: 0 | Q47: 0 | R47: 0 | S47: 0 | T47: 0 | U47: 0 | V47: 0 | W47: 0 | X47: 0 | Y47: 0 | Z47: 0 | AA47: 0 | AB47: 0
A48: 6001.10.08 | B48: IT智能化服务收入 | C48: 0 | D48: 0 | E48: 0 | F48: 0 | G48: 0 | H48: 0 | I48: 0 | J48: 0 | K48: 0 | L48: 0 | M48: 0 | N48: 0 | O48: 0 | P48: 0 | Q48: 0 | R48: 0 | S48: 0 | T48: 0 | U48: 0 | V48: 0 | W48: 0 | X48: 0 | Y48: 0 | Z48: 0 | AA48: 0 | AB48: 0
A49: 6001.10.08.01 | B49: IT智能化产品销售收入 | C49: 0 | P49: 0
A50: 6001.10.08.02 | B50: IT智能化产品使用费收入 | C50: 0 | P50: 0
A51: 6001.10.99 | B51: 其他咨询服务收入 | C51: 0 | P51: 0 | Q51: 0 | R51: 0 | S51: 0 | T51: 0 | U51: 0 | V51: 0 | W51: 0 | X51: 0 | Y51: 0 | Z51: 0 | AA51: 0 | AB51: 0
A52: 6001.13 | B52: 建安工程（不含装修）业务收入 | C52: 0 | D52: 0 | E52: 0 | F52: 0 | G52: 0 | H52: 0 | I52: 0 | J52: 0 | K52: 0 | L52: 0 | M52: 0 | N52: 0 | O52: 0 | P52: 0 | Q52: 0 | R52: 0 | S52: 0 | T52: 0 | U52: 0 | V52: 0 | W52: 0 | X52: 0 | Y52: 0 | Z52: 0 | AA52: 0 | AB52: 0
A53: 6001.13.01 | B53: 建安收入 | C53: 0 | D53: 0 | E53: 0 | F53: 0 | G53: 0 | H53: 0 | I53: 0 | J53: 0 | K53: 0 | L53: 0 | M53: 0 | N53: 0 | O53: 0 | P53: 0 | Q53: 0 | R53: 0 | S53: 0 | T53: 0 | U53: 0 | V53: 0 | W53: 0 | X53: 0 | Y53: 0 | Z53: 0 | AA53: 0 | AB53: 0
A54: 6001.13.01.01 | B54: 智能化工程收入 | C54: 0 | P54: 0
A55: 6001.13.01.01.01 | B55: 工程施工收入 | C55: 0 | P55: 0
A56: 6001.13.01.01.02 | B56: 设备销售收入 | C56: 0 | P56: 0
A57: 6001.13.01.99 | B57: 其他工程收入 | C57: 0 | P57: 0
A58: 6001.13.02 | B58: 设备维保收入 | C58: 0 | D58: 0 | E58: 0 | F58: 0 | G58: 0 | H58: 0 | I58: 0 | J58: 0 | K58: 0 | L58: 0 | M58: 0 | N58: 0 | O58: 0 | P58: 0 | Q58: 0 | R58: 0 | S58: 0 | T58: 0 | U58: 0 | V58: 0 | W58: 0 | X58: 0 | Y58: 0 | Z58: 0 | AA58: 0 | AB58: 0
A59: 6001.13.02.01 | B59: 设备收入 | C59: 0 | P59: 0
A60: 6001.13.02.02 | B60: 电梯收入 | C60: 0 | P60: 0
A61: 6001.13.03 | B61: 设计监理收入 | C61: 0 | P61: 0
A62: 6001.13.04 | B62: 设备运维收入 | C62: 0 | P62: 0
A63: 6001.14 | B63: 房屋中介业务收入 | C63: 0 | D63: 0 | E63: 0 | F63: 0 | G63: 0 | H63: 0 | I63: 0 | J63: 0 | K63: 0 | L63: 0 | M63: 0 | N63: 0 | O63: 0 | P63: 0 | Q63: 0 | R63: 0 | S63: 0 | T63: 0 | U63: 0 | V63: 0 | W63: 0 | X63: 0 | Y63: 0 | Z63: 0 | AA63: 0 | AB63: 0
A64: 6001.14.01 | B64: 开发商销售佣金收入 | C64: 0 | P64: 0
A65: 6001.14.02 | B65: 开发商租赁佣金收入 | C65: 0 | P65: 0
A66: 6001.14.03 | B66: 二手销售佣金收入 | C66: 0 | P66: 0
A67: 6001.14.04 | B67: 二手租赁佣金收入 | C67: 0 | P67: 0
A68: 6001.54 | B68: 保险经纪业务收入 | C68: 0 | D68: 0 | E68: 0 | F68: 0 | G68: 0 | H68: 0 | I68: 0 | J68: 0 | K68: 0 | L68: 0 | M68: 0 | N68: 0 | O68: 0 | P68: 0 | Q68: 0 | R68: 0 | S68: 0 | T68: 0 | U68: 0 | V68: 0 | W68: 0 | X68: 0 | Y68: 0 | Z68: 0 | AA68: 0 | AB68: 0
A69: 6001.54.01 | B69: 保险代理佣金收入 | C69: 0 | P69: 0
A70: 6001.54.02 | B70: 保险经纪佣金收入 | C70: 0 | P70: 0
A71: 6001.54.03 | B71: 保险咨询费收入 | C71: 0 | P71: 0
A72: 6001.54.99 | B72: 其他保险经纪业务收入 | C72: 0 | P72: 0
A73: 6051 | B73: 其他业务收入 | C73: 0 | P73: 0
A74: 6400 | B74: （二）营业成本 | C74: 11690933 | D74: 448535.49 | E74: 1581000.4 | F74: 770818.17 | G74: 984500.57 | H74: 908781.18 | I74: 1036527.8 | J74: 928190.14 | K74: 1053268.2 | L74: 968170.7 | M74: 967448.89 | N74: 1036974.8 | O74: 1006716.8 | P74: 12355034 | Q74: 1136002.6 | R74: 887706.46 | S74: 1096288 | T74: 922806.07 | U74: 923978.62 | V74: 1217987.6 | W74: 939635.16 | X74: 1109473.6 | Y74: 1126853.8 | Z74: 954606.39 | AA74: 960340.19 | AB74: 1079355.9
A75: 6401 | B75: 主营业务成本 | C75: 11690933 | D75: 448535.49 | E75: 1581000.4 | F75: 770818.17 | G75: 984500.57 | H75: 908781.18 | I75: 1036527.8 | J75: 928190.14 | K75: 1053268.2 | L75: 968170.7 | M75: 967448.89 | N75: 1036974.8 | O75: 1006716.8 | P75: 12355034 | Q75: 1136002.6 | R75: 887706.46 | S75: 1096288 | T75: 922806.07 | U75: 923978.62 | V75: 1217987.6 | W75: 939635.16 | X75: 1109473.6 | Y75: 1126853.8 | Z75: 954606.39 | AA75: 960340.19 | AB75: 1079355.9
A76: 6401.03 | B76: 物业管理业务成本 | C76: 11690933 | D76: 448535.49 | E76: 1581000.4 | F76: 770818.17 | G76: 984500.57 | H76: 908781.18 | I76: 1036527.8 | J76: 928190.14 | K76: 1053268.2 | L76: 968170.7 | M76: 967448.89 | N76: 1036974.8 | O76: 1006716.8 | P76: 12355034 | Q76: 1136002.6 | R76: 887706.46 | S76: 1096288 | T76: 922806.07 | U76: 923978.62 | V76: 1217987.6 | W76: 939635.16 | X76: 1109473.6 | Y76: 1126853.8 | Z76: 954606.39 | AA76: 960340.19 | AB76: 1079355.9
A77: 6401.03.01 | B77: 材料费用 | C77: 323435.27 | D77: 18806.1 | E77: 24739.89 | F77: -8850.13 | G77: 47906.51 | H77: 0 | I77: 37588.86 | J77: 788.5 | K77: 640.6 | L77: 5274.52 | M77: 86540.42 | N77: 60000 | O77: 50000 | P77: 353585.77 | Q77: 42419.611 | R77: 25191.292 | S77: 26961.204 | T77: 26961.204 | U77: 51739.965 | V77: 25191.292 | W77: 29164.743 | X77: 25191.292 | Y77: 25191.292 | Z77: 25191.292 | AA77: 25191.292 | AB77: 25191.292
A78: 6401.03.02 | B78: 外包费用 | C78: 2414879.8 | D78: 216824.9 | E78: 203396.64 | F78: 59481.18 | G78: 159100.27 | H78: 267652.58 | I78: 267837 | J78: 178832.07 | K78: 237023.83 | L78: 227499.02 | M78: 150440.99 | N78: 223395.66 | O78: 223395.66 | P78: 2470893.8 | Q78: 124078.9 | R78: 121628.9 | S78: 314872.29 | T78: 139077.76 | U78: 124983.61 | V78: 388631.73 | W78: 122228.9 | X78: 279190.51 | Y78: 298981.73 | Z78: 121628.9 | AA78: 122228.9 | AB78: 313361.73
A79: 6401.03.02.01 | B79: 保洁外包 | C79: 1089427.1 | D79: 55043.64 | E79: 96258.21 | F79: 18094.31 | G79: 74681.11 | H79: 149282.12 | I79: 59520.86 | J79: 94965.38 | K79: 116705.41 | L79: 127394.14 | M79: 42693.62 | N79: 127394.14 | O79: 127394.14 | P79: 1255991.3 | Q79: 104150.94 | R79: 104150.94 | S79: 104150.94 | T79: 104150.94 | U79: 104150.94 | V79: 107150.94 | W79: 104150.94 | X79: 104150.94 | Y79: 104150.94 | Z79: 104150.94 | AA79: 104150.94 | AB79: 107330.94
A80: 6401.03.02.02 | B80: 安全外包 | C80: 0 | D80: 0 | E80: 0 | F80: 0 | G80: 0 | H80: 0 | I80: 0 | J80: 0 | K80: 0 | L80: 0 | M80: 0 | P80: 0 | Q80: 0 | R80: 0 | S80: 0 | T80: 0 | U80: 0 | V80: 0 | W80: 0 | X80: 0 | Y80: 0 | Z80: 0 | AA80: 0 | AB80: 0
A81: 6401.03.02.03 | B81: 绿化外包 | C81: 138296.78 | D81: 11207.55 | E81: 19933.76 | F81: 10807.55 | G81: 10690.57 | H81: 10807.55 | I81: 10430.19 | J81: 11090.57 | K81: 11090.57 | L81: 9815.82 | M81: 10807.55 | N81: 10807.55 | O81: 10807.55 | P81: 60000 | Q81: 5000 | R81: 5000 | S81: 5000 | T81: 5000 | U81: 5000 | V81: 5000 | W81: 5000 | X81: 5000 | Y81: 5000 | Z81: 5000 | AA81: 5000 | AB81: 5000
A82: 6401.03.02.04 | B82: 消杀外包 | C82: 21931.04 | D82: 2019.46 | E82: 2019.46 | F82: 0 | G82: 2019.46 | H82: 2019.46 | I82: 1736.44 | J82: 2019.46 | K82: 2019.46 | L82: 2019.46 | M82: 2019.46 | N82: 2019.46 | O82: 2019.46 | P82: 24233.547 | Q82: 2019.4623 | R82: 2019.4623 | S82: 2019.4623 | T82: 2019.4623 | U82: 2019.4623 | V82: 2019.4623 | W82: 2019.4623 | X82: 2019.4623 | Y82: 2019.4623 | Z82: 2019.4623 | AA82: 2019.4623 | AB82: 2019.4623
A83: 6401.03.02.05 | B83: 电梯维保外保 | C83: 445700 | D83: 44672.64 | E83: 44672.64 | F83: -4749.05 | G83: 44672.64 | H83: 44672.64 | I83: 35880.05 | J83: 40206.6 | K83: 40206.6 | L83: 40206.6 | M83: 30872.64 | N83: 42193 | O83: 42193 | P83: 454408.49 | Q83: 0 | R83: 0 | S83: 123464.15 | T83: 1268.8679 | U83: 2754.717 | V83: 108973.58 | W83: 0 | X83: 0 | Y83: 108973.58 | Z83: 0 | AA83: 0 | AB83: 108973.58
A84: 6401.03.02.06 | B84: 设备设施维保外包 | C84: 421766.96 | D84: 97160.88 | E84: 30127.58 | F84: 26799.3 | G84: 24390.17 | H84: 22836.78 | I84: 86589.88 | J84: 16386.99 | K84: 5565.1 | L84: 27977.57 | M84: 27977.57 | N84: 27977.57 | O84: 27977.57 | P84: 355280 | Q84: 3850 | R84: 1400 | S84: 57500 | T84: 17580 | U84: 2000 | V84: 142750 | W84: 2000 | X84: 1400 | Y84: 56100 | Z84: 1400 | AA84: 2000 | AB84: 67300
A85: 6401.03.02.07 | B85: 消防保外包 | C85: 54043.2 | D85: 4559.76 | E85: 4559.75 | F85: 4559.75 | G85: 4113.3 | H85: 4559.75 | I85: 4332.39 | J85: 4559.75 | K85: 4559.75 | L85: 4559.75 | M85: 4559.75 | N85: 4559.75 | O85: 4559.75 | P85: 54716.981 | Q85: 0 | R85: 0 | S85: 13679.245 | T85: 0 | U85: 0 | V85: 13679.245 | W85: 0 | X85: 0 | Y85: 13679.245 | Z85: 0 | AA85: 0 | AB85: 13679.245
A86: 6401.03.02.08 | B86: 装修垃圾清运外包 | C86: 0 | D86: 0 | E86: 0 | F86: 0 | G86: 0 | H86: 0 | I86: 0 | J86: 0 | K86: 0 | L86: 0 | M86: 0 | P86: 0 | Q86: 0 | R86: 0 | S86: 0 | T86: 0 | U86: 0 | V86: 0 | W86: 0 | X86: 0 | Y86: 0 | Z86: 0 | AA86: 0 | AB86: 0
A87: 6401.03.02.09 | B87: 生活垃圾清运外包 | C87: 24304.887 | D87: 2160.97 | E87: 5825.24 | F87: 3969.32 | G87: -1466.98 | H87: 2160.97 | I87: -4649.56 | J87: 4562.5 | K87: 2135.85 | L87: 2047.45 | M87: 1898.75 | N87: 2830.1887 | O87: 2830.1887 | P87: 28301.887 | Q87: 2358.4906 | R87: 2358.4906 | S87: 2358.4906 | T87: 2358.4906 | U87: 2358.4906 | V87: 2358.4906 | W87: 2358.4906 | X87: 2358.4906 | Y87: 2358.4906 | Z87: 2358.4906 | AA87: 2358.4906 | AB87: 2358.4906
A88: 6401.03.02.10 | B88: 工程施工外包 | C88: 152032.2 | D88: 0 | E88: 0 | F88: 0 | G88: 0 | H88: 0 | I88: 73996.75 | J88: 3908.26 | K88: 54741.09 | L88: 9284.83 | M88: 10101.27 | P88: 30000 | Q88: 2500 | R88: 2500 | S88: 2500 | T88: 2500 | U88: 2500 | V88: 2500 | W88: 2500 | X88: 2500 | Y88: 2500 | Z88: 2500 | AA88: 2500 | AB88: 2500
A89: 6401.03.02.11 | B89: 人事外包费 | C89: 0 | D89: 0 | E89: 0 | F89: 0 | G89: 0 | H89: 0 | I89: 0 | J89: 0 | K89: 0 | L89: 0 | M89: 0 | P89: 0 | Q89: 0 | R89: 0 | S89: 0 | T89: 0 | U89: 0 | V89: 0 | W89: 0 | X89: 0 | Y89: 0 | Z89: 0 | AA89: 0 | AB89: 0
A90: 6401.03.02.12 | B90: 财务外包费 | C90: 0 | D90: 0 | E90: 0 | F90: 0 | G90: 0 | H90: 0 | I90: 0 | J90: 0 | K90: 0 | L90: 0 | M90: 0 | P90: 0
A91: 6401.03.02.13 | B91: IT外包费 | C91: 0 | D91: 0 | E91: 0 | F91: 0 | G91: 0 | H91: 0 | I91: 0 | J91: 0 | K91: 0 | L91: 0 | M91: 0 | P91: 0
A92: 6401.03.02.14 | B92: 餐饮外包费 | C92: 0 | D92: 0 | E92: 0 | F92: 0 | G92: 0 | H92: 0 | I92: 0 | J92: 0 | K92: 0 | L92: 0 | M92: 0 | P92: 0
A93: 6401.03.02.99 | B93: 其他外包费 | C93: 67377.65 | D93: 0 | E93: 0 | F93: 0 | G93: 0 | H93: 31313.31 | I93: 0 | J93: 1132.56 | K93: 0 | L93: 4193.4 | M93: 19510.38 | N93: 5614 | O93: 5614 | P93: 207961.61 | Q93: 4200 | R93: 4200 | S93: 4200 | T93: 4200 | U93: 4200 | V93: 4200 | W93: 4200 | X93: 161761.61 | Y93: 4200 | Z93: 4200 | AA93: 4200 | AB93: 4200
A94: 6401.03.03 | B94: 社区文化及业委会费 | C94: 42123.2 | D94: -23800 | E94: 0 | F94: 30923.2 | G94: 5000 | H94: 0 | I94: 0 | J94: 0 | K94: 0 | L94: 0 | M94: 0 | N94: 30000 | P94: 65000 | Q94: 30000 | R94: 0 | S94: 0 | T94: 0 | U94: 0 | V94: 0 | W94: 0 | X94: 5000 | Y94: 0 | Z94: 0 | AA94: 30000 | AB94: 0
A95: 6401.03.04 | B95: 酬金成本 | C95: 0 | D95: 0 | E95: 0 | F95: 0 | G95: 0 | H95: 0 | I95: 0 | J95: 0 | K95: 0 | L95: 0 | M95: 0 | P95: 0
A96: 6401.03.05 | B96: 商品销售成本 | C96: 0 | D96: 0 | E96: 0 | F96: 0 | G96: 0 | H96: 0 | I96: 0 | J96: 0 | K96: 0 | L96: 0 | M96: 0 | P96: 0 | Q96: 0 | R96: 0 | S96: 0 | T96: 0 | U96: 0 | V96: 0 | W96: 0 | X96: 0 | Y96: 0 | Z96: 0 | AA96: 0 | AB96: 0
A97: 6401.03.06 | B97: 餐饮业务成本 | C97: 0 | D97: 0 | E97: 0 | F97: 0 | G97: 0 | H97: 0 | I97: 0 | J97: 0 | K97: 0 | L97: 0 | M97: 0 | P97: 0
A98: 6401.03.07 | B98: 业务支持费 | C98: 0 | P98: 0
A99: 6401.03.80 | B99: 能源成本类 | C99: 2108879.2 | D99: 107847.23 | E99: 157162.32 | F99: 134654.26 | G99: 58205.16 | H99: 152854.37 | I99: 159212.93 | J99: 205808.57 | K99: 261877.39 | L99: 260062.3 | M99: 227239.96 | N99: 210056.34 | O99: 173898.34 | P99: 2119032.3 | Q99: 101616.04 | R99: 155244.67 | S99: 143362.87 | T99: 168218.84 | U99: 152965.79 | V99: 212645.46 | W99: 199297.43 | X99: 209542.71 | Y99: 211661.73 | Z99: 218342.1 | AA99: 196850.91 | AB99: 149283.77
A100: 6401.03.80.01 | B100: 水费 | C100: 106609.15 | D100: 6687.07 | E100: 7627.82 | F100: 2650.28 | G100: 7218.32 | H100: 6318.59 | I100: 8394.46 | J100: 10912.8 | K100: 12781.01 | L100: 13849.78 | M100: 10056.34 | N100: 10056.34 | O100: 10056.34 | P100: 115035.3 | Q100: 7660.3204 | R100: 8124.2893 | S100: 5103.6583 | T100: 8153.2874 | U100: 7684.4854 | V100: 9786.8447 | W100: 11439.734 | X100: 13227.948 | Y100: 13387.437 | Z100: 10129.988 | AA100: 10753.447 | AB100: 9583.8583
...

Sheet 自有人工预算（附表）
A1: Kingdee | B1: JDC001-7.1 | C1: 自有人工预算
B2: 组织 | C2: WY.FW.01.10.02 | D2: 深圳市金地物业服务有限公司-深圳金地中心
B3: 版本 | C3: VNone | D3: 不区分版本
B4: 预算期间 | C4: 2025年
B5: 填报单位名称 | C5: 深圳金地中心
B7: 01.人数信息
B8: 岗位 | C8: 人力维度 | D8: 2025年预算 | E8: 1月预算 | F8: 2月预算 | G8: 3月预算 | H8: 4月预算 | I8: 5月预算 | J8: 6月预算 | K8: 7月预算 | L8: 8月预算 | M8: 9月预算 | N8: 10月预算 | O8: 11月预算 | P8: 12月预算
B9: 管理及专业序列 | C9: 非技能 | D9: 0 | E9: 12 | F9: 12 | G9: 12 | H9: 12 | I9: 12 | J9: 12 | K9: 12 | L9: 12 | M9: 12 | N9: 12 | O9: 12 | P9: 12
B10: 工程 | C10: 工程管理 | D10: 0 | E10: 11 | F10: 11 | G10: 11 | H10: 11 | I10: 11 | J10: 11 | K10: 11 | L10: 11 | M10: 11 | N10: 11 | O10: 11 | P10: 11
B11: 安全 | C11: 安全管理 | D11: 0 | E11: 15 | F11: 15 | G11: 15 | H11: 15 | I11: 15 | J11: 15 | K11: 15 | L11: 15 | M11: 15 | N11: 15 | O11: 15 | P11: 15
B12: 环境 | C12: 环境管理 | D12: 0 | E12: 7 | F12: 7 | G12: 7 | H12: 7 | I12: 7 | J12: 7 | K12: 7 | L12: 7 | M12: 7 | N12: 7 | O12: 7 | P12: 7
B13: 客服 | C13: 客服管理 | D13: 0 | E13: 13 | F13: 13 | G13: 13 | H13: 13 | I13: 13 | J13: 13 | K13: 13 | L13: 13 | M13: 13 | N13: 13 | O13: 13 | P13: 13
B14: 其他 | C14: 项目其他 | D14: 0 | E14: 5 | F14: 5 | G14: 5 | H14: 5 | I14: 5 | J14: 5 | K14: 5 | L14: 5 | M14: 5 | N14: 5 | O14: 5 | P14: 5
B15: 片总 | C15: 片总 | D15: 0
B16: 运营经理 | C16: 运营经理 | D16: 0
B17: 人力BP | C17: 人力BP | D17: 0
B18: 财务BP | C18: 财务BP | D18: 0
B19: 其他 | C19: 其他 | D19: 0
B20: 汇总 | D20: 0 | E20: 0 | F20: 0 | G20: 0 | H20: 0 | I20: 0 | J20: 0 | K20: 0 | L20: 0 | M20: 0 | N20: 0 | O20: 0 | P20: 0
B22: 02.人工总成本
B23: 岗位 | C23: 人力维度 | D23: 2025年预算 | E23: 1月预算 | F23: 2月预算 | G23: 3月预算 | H23: 4月预算 | I23: 5月预算 | J23: 6月预算 | K23: 7月预算 | L23: 8月预算 | M23: 9月预算 | N23: 10月预算 | O23: 11月预算 | P23: 12月预算
B24: 管理及专业序列 | C24: 非技能 | D24: 1683714.7 | E24: 189457.56 | F24: 135841.56 | G24: 135841.56 | H24: 135841.56 | I24: 135841.56 | J24: 135841.56 | K24: 135841.56 | L24: 135841.56 | M24: 135841.56 | N24: 135841.56 | O24: 135841.56 | P24: 135841.56
B25: 工程 | C25: 工程管理 | D25: 1108729.6 | E25: 94713.3 | F25: =92183.3+91800/11 -> 100528.75 | G25: =92183.3+91800/11 -> 100528.75 | H25: =92183.3+91800/11 -> 100528.75 | I25: =92183.3+91800/11 -> 100528.75 | J25: =92183.3+91800/11 -> 100528.75 | K25: =92183.3+91800/11 -> 100528.75 | L25: =92183.3+91800/11 -> 100528.75 | M25: =92183.3+91800/11 -> 100528.75 | ... P25: =92183.3+91800/11 -> 100528.75
B26: 安全 | C26: 安全管理 | D26: 1715797.4 | E26: 197789.17 | F26: 138000.75 | G26: 138000.75 | H26: 138000.75 | I26: 138000.75 | J26: 138000.75 | K26: 138000.75 | L26: 138000.75 | M26: 138000.75 | N26: 138000.75 | O26: 138000.75 | P26: 138000.75
B27: 环境 | C27: 环境管理 | D27: 449941.52 | E27: 38970.96 | F27: 37360.96 | G27: 37360.96 | H27: 37360.96 | I27: 37360.96 | J27: 37360.96 | K27: 37360.96 | L27: 37360.96 | M27: 37360.96 | N27: 37360.96 | O27: 37360.96 | P27: 37360.96
B28: 客服 | C28: 客服管理 | D28: 1409128.8 | E28: 120168.23 | F28: 117178.23 | G28: 117178.23 | H28: 117178.23 | I28: 117178.23 | J28: 117178.23 | K28: 117178.23 | L28: 117178.23 | M28: 117178.23 | N28: 117178.23 | O28: 117178.23 | P28: 117178.23
B29: 其他 | C29: 项目其他 | D29: 767300.2 | E29: 64995.85 | F29: 63845.85 | G29: 63845.85 | H29: 63845.85 | I29: 63845.85 | J29: 63845.85 | K29: 63845.85 | L29: 63845.85 | M29: 63845.85 | N29: 63845.85 | O29: 63845.85 | P29: 63845.85
B30: 片总 | C30: 片总 | D30: 0 | E30: 0 | F30: 0 | G30: 0 | H30: 0 | I30: 0 | J30: 0 | K30: 0 | L30: 0 | M30: 0 | N30: 0 | O30: 0 | P30: 0
B31: 运营经理 | C31: 运营经理 | D31: 0 | E31: 0 | F31: 0 | G31: 0 | H31: 0 | I31: 0 | J31: 0 | K31: 0 | L31: 0 | M31: 0 | N31: 0 | O31: 0 | P31: 0
B32: 人力BP | C32: 人力BP | D32: 0 | E32: 0 | F32: 0 | G32: 0 | H32: 0 | I32: 0 | J32: 0 | K32: 0 | L32: 0 | M32: 0 | N32: 0 | O32: 0 | P32: 0
B33: 财务BP | C33: 财务BP | D33: 0 | E33: 0 | F33: 0 | G33: 0 | H33: 0 | I33: 0 | J33: 0 | K33: 0 | L33: 0 | M33: 0 | N33: 0 | O33: 0 | P33: 0
B34: 其他 | C34: 其他 | D34: 0 | E34: 0 | F34: 0 | G34: 0 | H34: 0 | I34: 0 | J34: 0 | K34: 0 | L34: 0 | M34: 0 | N34: 0 | O34: 0 | P34: 0
B35: 汇总 | D35: 7134612.2 | E35: 706095.07 | F35: 584410.65 | G35: 584410.65 | H35: 584410.65 | I35: 584410.65 | J35: 584410.65 | K35: 584410.65 | L35: 584410.65 | M35: 584410.65 | N35: 584410.65 | O35: 584410.65 | P35: 584410.65
B37: 03.工资成本
B38: 岗位 | C38: 人力维度 | D38: 2025年预算 | E38: 1月预算 | F38: 2月预算 | G38: 3月预算 | H38: 4月预算 | I38: 5月预算 | J38: 6月预算 | K38: 7月预算 | L38: 8月预算 | M38: 9月预算 | N38: 10月预算 | O38: 11月预算 | P38: 12月预算
B39: 管理及专业序列 | C39: 非技能 | D39: 1192079.5 | E39: 99339.96 | F39: 99339.96 | G39: 99339.96 | H39: 99339.96 | I39: 99339.96 | J39: 99339.96 | K39: 99339.96 | L39: 99339.96 | M39: 99339.96 | N39: 99339.96 | O39: 99339.96 | P39: 99339.96
B40: 工程 | C40: 工程管理 | D40: 996893.04 | E40: 83074.42 | F40: 83074.42 | G40: 83074.42 | H40: 83074.42 | I40: 83074.42 | J40: 83074.42 | K40: 83074.42 | L40: 83074.42 | M40: 83074.42 | N40: 83074.42 | O40: 83074.42 | P40: 83074.42
B41: 安全 | C41: 安全管理 | D41: 1504595.9 | E41: 125940 | F41: 125332.35 | G41: 125332.35 | H41: 125332.35 | I41: 125332.35 | J41: 125332.35 | K41: 125332.35 | L41: 125332.35 | M41: 125332.35 | N41: 125332.35 | O41: 125332.35 | P41: 125332.35
B42: 环境 | C42: 环境管理 | D42: 390684 | E42: 32557 | F42: 32557 | G42: 32557 | H42: 32557 | I42: 32557 | J42: 32557 | K42: 32557 | L42: 32557 | M42: 32557 | N42: 32557 | O42: 32557 | P42: 32557
B43: 客服 | C43: 客服管理 | D43: 1283797.3 | E43: 106983.11 | F43: 106983.11 | G43: 106983.11 | H43: 106983.11 | I43: 106983.11 | J43: 106983.11 | K43: 106983.11 | L43: 106983.11 | M43: 106983.11 | N43: 106983.11 | O43: 106983.11 | P43: 106983.11
B44: 其他 | C44: 项目其他 | D44: 487650 | E44: 40637.5 | F44: 40637.5 | G44: 40637.5 | H44: 40637.5 | I44: 40637.5 | J44: 40637.5 | K44: 40637.5 | L44: 40637.5 | M44: 40637.5 | N44: 40637.5 | O44: 40637.5 | P44: 40637.5
B45: 片总 | C45: 片总 | D45: 0 | E45: 0 | F45: 0 | G45: 0 | H45: 0 | I45: 0 | J45: 0 | K45: 0 | L45: 0 | M45: 0 | N45: 0 | O45: 0 | P45: 0
B46: 运营经理 | C46: 运营经理 | D46: 0 | E46: 0 | F46: 0 | G46: 0 | H46: 0 | I46: 0 | J46: 0 | K46: 0 | L46: 0 | M46: 0 | N46: 0 | O46: 0 | P46: 0
B47: 人力BP | C47: 人力BP | D47: 0 | E47: 0 | F47: 0 | G47: 0 | H47: 0 | I47: 0 | J47: 0 | K47: 0 | L47: 0 | M47: 0 | N47: 0 | O47: 0 | P47: 0
B48: 财务BP | C48: 财务BP | D48: 0 | E48: 0 | F48: 0 | G48: 0 | H48: 0 | I48: 0 | J48: 0 | K48: 0 | L48: 0 | M48: 0 | N48: 0 | O48: 0 | P48: 0
B49: 其他 | C49: 其他 | D49: 0 | E49: 0 | F49: 0 | G49: 0 | H49: 0 | I49: 0 | J49: 0 | K49: 0 | L49: 0 | M49: 0 | N49: 0 | O49: 0 | P49: 0
B50: 汇总 | D50: 5855699.7 | E50: 488531.99 | F50: 487924.34 | G50: 487924.34 | H50: 487924.34 | I50: 487924.34 | J50: 487924.34 | K50: 487924.34 | L50: 487924.34 | M50: 487924.34 | N50: 487924.34 | O50: 487924.34 | P50: 487924.34
B52: 04.年度绩效
B53: 岗位 | C53: 人力维度 | D53: 2025年预算 | E53: 1月预算 | F53: 2月预算 | G53: 3月预算 | H53: 4月预算 | I53: 5月预算 | J53: 6月预算 | K53: 7月预算 | L53: 8月预算 | M53: 9月预算 | N53: 10月预算 | O53: 11月预算 | P53: 12月预算
B54: 管理及专业序列 | C54: 非技能 | D54: 194544 | E54: 16212 | F54: 16212 | G54: 16212 | H54: 16212 | I54: 16212 | J54: 16212 | K54: 16212 | L54: 16212 | M54: 16212 | N54: 16212 | O54: 16212 | P54: 16212
B55: 工程 | C55: 工程管理 | D55: 0 | E55: 0 | F55: 0 | G55: 0 | H55: 0 | I55: 0 | J55: 0 | K55: 0 | L55: 0 | M55: 0 | N55: 0 | O55: 0 | P55: 0
B56: 安全 | C56: 安全管理 | D56: 0 | E56: 0 | F56: 0 | G56: 0 | H56: 0 | I56: 0 | J56: 0 | K56: 0 | L56: 0 | M56: 0 | N56: 0 | O56: 0 | P56: 0
B57: 环境 | C57: 环境管理 | D57: 0 | E57: 0 | F57: 0 | G57: 0 | H57: 0 | I57: 0 | J57: 0 | K57: 0 | L57: 0 | M57: 0 | N57: 0 | O57: 0 | P57: 0
B58: 客服 | C58: 客服管理 | D58: 0 | E58: 0 | F58: 0 | G58: 0 | H58: 0 | I58: 0 | J58: 0 | K58: 0 | L58: 0 | M58: 0 | N58: 0 | O58: 0 | P58: 0
B59: 其他 | C59: 项目其他 | D59: 0 | E59: 0 | F59: 0 | G59: 0 | H59: 0 | I59: 0 | J59: 0 | K59: 0 | L59: 0 | M59: 0 | N59: 0 | O59: 0 | P59: 0
B60: 片总 | C60: 片总 | D60: 0 | E60: 0 | F60: 0 | G60: 0 | H60: 0 | I60: 0 | J60: 0 | K60: 0 | L60: 0 | M60: 0 | N60: 0 | O60: 0 | P60: 0
B61: 运营经理 | C61: 运营经理 | D61: 0 | E61: 0 | F61: 0 | G61: 0 | H61: 0 | I61: 0 | J61: 0 | K61: 0 | L61: 0 | M61: 0 | N61: 0 | O61: 0 | P61: 0
B62: 人力BP | C62: 人力BP | D62: 0 | E62: 0 | F62: 0 | G62: 0 | H62: 0 | I62: 0 | J62: 0 | K62: 0 | L62: 0 | M62: 0 | N62: 0 | O62: 0 | P62: 0
B63: 财务BP | C63: 财务BP | D63: 0 | E63: 0 | F63: 0 | G63: 0 | H63: 0 | I63: 0 | J63: 0 | K63: 0 | L63: 0 | M63: 0 | N63: 0 | O63: 0 | P63: 0
B64: 其他 | C64: 其他 | D64: 0 | E64: 0 | F64: 0 | G64: 0 | H64: 0 | I64: 0 | J64: 0 | K64: 0 | L64: 0 | M64: 0 | N64: 0 | O64: 0 | P64: 0
B65: 汇总 | D65: 194544 | E65: 16212 | F65: 16212 | G65: 16212 | H65: 16212 | I65: 16212 | J65: 16212 | K65: 16212 | L65: 16212 | M65: 16212 | N65: 16212 | O65: 16212 | P65: 16212
B67: 05.社保
B68: 岗位 | C68: 人力维度 | D68: 2025年预算 | E68: 1月预算 | F68: 2月预算 | G68: 3月预算 | H68: 4月预算 | I68: 5月预算 | J68: 6月预算 | K68: 7月预算 | L68: 8月预算 | M68: 9月预算 | N68: 10月预算 | O68: 11月预算 | P68: 12月预算
B69: 管理及专业序列 | C69: 非技能 | D69: 191792.16 | E69: 15982.68 | F69: 15982.68 | G69: 15982.68 | H69: 15982.68 | I69: 15982.68 | J69: 15982.68 | K69: 15982.68 | L69: 15982.68 | M69: 15982.68 | N69: 15982.68 | O69: 15982.68 | P69: 15982.68
B70: 工程 | C70: 工程管理 | D70: 93730.56 | E70: 7810.88 | F70: 7810.88 | G70: 7810.88 | H70: 7810.88 | I70: 7810.88 | J70: 7810.88 | K70: 7810.88 | L70: 7810.88 | M70: 7810.88 | N70: 7810.88 | O70: 7810.88 | P70: 7810.88
B71: 安全 | C71: 安全管理 | D71: 130780.8 | E71: 10898.4 | F71: 10898.4 | G71: 10898.4 | H71: 10898.4 | I71: 10898.4 | J71: 10898.4 | K71: 10898.4 | L71: 10898.4 | M71: 10898.4 | N71: 10898.4 | O71: 10898.4 | P71: 10898.4
B72: 环境 | C72: 环境管理 | D72: 57647.52 | E72: 4803.96 | F72: 4803.96 | G72: 4803.96 | H72: 4803.96 | I72: 4803.96 | J72: 4803.96 | K72: 4803.96 | L72: 4803.96 | M72: 4803.96 | N72: 4803.96 | O72: 4803.96 | P72: 4803.96
B73: 客服 | C73: 客服管理 | D73: 105248.52 | E73: 8770.71 | F73: 8770.71 | G73: 8770.71 | H73: 8770.71 | I73: 8770.71 | J73: 8770.71 | K73: 8770.71 | L73: 8770.71 | M73: 8770.71 | N73: 8770.71 | O73: 8770.71 | P73: 8770.71
B74: 其他 | C74: 项目其他 | D74: 52960.2 | E74: 4413.35 | F74: 4413.35 | G74: 4413.35 | H74: 4413.35 | I74: 4413.35 | J74: 4413.35 | K74: 4413.35 | L74: 4413.35 | M74: 4413.35 | N74: 4413.35 | O74: 4413.35 | P74: 4413.35
B75: 片总 | C75: 片总 | D75: 0 | E75: 0 | F75: 0 | G75: 0 | H75: 0 | I75: 0 | J75: 0 | K75: 0 | L75: 0 | M75: 0 | N75: 0 | O75: 0 | P75: 0
B76: 运营经理 | C76: 运营经理 | D76: 0 | E76: 0 | F76: 0 | G76: 0 | H76: 0 | I76: 0 | J76: 0 | K76: 0 | L76: 0 | M76: 0 | N76: 0 | O76: 0 | P76: 0
B77: 人力BP | C77: 人力BP | D77: 0 | E77: 0 | F77: 0 | G77: 0 | H77: 0 | I77: 0 | J77: 0 | K77: 0 | L77: 0 | M77: 0 | N77: 0 | O77: 0 | P77: 0
B78: 财务BP | C78: 财务BP | D78: 0 | E78: 0 | F78: 0 | G78: 0 | H78: 0 | I78: 0 | J78: 0 | K78: 0 | L78: 0 | M78: 0 | N78: 0 | O78: 0 | P78: 0
B79: 其他 | C79: 其他 | D79: 0 | E79: 0 | F79: 0 | G79: 0 | H79: 0 | I79: 0 | J79: 0 | K79: 0 | L79: 0 | M79: 0 | N79: 0 | O79: 0 | P79: 0
B80: 汇总 | D80: 632159.76 | E80: 52679.98 | F80: 52679.98 | G80: 52679.98 | H80: 52679.98 | I80: 52679.98 | J80: 52679.98 | K80: 52679.98 | L80: 52679.98 | M80: 52679.98 | N80: 52679.98 | O80: 52679.98 | P80: 52679.98
B82: 06.公积金
B83: 岗位 | C83: 人力维度 | D83: 2025年预算 | E83: 1月预算 | F83: 2月预算 | G83: 3月预算 | H83: 4月预算 | I83: 5月预算 | J83: 6月预算 | K83: 7月预算 | L83: 8月预算 | M83: 9月预算 | N83: 10月预算 | O83: 11月预算 | P83: 12月预算
B84: 管理及专业序列 | C84: 非技能 | D84: 51683.04 | E84: 4306.92 | F84: 4306.92 | G84: 4306.92 | H84: 4306.92 | I84: 4306.92 | J84: 4306.92 | K84: 4306.92 | L84: 4306.92 | M84: 4306.92 | N84: 4306.92 | O84: 4306.92 | P84: 4306.92
B85: 工程 | C85: 工程管理 | D85: 15576 | E85: 1298 | F85: 1298 | G85: 1298 | H85: 1298 | I85: 1298 | J85: 1298 | K85: 1298 | L85: 1298 | M85: 1298 | N85: 1298 | O85: 1298 | P85: 1298
B86: 安全 | C86: 安全管理 | D86: 21240 | E86: 1770 | F86: 1770 | G86: 1770 | H86: 1770 | I86: 1770 | J86: 1770 | K86: 1770 | L86: 1770 | M86: 1770 | N86: 1770 | O86: 1770 | P86: 1770
B87: 环境 | C87: 环境管理 | D87: 0 | E87: 0 | F87: 0 | G87: 0 | H87: 0 | I87: 0 | J87: 0 | K87: 0 | L87: 0 | M87: 0 | N87: 0 | O87: 0 | P87: 0
B88: 客服 | C88: 客服管理 | D88: 17092.92 | E88: 1424.41 | F88: 1424.41 | G88: 1424.41 | H88: 1424.41 | I88: 1424.41 | J88: 1424.41 | K88: 1424.41 | L88: 1424.41 | M88: 1424.41 | N88: 1424.41 | O88: 1424.41 | P88: 1424.41
B89: 其他 | C89: 项目其他 | D89: 7080 | E89: 590 | F89: 590 | G89: 590 | H89: 590 | I89: 590 | J89: 590 | K89: 590 | L89: 590 | M89: 590 | N89: 590 | O89: 590 | P89: 590
B90: 片总 | C90: 片总 | D90: 0 | E90: 0 | F90: 0 | G90: 0 | H90: 0 | I90: 0 | J90: 0 | K90: 0 | L90: 0 | M90: 0 | N90: 0 | O90: 0 | P90: 0
B91: 运营经理 | C91: 运营经理 | D91: 0 | E91: 0 | F91: 0 | G91: 0 | H91: 0 | I91: 0 | J91: 0 | K91: 0 | L91: 0 | M91: 0 | N91: 0 | O91: 0 | P91: 0
B92: 人力BP | C92: 人力BP | D92: 0 | E92: 0 | F92: 0 | G92: 0 | H92: 0 | I92: 0 | J92: 0 | K92: 0 | L92: 0 | M92: 0 | N92: 0 | O92: 0 | P92: 0
B93: 财务BP | C93: 财务BP | D93: 0 | E93: 0 | F93: 0 | G93: 0 | H93: 0 | I93: 0 | J93: 0 | K93: 0 | L93: 0 | M93: 0 | N93: 0 | O93: 0 | P93: 0
B94: 其他 | C94: 其他 | D94: 0 | E94: 0 | F94: 0 | G94: 0 | H94: 0 | I94: 0 | J94: 0 | K94: 0 | L94: 0 | M94: 0 | N94: 0 | O94: 0 | P94: 0
B95: 汇总 | D95: 112671.96 | E95: 9389.33 | F95: 9389.33 | G95: 9389.33 | H95: 9389.33 | I95: 9389.33 | J95: 9389.33 | K95: 9389.33 | L95: 9389.33 | M95: 9389.33 | N95: 9389.33 | O95: 9389.33 | P95: 9389.33
B97: 07.福利费
B98: 岗位 | C98: 人力维度 | D98: 2025年预算 | E98: 1月预算 | F98: 2月预算 | G98: 3月预算 | H98: 4月预算 | I98: 5月预算 | J98: 6月预算 | K98: 7月预算 | L98: 8月预算 | M98: 9月预算 | N98: 10月预算 | O98: 11月预算 | P98: 12月预算
B99: 管理及专业序列 | C99: 非技能 | D99: 53616 | E99: 53616 | F99: 0 | G99: 0 | H99: 0 | I99: 0 | J99: 0 | K99: 0 | L99: 0 | M99: 0 | N99: 0 | O99: 0 | P99: 0
B100: 工程 | C100: 工程管理 | D100: 2530 | E100: 2530 | F100: 0 | G100: 0 | H100: 0 | I100: 0 | J100: 0 | K100: 0 | L100: 0 | M100: 0 | N100: 0 | O100: 0 | P100: 0
B101: 安全 | C101: 安全管理 | D101: 59180.769 | E101: 59180.769 | F101: 0 | G101: 0 | H101: 0 | I101: 0 | J101: 0 | K101: 0 | L101: 0 | M101: 0 | N101: 0 | O101: 0 | P101: 0
B102: 环境 | C102: 环境管理 | D102: 1610 | E102: 1610 | F102: 0 | G102: 0 | H102: 0 | I102: 0 | J102: 0 | K102: 0 | L102: 0 | M102: 0 | N102: 0 | O102: 0 | P102: 0
B103: 客服 | C103: 客服管理 | D103: 2990 | E103: 2990 | F103: 0 | G103: 0 | H103: 0 | I103: 0 | J103: 0 | K103: 0 | L103: 0 | M103: 0 | N103: 0 | O103: 0 | P103: 0
B104: 其他 | C104: 项目其他 | D104: 219610 | E104: 19355 | F104: 18205 | G104: 18205 | H104: 18205 | I104: 18205 | J104: 18205 | K104: 18205 | L104: 18205 | M104: 18205 | N104: 18205 | O104: 18205 | P104: 18205
B105: 片总 | C105: 片总 | D105: 0 | E105: 0 | F105: 0 | G105: 0 | H105: 0 | I105: 0 | J105: 0 | K105: 0 | L105: 0 | M105: 0 | N105: 0 | O105: 0 | P105: 0
B106: 运营经理 | C106: 运营经理 | D106: 0 | E106: 0 | F106: 0 | G106: 0 | H106: 0 | I106: 0 | J106: 0 | K106: 0 | L106: 0 | M106: 0 | N106: 0 | O106: 0 | P106: 0
B107: 人力BP | C107: 人力BP | D107: 0 | E107: 0 | F107: 0 | G107: 0 | H107: 0 | I107: 0 | J107: 0 | K107: 0 | L107: 0 | M107: 0 | N107: 0 | O107: 0 | P107: 0
...

Sheet 1 预算编制表单
A1: 合同维度 | B1: 是否为末级科目 | C1: 基础信息 | H1: 2025年 | O1: 填选发生月份 | AB1: 2025年 | AC1: 2025年 | AF1: 2025年 | AI1: 2025年 | AL1: 2025年 | AO1: 2025年 | AR1: 2025年 | AU1: 2025年 | AX1: 2025年 | BA1: 2025年 | BD1: 2025年 | BG1: 2025年 | BJ1: 2025年
AC2: 1月 | AF2: 2月 | AI2: 3月 | AL2: 4月 | AM2: 4月 | AN2: 4月 | AO2: 5月 | AP2: 5月 | AQ2: 5月 | AR2: 6月 | AS2: 6月 | AT2: 6月 | AU2: 7月 | AV2: 7月 | AW2: 7月 | AX2: 8月 | AY2: 8月 | AZ2: 8月 | BA2: 9月 | BB2: 9月 | BC2: 9月 | BD2: 10月 | BE2: 10月 | BF2: 10月 | BG2: 11月 | BH2: 11月 | BI2: 11月 | BJ2: 12月 | BK2: 12月 | BL2: 12月
C3: 费项编码 | D3: 费项名称 | E3: 指标说明 | F3: 填写说明 | G3: 编制周期& 分摊方式 | H3: 年总计 D=A*B*C | I3: 工程量说明 | J3: 工程量 A | K3: 计量单位 | L3: 单价 B | M3: 计价单位 | N3: 频次 C | O3: 1月 | P3: 2月 | Q3: 3月 | R3: 4月 | S3: 5月 | T3: 6月 | U3: 7月 | V3: 8月 | W3: 9月 | X3: 10月 | Y3: 11月 | Z3: 12月 | AA3: D-E | AB3: 1~12月合计 E | AC3: 总价 c=a*b | AD3: 工程量 a | AE3: 单价 b | AF3: 总价 c=a*b | AG3: 工程量 a | AH3: 单价 b | AI3: 总价 c=a*b | AJ3: 工程量 a | AK3: 单价 b | AL3: 总价 c=a*b | AM3: 工程量 a | AN3: 单价 b | AO3: 总价 c=a*b | AP3: 工程量 a | AQ3: 单价 b | AR3: 总价 c=a*b | AS3: 工程量 a | AT3: 单价 b | AU3: 总价 c=a*b | AV3: 工程量 a | AW3: 单价 b | AX3: 总价 c=a*b | AY3: 工程量 a | AZ3: 单价 b | BA3: 总价 c=a*b | BB3: 工程量 a | BC3: 单价 b | BD3: 总价 c=a*b | BE3: 工程量 a | BF3: 单价 b | BG3: 总价 c=a*b | BH3: 工程量 a | BI3: 单价 b | BJ3: 总价 c=a*b | BK3: 工程量 a | BL3: 单价 b
B4: 否 | C4: 1 | D4: 项目运营成本 | E4: 项目运营成本包含范围为项目，全部人员成本（含片区总及项目自有人员成本、项目团队行政费用等） | H4: =H5+H381+H582+H652+H658+H668 -> 12355034 | AB4: =AB5+AB381+AB582+AB652+AB658+AB668 -> 12355034 | AC4: =AC5+AC381+AC582+AC652+AC658+AC668 -> 1133480.3 | AF4: =AF5+AF381+AF582+AF652+AF658+AF668 -> 1020141.3 | AI4: =AI5+AI381+AI582+AI652+AI658+AI668 -> 1020141.3 | AL4: =AL5+AL381+AL582+AL652+AL658+AL668 -> 1020141.3 | AO4: =AO5+AO381+AO582+AO652+AO658+AO668 -> 1020141.3 | AR4: =AR5+AR381+AR582+AR652+AR658+AR668 -> 1020141.3 | AU4: =AU5+AU381+AU582+AU652+AU658+AU668 -> 1020141.3 | AX4: =AX5+AX381+AX582+AX652+AX658+AX668 -> 1020141.3 | BA4: =BA5+BA381+BA582+BA652+BA658+BA668 -> 1020141.3 | BD4: =BD5+BD381+BD582+BD652+BD658+BD668 -> 1020141.3 | BG4: =BG5+BG381+BG582+BG652+BG658+BG668 -> 1020141.3 | BJ4: =BJ5+BJ381+BJ582+BJ652+BJ658+BJ668 -> 1020141.3
B5: 否 | C5: 1.1 | D5: 服务成本 | H5: =H6+H208+H308 -> 9128362.7 | AB5: =AB6+AB208+AB308 -> 9128362.7 | AC5: =AC6+AC208+AC308 -> 864590.94 | AF5: =AF6+AF208+AF308 -> 751251.98 | AI5: =AI6+AI208+AI308 -> 751251.98 | AL5: =AL6+AL208+AL308 -> 751251.98 | AO5: =AO6+AO208+AO308 -> 751251.98 | AR5: =AR6+AR208+AR308 -> 751251.98 | AU5: =AU6+AU208+AU308 -> 751251.98 | AX5: =AX6+AX208+AX308 -> 751251.98 | BA5: =BA6+BA208+BA308 -> 751251.98 | BD5: =BD6+BD208+BD308 -> 751251.98 | BG5: =BG6+BG208+BG308 -> 751251.98 | BJ5: =BJ6+BJ208+BJ308 -> 751251.98
B6: 否 | C6: 1.1.1 | D6: 人工服务 | H6: =H7+H29+H57+H111+H143+H159+H176+H189 -> 8542403.5 | AB6: =AB7+AB29+AB57+AB111+AB143+AB159+AB176+AB189 -> 8542403.5 | AC6: =AC7+AC29+AC57+AC111+AC143+AC159+AC176+AC189 -> 815761.01 | AF6: =AF7+AF29+AF57+AF111+AF143+AF159+AF176+AF189 -> 702422.05 | AI6: =AI7+AI29+AI57+AI111+AI143+AI159+AI176+AI189 -> 702422.05 | AL6: =AL7+AL29+AL57+AL111+AL143+AL159+AL176+AL189 -> 702422.05 | AO6: =AO7+AO29+AO57+AO111+AO143+AO159+AO176+AO189 -> 702422.05 | AR6: =AR7+AR29+AR57+AR111+AR143+AR159+AR176+AR189 -> 702422.05 | AU6: =AU7+AU29+AU57+AU111+AU143+AU159+AU176+AU189 -> 702422.05 | AX6: =AX7+AX29+AX57+AX111+AX143+AX159+AX176+AX189 -> 702422.05 | BA6: =BA7+BA29+BA57+BA111+BA143+BA159+BA176+BA189 -> 702422.05 | BD6: =BD7+BD29+BD57+BD111+BD143+BD159+BD176+BD189 -> 702422.05 | BG6: =BG7+BG29+BG57+BG111+BG143+BG159+BG176+BG189 -> 702422.05 | BJ6: =BJ7+BJ29+BJ57+BJ111+BJ143+BJ159+BJ176+BJ189 -> 702422.05
B7: 否 | C7: 1.1.1.1 | D7: 保安人员 | H7: =H8+H15+H22 -> 1715797.4 | AB7: =AB8+AB15+AB22 -> 1715797.4 | AC7: =AC8+AC15+AC22 -> 197789.17 | AF7: =AF8+AF15+AF22 -> 138000.75 | AI7: =AI8+AI15+AI22 -> 138000.75 | AL7: =AL8+AL15+AL22 -> 138000.75 | AO7: =AO8+AO15+AO22 -> 138000.75 | AR7: =AR8+AR15+AR22 -> 138000.75 | AU7: =AU8+AU15+AU22 -> 138000.75 | AX7: =AX8+AX15+AX22 -> 138000.75 | BA7: =BA8+BA15+BA22 -> 138000.75 | BD7: =BD8+BD15+BD22 -> 138000.75 | BG7: =BG8+BG15+BG22 -> 138000.75 | BJ7: =BJ8+BJ15+BJ22 -> 138000.75
B8: 否 | C8: 1.1.1.1.1 | D8: 自有人员 | H8: =SUM(H9:H14) -> 1715797.4 | AB8: =SUM(AB9:AB14) -> 1715797.4 | AC8: =SUM(AC9:AC14) -> 197789.17 | AF8: =SUM(AF9:AF14) -> 138000.75 | AI8: =SUM(AI9:AI14) -> 138000.75 | AL8: =SUM(AL9:AL14) -> 138000.75 | AO8: =SUM(AO9:AO14) -> 138000.75 | AR8: =SUM(AR9:AR14) -> 138000.75 | AU8: =SUM(AU9:AU14) -> 138000.75 | AX8: =SUM(AX9:AX14) -> 138000.75 | BA8: =SUM(BA9:BA14) -> 138000.75 | BD8: =SUM(BD9:BD14) -> 138000.75 | BG8: =SUM(BG9:BG14) -> 138000.75 | BJ8: =SUM(BJ9:BJ14) -> 138000.75
B9: 是 | C9: 1.1.1.1.1.1 | D9: 保安经理 | E9: 指自有保安经理 | G9: 按月编制，汇总成年总量 | H9: =AB9 -> 1715797.4 | I9: 岗位数量 | J9: =SUM(AD9,AG9,AJ9,AM9,AP9,AS9,AV9,AY9,BB9,BE9,BH9,BK9)/N9 -> 15 | K9: 岗 | L9: =H9/N9/J9 -> 9532.2079 | M9: 元/㎡/月 | N9: =COUNTIF(AD9,">0")+COUNTIF(AG9,">0")+COUNTIF(AJ9,">0")+COUNTIF(AM9,">0")+COUNTIF(AP9,">0")+COUNTIF(AS9,">0")+COUNTIF(AV9,">0")+COUNTIF(AY9,">0")+COUNTIF(BB9,">0")+COUNTIF(BE9,">0")+COUNTIF(BH9,">0")+COUNTIF(BK9,">0") -> 12 | AB9: =SUM(AC9,AF9,AI9,AL9,AO9,AR9,AU9,AX9,BA9,BD9,BG9,BJ9) -> 1715797.4 | AC9: =AD9*AE9 -> 197789.17 | AD9: ='1-2 人员岗位信息'!F11 -> 15 | AE9: =IFERROR('自有人工预算（附表）'!E26/AD9,0) -> 13185.945 | AF9: =AG9*AH9 -> 138000.75 | AG9: =SUMIFS('1-2 人员岗位信息'!G:G,'1-2 人员岗位信息'!$C:$C,"自有人员",'1-2 人员岗位信息'!$B:$B,$D9) -> 15 | AH9: =IFERROR('自有人工预算（附表）'!F26/AG9,0) -> 9200.05 | AI9: =AJ9*AK9 -> 138000.75 | AJ9: =SUMIFS('1-2 人员岗位信息'!H:H,'1-2 人员岗位信息'!$C:$C,"自有人员",'1-2 人员岗位信息'!$B:$B,$D9) -> 15 | AK9: =IFERROR('自有人工预算（附表）'!G26/AJ9,0) -> 9200.05 | AL9: =AM9*AN9 -> 138000.75 | AM9: =SUMIFS('1-2 人员岗位信息'!I:I,'1-2 人员岗位信息'!$C:$C,"自有人员",'1-2 人员岗位信息'!$B:$B,$D9) -> 15 | AN9: =IFERROR('自有人工预算（附表）'!H26/AM9,0) -> 9200.05 | AO9: =AP9*AQ9 -> 138000.75 | AP9: =SUMIFS('1-2 人员岗位信息'!J:J,'1-2 人员岗位信息'!$C:$C,"自有人员",'1-2 人员岗位信息'!$B:$B,$D9) -> 15 | AQ9: =IFERROR('自有人工预算（附表）'!I26/AP9,0) -> 9200.05 | AR9: =AS9*AT9 -> 138000.75 | AS9: =SUMIFS('1-2 人员岗位信息'!K:K,'1-2 人员岗位信息'!$C:$C,"自有人员",'1-2 人员岗位信息'!$B:$B,$D9) -> 15 | AT9: =IFERROR('自有人工预算（附表）'!J26/AS9,0) -> 9200.05 | AU9: =AV9*AW9 -> 138000.75 | AV9: =SUMIFS('1-2 人员岗位信息'!L:L,'1-2 人员岗位信息'!$C:$C,"自有人员",'1-2 人员岗位信息'!$B:$B,$D9) -> 15 | AW9: =IFERROR('自有人工预算（附表）'!K26/AV9,0) -> 9200.05 | AX9: =AY9*AZ9 -> 138000.75 | AY9: =SUMIFS('1-2 人员岗位信息'!M:M,'1-2 人员岗位信息'!$C:$C,"自有人员",'1-2 人员岗位信息'!$B:$B,$D9) -> 15 | AZ9: =IFERROR('自有人工预算（附表）'!L26/AY9,0) -> 9200.05 | BA9: =BB9*BC9 -> 138000.75 | BB9: =SUMIFS('1-2 人员岗位信息'!N:N,'1-2 人员岗位信息'!$C:$C,"自有人员",'1-2 人员岗位信息'!$B:$B,$D9) -> 15 | BC9: =IFERROR('自有人工预算（附表）'!M26/BB9,0) -> 9200.05 | BD9: =BE9*BF9 -> 138000.75 | BE9: =SUMIFS('1-2 人员岗位信息'!O:O,'1-2 人员岗位信息'!$C:$C,"自有人员",'1-2 人员岗位信息'!$B:$B,$D9) -> 15 | BF9: =IFERROR('自有人工预算（附表）'!N26/BE9,0) -> 9200.05 | BG9: =BH9*BI9 -> 138000.75 | BH9: =SUMIFS('1-2 人员岗位信息'!P:P,'1-2 人员岗位信息'!$C:$C,"自有人员",'1-2 人员岗位信息'!$B:$B,$D9) -> 15 | BI9: =IFERROR('自有人工预算（附表）'!O26/BH9,0) -> 9200.05 | BJ9: =BK9*BL9 -> 138000.75 | BK9: =SUMIFS('1-2 人员岗位信息'!Q:Q,'1-2 人员岗位信息'!$C:$C,"自有人员",'1-2 人员岗位信息'!$B:$B,$D9) -> 15 | BL9: =IFERROR('自有人工预算（附表）'!P26/BK9,0) -> 9200.05
B10: 是 | C10: 1.1.1.1.1.2 | D10: 保安主管 | E10: 指自有保安主管 | G10: 按月编制，汇总成年总量 | H10: =AB10 -> 0 | I10: 岗位数量 | J10: =SUM(AD10,AG10,AJ10,AM10,AP10,AS10,AV10,AY10,BB10,BE10,BH10,BK10)/N10 -> #DIV/0! | K10: 岗 | L10: =H10/N10/J10 -> #DIV/0! | M10: 元/㎡/月 | N10: =COUNTIF(AD10,">0")+COUNTIF(AG10,">0")+COUNTIF(AJ10,">0")+COUNTIF(AM10,">0")+COUNTIF(AP10,">0")+COUNTIF(AS10,">0")+COUNTIF(AV10,">0")+COUNTIF(AY10,">0")+COUNTIF(BB10,">0")+COUNTIF(BE10,">0")+COUNTIF(BH10,">0")+COUNTIF(BK10,">0") -> 0 | AB10: =SUM(AC10,AF10,AI10,AL10,AO10,AR10,AU10,AX10,BA10,BD10,BG10,BJ10) -> 0 | AC10: =AD10*AE10 -> 0 | AD10: ='1-2 人员岗位信息'!F15 -> 0 | AF10: =AG10*AH10 -> 0 | AG10: =SUMIFS('1-2 人员岗位信息'!G:G,'1-2 人员岗位信息'!$C:$C,"自有人员",'1-2 人员岗位信息'!$B:$B,$D10) -> 0 | AI10: =AJ10*AK10 -> 0 | AJ10: =SUMIFS('1-2 人员岗位信息'!H:H,'1-2 人员岗位信息'!$C:$C,"自有人员",'1-2 人员岗位信息'!$B:$B,$D10) -> 0 | AL10: =AM10*AN10 -> 0 | AM10: =SUMIFS('1-2 人员岗位信息'!I:I,'1-2 人员岗位信息'!$C:$C,"自有人员",'1-2 人员岗位信息'!$B:$B,$D10) -> 0 | AO10: =AP10*AQ10 -> 0 | AP10: =SUMIFS('1-2 人员岗位信息'!J:J,'1-2 人员岗位信息'!$C:$C,"自有人员",'1-2 人员岗位信息'!$B:$B,$D10) -> 0 | AR10: =AS10*AT10 -> 0 | AS10: =SUMIFS('1-2 人员岗位信息'!K:K,'1-2 人员岗位信息'!$C:$C,"自有人员",'1-2 人员岗位信息'!$B:$B,$D10) -> 0 | AU10: =AV10*AW10 -> 0 | AV10: =SUMIFS('1-2 人员岗位信息'!L:L,'1-2 人员岗位信息'!$C:$C,"自有人员",'1-2 人员岗位信息'!$B:$B,$D10) -> 0 | AX10: =AY10*AZ10 -> 0 | AY10: =SUMIFS('1-2 人员岗位信息'!M:M,'1-2 人员岗位信息'!$C:$C,"自有人员",'1-2 人员岗位信息'!$B:$B,$D10) -> 0 | BA10: =BB10*BC10 -> 0 | BB10: =SUMIFS('1-2 人员岗位信息'!N:N,'1-2 人员岗位信息'!$C:$C,"自有人员",'1-2 人员岗位信息'!$B:$B,$D10) -> 0 | BD10: =BE10*BF10 -> 0 | BE10: =SUMIFS('1-2 人员岗位信息'!O:O,'1-2 人员岗位信息'!$C:$C,"自有人员",'1-2 人员岗位信息'!$B:$B,$D10) -> 0 | BG10: =BH10*BI10 -> 0 | BH10: =SUMIFS('1-2 人员岗位信息'!P:P,'1-2 人员岗位信息'!$C:$C,"自有人员",'1-2 人员岗位信息'!$B:$B,$D10) -> 0 | BJ10: =BK10*BL10 -> 0 | BK10: =SUMIFS('1-2 人员岗位信息'!Q:Q,'1-2 人员岗位信息'!$C:$C,"自有人员",'1-2 人员岗位信息'!$B:$B,$D10) -> 0
B11: 是 | C11: 1.1.1.1.1.3 | D11: 门岗员工 | E11: 含车岗、形象岗、商写礼宾岗 | G11: 按月编制，汇总成年总量 | H11: =AB11 -> 0 | I11: 岗位数量 | J11: =SUM(AD11,AG11,AJ11,AM11,AP11,AS11,AV11,AY11,BB11,BE11,BH11,BK11)/N11 -> #DIV/0! | K11: 岗 | L11: =H11/N11/J11 -> #DIV/0! | M11: 元/㎡/月 | N11: =COUNTIF(AD11,">0")+COUNTIF(AG11,">0")+COUNTIF(AJ11,">0")+COUNTIF(AM11,">0")+COUNTIF(AP11,">0")+COUNTIF(AS11,">0")+COUNTIF(AV11,">0")+COUNTIF(AY11,">0")+COUNTIF(BB11,">0")+COUNTIF(BE11,">0")+COUNTIF(BH11,">0")+COUNTIF(BK11,">0") -> 0 | AB11: =SUM(AC11,AF11,AI11,AL11,AO11,AR11,AU11,AX11,BA11,BD11,BG11,BJ11) -> 0 | AC11: =AD11*AE11 -> 0 | AD11: ='1-2 人员岗位信息'!F19 -> 0 | AF11: =AG11*AH11 -> 0 | AG11: =SUMIFS('1-2 人员岗位信息'!G:G,'1-2 人员岗位信息'!$C:$C,"自有人员",'1-2 人员岗位信息'!$B:$B,$D11) -> 0 | AI11: =AJ11*AK11 -> 0 | AJ11: =SUMIFS('1-2 人员岗位信息'!H:H,'1-2 人员岗位信息'!$C:$C,"自有人员",'1-2 人员岗位信息'!$B:$B,$D11) -> 0 | AL11: =AM11*AN11 -> 0 | AM11: =SUMIFS('1-2 人员岗位信息'!I:I,'1-2 人员岗位信息'!$C:$C,"自有人员",'1-2 人员岗位信息'!$B:$B,$D11) -> 0 | AO11: =AP11*AQ11 -> 0 | AP11: =SUMIFS('1-2 人员岗位信息'!J:J,'1-2 人员岗位信息'!$C:$C,"自有人员",'1-2 人员岗位信息'!$B:$B,$D11) -> 0 | AR11: =AS11*AT11 -> 0 | AS11: =SUMIFS('1-2 人员岗位信息'!K:K,'1-2 人员岗位信息'!$C:$C,"自有人员",'1-2 人员岗位信息'!$B:$B,$D11) -> 0 | AU11: =AV11*AW11 -> 0 | AV11: =SUMIFS('1-2 人员岗位信息'!L:L,'1-2 人员岗位信息'!$C:$C,"自有人员",'1-2 人员岗位信息'!$B:$B,$D11) -> 0 | AX11: =AY11*AZ11 -> 0 | AY11: =SUMIFS('1-2 人员岗位信息'!M:M,'1-2 人员岗位信息'!$C:$C,"自有人员",'1-2 人员岗位信息'!$B:$B,$D11) -> 0 | BA11: =BB11*BC11 -> 0 | BB11: =SUMIFS('1-2 人员岗位信息'!N:N,'1-2 人员岗位信息'!$C:$C,"自有人员",'1-2 人员岗位信息'!$B:$B,$D11) -> 0 | BD11: =BE11*BF11 -> 0 | BE11: =SUMIFS('1-2 人员岗位信息'!O:O,'1-2 人员岗位信息'!$C:$C,"自有人员",'1-2 人员岗位信息'!$B:$B,$D11) -> 0 | BG11: =BH11*BI11 -> 0 | BH11: =SUMIFS('1-2 人员岗位信息'!P:P,'1-2 人员岗位信息'!$C:$C,"自有人员",'1-2 人员岗位信息'!$B:$B,$D11) -> 0 | BJ11: =BK11*BL11 -> 0 | BK11: =SUMIFS('1-2 人员岗位信息'!Q:Q,'1-2 人员岗位信息'!$C:$C,"自有人员",'1-2 人员岗位信息'!$B:$B,$D11) -> 0
B12: 是 | C12: 1.1.1.1.1.4 | D12: 巡逻岗员工 | E12: 含机动岗 | G12: 按月编制，汇总成年总量 | H12: =AB12 -> 0 | I12: 岗位数量 | J12: =SUM(AD12,AG12,AJ12,AM12,AP12,AS12,AV12,AY12,BB12,BE12,BH12,BK12)/N12 -> #DIV/0! | K12: 岗 | L12: =H12/N12/J12 -> #DIV/0! | M12: 元/㎡/月 | N12: =COUNTIF(AD12,">0")+COUNTIF(AG12,">0")+COUNTIF(AJ12,">0")+COUNTIF(AM12,">0")+COUNTIF(AP12,">0")+COUNTIF(AS12,">0")+COUNTIF(AV12,">0")+COUNTIF(AY12,">0")+COUNTIF(BB12,">0")+COUNTIF(BE12,">0")+COUNTIF(BH12,">0")+COUNTIF(BK12,">0") -> 0 | AB12: =SUM(AC12,AF12,AI12,AL12,AO12,AR12,AU12,AX12,BA12,BD12,BG12,BJ12) -> 0 | AC12: =AD12*AE12 -> 0 | AD12: ='1-2 人员岗位信息'!F23 -> 0 | AF12: =AG12*AH12 -> 0 | AG12: =SUMIFS('1-2 人员岗位信息'!G:G,'1-2 人员岗位信息'!$C:$C,"自有人员",'1-2 人员岗位信息'!$B:$B,$D12) -> 0 | AI12: =AJ12*AK12 -> 0 | AJ12: =SUMIFS('1-2 人员岗位信息'!H:H,'1-2 人员岗位信息'!$C:$C,"自有人员",'1-2 人员岗位信息'!$B:$B,$D12) -> 0 | AL12: =AM12*AN12 -> 0 | AM12: =SUMIFS('1-2 人员岗位信息'!I:I,'1-2 人员岗位信息'!$C:$C,"自有人员",'1-2 人员岗位信息'!$B:$B,$D12) -> 0 | AO12: =AP12*AQ12 -> 0 | AP12: =SUMIFS('1-2 人员岗位信息'!J:J,'1-2 人员岗位信息'!$C:$C,"自有人员",'1-2 人员岗位信息'!$B:$B,$D12) -> 0 | AR12: =AS12*AT12 -> 0 | AS12: =SUMIFS('1-2 人员岗位信息'!K:K,'1-2 人员岗位信息'!$C:$C,"自有人员",'1-2 人员岗位信息'!$B:$B,$D12) -> 0 | AU12: =AV12*AW12 -> 0 | AV12: =SUMIFS('1-2 人员岗位信息'!L:L,'1-2 人员岗位信息'!$C:$C,"自有人员",'1-2 人员岗位信息'!$B:$B,$D12) -> 0 | AX12: =AY12*AZ12 -> 0 | AY12: =SUMIFS('1-2 人员岗位信息'!M:M,'1-2 人员岗位信息'!$C:$C,"自有人员",'1-2 人员岗位信息'!$B:$B,$D12) -> 0 | BA12: =BB12*BC12 -> 0 | BB12: =SUMIFS('1-2 人员岗位信息'!N:N,'1-2 人员岗位信息'!$C:$C,"自有人员",'1-2 人员岗位信息'!$B:$B,$D12) -> 0 | BD12: =BE12*BF12 -> 0 | BE12: =SUMIFS('1-2 人员岗位信息'!O:O,'1-2 人员岗位信息'!$C:$C,"自有人员",'1-2 人员岗位信息'!$B:$B,$D12) -> 0 | BG12: =BH12*BI12 -> 0 | BH12: =SUMIFS('1-2 人员岗位信息'!P:P,'1-2 人员岗位信息'!$C:$C,"自有人员",'1-2 人员岗位信息'!$B:$B,$D12) -> 0 | BJ12: =BK12*BL12 -> 0 | BK12: =SUMIFS('1-2 人员岗位信息'!Q:Q,'1-2 人员岗位信息'!$C:$C,"自有人员",'1-2 人员岗位信息'!$B:$B,$D12) -> 0
B13: 是 | C13: 1.1.1.1.1.5 | D13: 中控岗员工 | E13: 指中控室、监控室人员 | G13: 按月编制，汇总成年总量 | H13: =AB13 -> 0 | I13: 岗位数量 | J13: =SUM(AD13,AG13,AJ13,AM13,AP13,AS13,AV13,AY13,BB13,BE13,BH13,BK13)/N13 -> #DIV/0! | K13: 岗 | L13: =H13/N13/J13 -> #DIV/0! | M13: 元/㎡/月 | N13: =COUNTIF(AD13,">0")+COUNTIF(AG13,">0")+COUNTIF(AJ13,">0")+COUNTIF(AM13,">0")+COUNTIF(AP13,">0")+COUNTIF(AS13,">0")+COUNTIF(AV13,">0")+COUNTIF(AY13,">0")+COUNTIF(BB13,">0")+COUNTIF(BE13,">0")+COUNTIF(BH13,">0")+COUNTIF(BK13,">0") -> 0 | AB13: =SUM(AC13,AF13,AI13,AL13,AO13,AR13,AU13,AX13,BA13,BD13,BG13,BJ13) -> 0 | AC13: =AD13*AE13 -> 0 | AD13: ='1-2 人员岗位信息'!F27 -> 0 | AF13: =AG13*AH13 -> 0 | AG13: =SUMIFS('1-2 人员岗位信息'!G:G,'1-2 人员岗位信息'!$C:$C,"自有人员",'1-2 人员岗位信息'!$B:$B,$D13) -> 0 | AI13: =AJ13*AK13 -> 0 | AJ13: =SUMIFS('1-2 人员岗位信息'!H:H,'1-2 人员岗位信息'!$C:$C,"自有人员",'1-2 人员岗位信息'!$B:$B,$D13) -> 0 | AL13: =AM13*AN13 -> 0 | AM13: =SUMIFS('1-2 人员岗位信息'!I:I,'1-2 人员岗位信息'!$C:$C,"自有人员",'1-2 人员岗位信息'!$B:$B,$D13) -> 0 | AO13: =AP13*AQ13 -> 0 | AP13: =SUMIFS('1-2 人员岗位信息'!J:J,'1-2 人员岗位信息'!$C:$C,"自有人员",'1-2 人员岗位信息'!$B:$B,$D13) -> 0 | AR13: =AS13*AT13 -> 0 | AS13: =SUMIFS('1-2 人员岗位信息'!K:K,'1-2 人员岗位信息'!$C:$C,"自有人员",'1-2 人员岗位信息'!$B:$B,$D13) -> 0 | AU13: =AV13*AW13 -> 0 | AV13: =SUMIFS('1-2 人员岗位信息'!L:L,'1-2 人员岗位信息'!$C:$C,"自有人员",'1-2 人员岗位信息'!$B:$B,$D13) -> 0 | AX13: =AY13*AZ13 -> 0 | AY13: =SUMIFS('1-2 人员岗位信息'!M:M,'1-2 人员岗位信息'!$C:$C,"自有人员",'1-2 人员岗位信息'!$B:$B,$D13) -> 0 | BA13: =BB13*BC13 -> 0 | BB13: =SUMIFS('1-2 人员岗位信息'!N:N,'1-2 人员岗位信息'!$C:$C,"自有人员",'1-2 人员岗位信息'!$B:$B,$D13) -> 0 | BD13: =BE13*BF13 -> 0 | BE13: =SUMIFS('1-2 人员岗位信息'!O:O,'1-2 人员岗位信息'!$C:$C,"自有人员",'1-2 人员岗位信息'!$B:$B,$D13) -> 0 | BG13: =BH13*BI13 -> 0 | BH13: =SUMIFS('1-2 人员岗位信息'!P:P,'1-2 人员岗位信息'!$C:$C,"自有人员",'1-2 人员岗位信息'!$B:$B,$D13) -> 0 | BJ13: =BK13*BL13 -> 0 | BK13: =SUMIFS('1-2 人员岗位信息'!Q:Q,'1-2 人员岗位信息'!$C:$C,"自有人员",'1-2 人员岗位信息'!$B:$B,$D13) -> 0
B14: 是 | C14: 1.1.1.1.1.6 | D14: 其他保安员工 | E14: 上述不包含的岗位可适用此项 | G14: 按月编制，汇总成年总量 | H14: =AB14 -> 0 | I14: 岗位数量 | J14: =SUM(AD14,AG14,AJ14,AM14,AP14,AS14,AV14,AY14,BB14,BE14,BH14,BK14)/N14 -> #DIV/0! | K14: 岗 | L14: =H14/N14/J14 -> #DIV/0! | M14: 元/㎡/月 | N14: =COUNTIF(AD14,">0")+COUNTIF(AG14,">0")+COUNTIF(AJ14,">0")+COUNTIF(AM14,">0")+COUNTIF(AP14,">0")+COUNTIF(AS14,">0")+COUNTIF(AV14,">0")+COUNTIF(AY14,">0")+COUNTIF(BB14,">0")+COUNTIF(BE14,">0")+COUNTIF(BH14,">0")+COUNTIF(BK14,">0") -> 0 | AB14: =SUM(AC14,AF14,AI14,AL14,AO14,AR14,AU14,AX14,BA14,BD14,BG14,BJ14) -> 0 | AC14: =AD14*AE14 -> 0 | AD14: ='1-2 人员岗位信息'!F31 -> 0 | AF14: =AG14*AH14 -> 0 | AG14: =SUMIFS('1-2 人员岗位信息'!G:G,'1-2 人员岗位信息'!$C:$C,"自有人员",'1-2 人员岗位信息'!$B:$B,$D14) -> 0 | AI14: =AJ14*AK14 -> 0 | AJ14: =SUMIFS('1-2 人员岗位信息'!H:H,'1-2 人员岗位信息'!$C:$C,"自有人员",'1-2 人员岗位信息'!$B:$B,$D14) -> 0 | AL14: =AM14*AN14 -> 0 | AM14: =SUMIFS('1-2 人员岗位信息'!I:I,'1-2 人员岗位信息'!$C:$C,"自有人员",'1-2 人员岗位信息'!$B:$B,$D14) -> 0 | AO14: =AP14*AQ14 -> 0 | AP14: =SUMIFS('1-2 人员岗位信息'!J:J,'1-2 人员岗位信息'!$C:$C,"自有人员",'1-2 人员岗位信息'!$B:$B,$D14) -> 0 | AR14: =AS14*AT14 -> 0 | AS14: =SUMIFS('1-2 人员岗位信息'!K:K,'1-2 人员岗位信息'!$C:$C,"自有人员",'1-2 人员岗位信息'!$B:$B,$D14) -> 0 | AU14: =AV14*AW14 -> 0 | AV14: =SUMIFS('1-2 人员岗位信息'!L:L,'1-2 人员岗位信息'!$C:$C,"自有人员",'1-2 人员岗位信息'!$B:$B,$D14) -> 0 | AX14: =AY14*AZ14 -> 0 | AY14: =SUMIFS('1-2 人员岗位信息'!M:M,'1-2 人员岗位信息'!$C:$C,"自有人员",'1-2 人员岗位信息'!$B:$B,$D14) -> 0 | BA14: =BB14*BC14 -> 0 | BB14: =SUMIFS('1-2 人员岗位信息'!N:N,'1-2 人员岗位信息'!$C:$C,"自有人员",'1-2 人员岗位信息'!$B:$B,$D14) -> 0 | BD14: =BE14*BF14 -> 0 | BE14: =SUMIFS('1-2 人员岗位信息'!O:O,'1-2 人员岗位信息'!$C:$C,"自有人员",'1-2 人员岗位信息'!$B:$B,$D14) -> 0 | BG14: =BH14*BI14 -> 0 | BH14: =SUMIFS('1-2 人员岗位信息'!P:P,'1-2 人员岗位信息'!$C:$C,"自有人员",'1-2 人员岗位信息'!$B:$B,$D14) -> 0 | BJ14: =BK14*BL14 -> 0 | BK14: =SUMIFS('1-2 人员岗位信息'!Q:Q,'1-2 人员岗位信息'!$C:$C,"自有人员",'1-2 人员岗位信息'!$B:$B,$D14) -> 0
B15: 否 | C15: 1.1.1.1.2 | D15: 劳务派遣 | H15: =SUM(H16:H21) -> 0 | AB15: =SUM(AB16:AB21) -> 0 | AC15: =SUM(AC16:AC21) -> 0 | AF15: =SUM(AF16:AF21) -> 0 | AI15: =SUM(AI16:AI21) -> 0 | AL15: =SUM(AL16:AL21) -> 0 | AO15: =SUM(AO16:AO21) -> 0 | AR15: =SUM(AR16:AR21) -> 0 | AU15: =SUM(AU16:AU21) -> 0 | AX15: =SUM(AX16:AX21) -> 0 | BA15: =SUM(BA16:BA21) -> 0 | BD15: =SUM(BD16:BD21) -> 0 | BG15: =SUM(BG16:BG21) -> 0 | BJ15: =SUM(BJ16:BJ21) -> 0
B16: 是 | C16: 1.1.1.1.2.1 | D16: 保安经理 | E16: 指派遣保安经理 | G16: 按月编制，汇总成年总量 | H16: =AB16 -> 0 | I16: 岗位数量 | J16: =SUM(AD16,AG16,AJ16,AM16,AP16,AS16,AV16,AY16,BB16,BE16,BH16,BK16)/N16 -> #DIV/0! | K16: 岗 | L16: =H16/N16/J16 -> #DIV/0! | M16: 元/㎡/月 | N16: =COUNTIF(AD16,">0")+COUNTIF(AG16,">0")+COUNTIF(AJ16,">0")+COUNTIF(AM16,">0")+COUNTIF(AP16,">0")+COUNTIF(AS16,">0")+COUNTIF(AV16,">0")+COUNTIF(AY16,">0")+COUNTIF(BB16,">0")+COUNTIF(BE16,">0")+COUNTIF(BH16,">0")+COUNTIF(BK16,">0") -> 0 | AB16: =SUM(AC16,AF16,AI16,AL16,AO16,AR16,AU16,AX16,BA16,BD16,BG16,BJ16) -> 0 | AC16: =AD16*AE16 -> 0 | AD16: ='1-2 人员岗位信息'!F12 -> 0 | AF16: =AG16*AH16 -> 0 | AG16: =SUMIFS('1-2 人员岗位信息'!G:G,'1-2 人员岗位信息'!$C:$C,"劳务派遣",'1-2 人员岗位信息'!$B:$B,$D16) -> 0 | AI16: =AJ16*AK16 -> 0 | AJ16: =SUMIFS('1-2 人员岗位信息'!H:H,'1-2 人员岗位信息'!$C:$C,"劳务派遣",'1-2 人员岗位信息'!$B:$B,$D16) -> 0 | AL16: =AM16*AN16 -> 0 | AM16: =SUMIFS('1-2 人员岗位信息'!I:I,'1-2 人员岗位信息'!$C:$C,"劳务派遣",'1-2 人员岗位信息'!$B:$B,$D16) -> 0 | AO16: =AP16*AQ16 -> 0 | AP16: =SUMIFS('1-2 人员岗位信息'!J:J,'1-2 人员岗位信息'!$C:$C,"劳务派遣",'1-2 人员岗位信息'!$B:$B,$D16) -> 0 | AR16: =AS16*AT16 -> 0 | AS16: =SUMIFS('1-2 人员岗位信息'!K:K,'1-2 人员岗位信息'!$C:$C,"劳务派遣",'1-2 人员岗位信息'!$B:$B,$D16) -> 0 | AU16: =AV16*AW16 -> 0 | AV16: =SUMIFS('1-2 人员岗位信息'!L:L,'1-2 人员岗位信息'!$C:$C,"劳务派遣",'1-2 人员岗位信息'!$B:$B,$D16) -> 0 | AX16: =AY16*AZ16 -> 0 | AY16: =SUMIFS('1-2 人员岗位信息'!M:M,'1-2 人员岗位信息'!$C:$C,"劳务派遣",'1-2 人员岗位信息'!$B:$B,$D16) -> 0 | BA16: =BB16*BC16 -> 0 | BB16: =SUMIFS('1-2 人员岗位信息'!N:N,'1-2 人员岗位信息'!$C:$C,"劳务派遣",'1-2 人员岗位信息'!$B:$B,$D16) -> 0 | BD16: =BE16*BF16 -> 0 | BE16: =SUMIFS('1-2 人员岗位信息'!O:O,'1-2 人员岗位信息'!$C:$C,"劳务派遣",'1-2 人员岗位信息'!$B:$B,$D16) -> 0 | BG16: =BH16*BI16 -> 0 | BH16: =SUMIFS('1-2 人员岗位信息'!P:P,'1-2 人员岗位信息'!$C:$C,"劳务派遣",'1-2 人员岗位信息'!$B:$B,$D16) -> 0 | BJ16: =BK16*BL16 -> 0 | BK16: =SUMIFS('1-2 人员岗位信息'!Q:Q,'1-2 人员岗位信息'!$C:$C,"劳务派遣",'1-2 人员岗位信息'!$B:$B,$D16) -> 0
B17: 是 | C17: 1.1.1.1.2.2 | D17: 保安主管 | E17: 指派遣保安主管 | G17: 按月编制，汇总成年总量 | H17: =AB17 -> 0 | I17: 岗位数量 | J17: =SUM(AD17,AG17,AJ17,AM17,AP17,AS17,AV17,AY17,BB17,BE17,BH17,BK17)/N17 -> #DIV/0! | K17: 岗 | L17: =H17/N17/J17 -> #DIV/0! | M17: 元/㎡/月 | N17: =COUNTIF(AD17,">0")+COUNTIF(AG17,">0")+COUNTIF(AJ17,">0")+COUNTIF(AM17,">0")+COUNTIF(AP17,">0")+COUNTIF(AS17,">0")+COUNTIF(AV17,">0")+COUNTIF(AY17,">0")+COUNTIF(BB17,">0")+COUNTIF(BE17,">0")+COUNTIF(BH17,">0")+COUNTIF(BK17,">0") -> 0 | AB17: =SUM(AC17,AF17,AI17,AL17,AO17,AR17,AU17,AX17,BA17,BD17,BG17,BJ17) -> 0 | AC17: =AD17*AE17 -> 0 | AD17: ='1-2 人员岗位信息'!F16 -> 0 | AF17: =AG17*AH17 -> 0 | AG17: =SUMIFS('1-2 人员岗位信息'!G:G,'1-2 人员岗位信息'!$C:$C,"劳务派遣",'1-2 人员岗位信息'!$B:$B,$D17) -> 0 | AI17: =AJ17*AK17 -> 0 | AJ17: =SUMIFS('1-2 人员岗位信息'!H:H,'1-2 人员岗位信息'!$C:$C,"劳务派遣",'1-2 人员岗位信息'!$B:$B,$D17) -> 0 | AL17: =AM17*AN17 -> 0 | AM17: =SUMIFS('1-2 人员岗位信息'!I:I,'1-2 人员岗位信息'!$C:$C,"劳务派遣",'1-2 人员岗位信息'!$B:$B,$D17) -> 0 | AO17: =AP17*AQ17 -> 0 | AP17: =SUMIFS('1-2 人员岗位信息'!J:J,'1-2 人员岗位信息'!$C:$C,"劳务派遣",'1-2 人员岗位信息'!$B:$B,$D17) -> 0 | AR17: =AS17*AT17 -> 0 | AS17: =SUMIFS('1-2 人员岗位信息'!K:K,'1-2 人员岗位信息'!$C:$C,"劳务派遣",'1-2 人员岗位信息'!$B:$B,$D17) -> 0 | AU17: =AV17*AW17 -> 0 | AV17: =SUMIFS('1-2 人员岗位信息'!L:L,'1-2 人员岗位信息'!$C:$C,"劳务派遣",'1-2 人员岗位信息'!$B:$B,$D17) -> 0 | AX17: =AY17*AZ17 -> 0 | AY17: =SUMIFS('1-2 人员岗位信息'!M:M,'1-2 人员岗位信息'!$C:$C,"劳务派遣",'1-2 人员岗位信息'!$B:$B,$D17) -> 0 | BA17: =BB17*BC17 -> 0 | BB17: =SUMIFS('1-2 人员岗位信息'!N:N,'1-2 人员岗位信息'!$C:$C,"劳务派遣",'1-2 人员岗位信息'!$B:$B,$D17) -> 0 | BD17: =BE17*BF17 -> 0 | BE17: =SUMIFS('1-2 人员岗位信息'!O:O,'1-2 人员岗位信息'!$C:$C,"劳务派遣",'1-2 人员岗位信息'!$B:$B,$D17) -> 0 | BG17: =BH17*BI17 -> 0 | BH17: =SUMIFS('1-2 人员岗位信息'!P:P,'1-2 人员岗位信息'!$C:$C,"劳务派遣",'1-2 人员岗位信息'!$B:$B,$D17) -> 0 | BJ17: =BK17*BL17 -> 0 | BK17: =SUMIFS('1-2 人员岗位信息'!Q:Q,'1-2 人员岗位信息'!$C:$C,"劳务派遣",'1-2 人员岗位信息'!$B:$B,$D17) -> 0
B18: 是 | C18: 1.1.1.1.2.3 | D18: 门岗员工 | E18: 含车岗、形象岗、商写礼宾岗 | G18: 按月编制，汇总成年总量 | H18: =AB18 -> 0 | I18: 岗位数量 | J18: =SUM(AD18,AG18,AJ18,AM18,AP18,AS18,AV18,AY18,BB18,BE18,BH18,BK18)/N18 -> #DIV/0! | K18: 岗 | L18: =H18/N18/J18 -> #DIV/0! | M18: 元/㎡/月 | N18: =COUNTIF(AD18,">0")+COUNTIF(AG18,">0")+COUNTIF(AJ18,">0")+COUNTIF(AM18,">0")+COUNTIF(AP18,">0")+COUNTIF(AS18,">0")+COUNTIF(AV18,">0")+COUNTIF(AY18,">0")+COUNTIF(BB18,">0")+COUNTIF(BE18,">0")+COUNTIF(BH18,">0")+COUNTIF(BK18,">0") -> 0 | AB18: =SUM(AC18,AF18,AI18,AL18,AO18,AR18,AU18,AX18,BA18,BD18,BG18,BJ18) -> 0 | AC18: =AD18*AE18 -> 0 | AD18: ='1-2 人员岗位信息'!F20 -> 0 | AF18: =AG18*AH18 -> 0 | AG18: =SUMIFS('1-2 人员岗位信息'!G:G,'1-2 人员岗位信息'!$C:$C,"劳务派遣",'1-2 人员岗位信息'!$B:$B,$D18) -> 0 | AI18: =AJ18*AK18 -> 0 | AJ18: =SUMIFS('1-2 人员岗位信息'!H:H,'1-2 人员岗位信息'!$C:$C,"劳务派遣",'1-2 人员岗位信息'!$B:$B,$D18) -> 0 | AL18: =AM18*AN18 -> 0 | AM18: =SUMIFS('1-2 人员岗位信息'!I:I,'1-2 人员岗位信息'!$C:$C,"劳务派遣",'1-2 人员岗位信息'!$B:$B,$D18) -> 0 | AO18: =AP18*AQ18 -> 0 | AP18: =SUMIFS('1-2 人员岗位信息'!J:J,'1-2 人员岗位信息'!$C:$C,"劳务派遣",'1-2 人员岗位信息'!$B:$B,$D18) -> 0 | AR18: =AS18*AT18 -> 0 | AS18: =SUMIFS('1-2 人员岗位信息'!K:K,'1-2 人员岗位信息'!$C:$C,"劳务派遣",'1-2 人员岗位信息'!$B:$B,$D18) -> 0 | AU18: =AV18*AW18 -> 0 | AV18: =SUMIFS('1-2 人员岗位信息'!L:L,'1-2 人员岗位信息'!$C:$C,"劳务派遣",'1-2 人员岗位信息'!$B:$B,$D18) -> 0 | AX18: =AY18*AZ18 -> 0 | AY18: =SUMIFS('1-2 人员岗位信息'!M:M,'1-2 人员岗位信息'!$C:$C,"劳务派遣",'1-2 人员岗位信息'!$B:$B,$D18) -> 0 | BA18: =BB18*BC18 -> 0 | BB18: =SUMIFS('1-2 人员岗位信息'!N:N,'1-2 人员岗位信息'!$C:$C,"劳务派遣",'1-2 人员岗位信息'!$B:$B,$D18) -> 0 | BD18: =BE18*BF18 -> 0 | BE18: =SUMIFS('1-2 人员岗位信息'!O:O,'1-2 人员岗位信息'!$C:$C,"劳务派遣",'1-2 人员岗位信息'!$B:$B,$D18) -> 0 | BG18: =BH18*BI18 -> 0 | BH18: =SUMIFS('1-2 人员岗位信息'!P:P,'1-2 人员岗位信息'!$C:$C,"劳务派遣",'1-2 人员岗位信息'!$B:$B,$D18) -> 0 | BJ18: =BK18*BL18 -> 0 | BK18: =SUMIFS('1-2 人员岗位信息'!Q:Q,'1-2 人员岗位信息'!$C:$C,"劳务派遣",'1-2 人员岗位信息'!$B:$B,$D18) -> 0
B19: 是 | C19: 1.1.1.1.2.4 | D19: 巡逻岗员工 | E19: 含机动岗 | G19: 按月编制，汇总成年总量 | H19: =AB19 -> 0 | I19: 岗位数量 | J19: =SUM(AD19,AG19,AJ19,AM19,AP19,AS19,AV19,AY19,BB19,BE19,BH19,BK19)/N19 -> #DIV/0! | K19: 岗 | L19: =H19/N19/J19 -> #DIV/0! | M19: 元/㎡/月 | N19: =COUNTIF(AD19,">0")+COUNTIF(AG19,">0")+COUNTIF(AJ19,">0")+COUNTIF(AM19,">0")+COUNTIF(AP19,">0")+COUNTIF(AS19,">0")+COUNTIF(AV19,">0")+COUNTIF(AY19,">0")+COUNTIF(BB19,">0")+COUNTIF(BE19,">0")+COUNTIF(BH19,">0")+COUNTIF(BK19,">0") -> 0 | AB19: =SUM(AC19,AF19,AI19,AL19,AO19,AR19,AU19,AX19,BA19,BD19,BG19,BJ19) -> 0 | AC19: =AD19*AE19 -> 0 | AD19: ='1-2 人员岗位信息'!F24 -> 0 | AF19: =AG19*AH19 -> 0 | AG19: =SUMIFS('1-2 人员岗位信息'!G:G,'1-2 人员岗位信息'!$C:$C,"劳务派遣",'1-2 人员岗位信息'!$B:$B,$D19) -> 0 | AI19: =AJ19*AK19 -> 0 | AJ19: =SUMIFS('1-2 人员岗位信息'!H:H,'1-2 人员岗位信息'!$C:$C,"劳务派遣",'1-2 人员岗位信息'!$B:$B,$D19) -> 0 | AL19: =AM19*AN19 -> 0 | AM19: =SUMIFS('1-2 人员岗位信息'!I:I,'1-2 人员岗位信息'!$C:$C,"劳务派遣",'1-2 人员岗位信息'!$B:$B,$D19) -> 0 | AO19: =AP19*AQ19 -> 0 | AP19: =SUMIFS('1-2 人员岗位信息'!J:J,'1-2 人员岗位信息'!$C:$C,"劳务派遣",'1-2 人员岗位信息'!$B:$B,$D19) -> 0 | AR19: =AS19*AT19 -> 0 | AS19: =SUMIFS('1-2 人员岗位信息'!K:K,'1-2 人员岗位信息'!$C:$C,"劳务派遣",'1-2 人员岗位信息'!$B:$B,$D19) -> 0 | AU19: =AV19*AW19 -> 0 | AV19: =SUMIFS('1-2 人员岗位信息'!L:L,'1-2 人员岗位信息'!$C:$C,"劳务派遣",'1-2 人员岗位信息'!$B:$B,$D19) -> 0 | AX19: =AY19*AZ19 -> 0 | AY19: =SUMIFS('1-2 人员岗位信息'!M:M,'1-2 人员岗位信息'!$C:$C,"劳务派遣",'1-2 人员岗位信息'!$B:$B,$D19) -> 0 | BA19: =BB19*BC19 -> 0 | BB19: =SUMIFS('1-2 人员岗位信息'!N:N,'1-2 人员岗位信息'!$C:$C,"劳务派遣",'1-2 人员岗位信息'!$B:$B,$D19) -> 0 | BD19: =BE19*BF19 -> 0 | BE19: =SUMIFS('1-2 人员岗位信息'!O:O,'1-2 人员岗位信息'!$C:$C,"劳务派遣",'1-2 人员岗位信息'!$B:$B,$D19) -> 0 | BG19: =BH19*BI19 -> 0 | BH19: =SUMIFS('1-2 人员岗位信息'!P:P,'1-2 人员岗位信息'!$C:$C,"劳务派遣",'1-2 人员岗位信息'!$B:$B,$D19) -> 0 | BJ19: =BK19*BL19 -> 0 | BK19: =SUMIFS('1-2 人员岗位信息'!Q:Q,'1-2 人员岗位信息'!$C:$C,"劳务派遣",'1-2 人员岗位信息'!$B:$B,$D19) -> 0
B20: 是 | C20: 1.1.1.1.2.5 | D20: 中控岗员工 | E20: 指中控室、监控室人员 | G20: 按月编制，汇总成年总量 | H20: =AB20 -> 0 | I20: 岗位数量 | J20: =SUM(AD20,AG20,AJ20,AM20,AP20,AS20,AV20,AY20,BB20,BE20,BH20,BK20)/N20 -> #DIV/0! | K20: 岗 | L20: =H20/N20/J20 -> #DIV/0! | M20: 元/㎡/月 | N20: =COUNTIF(AD20,">0")+COUNTIF(AG20,">0")+COUNTIF(AJ20,">0")+COUNTIF(AM20,">0")+COUNTIF(AP20,">0")+COUNTIF(AS20,">0")+COUNTIF(AV20,">0")+COUNTIF(AY20,">0")+COUNTIF(BB20,">0")+COUNTIF(BE20,">0")+COUNTIF(BH20,">0")+COUNTIF(BK20,">0") -> 0 | AB20: =SUM(AC20,AF20,AI20,AL20,AO20,AR20,AU20,AX20,BA20,BD20,BG20,BJ20) -> 0 | AC20: =AD20*AE20 -> 0 | AD20: ='1-2 人员岗位信息'!F28 -> 0 | AF20: =AG20*AH20 -> 0 | AG20: =SUMIFS('1-2 人员岗位信息'!G:G,'1-2 人员岗位信息'!$C:$C,"劳务派遣",'1-2 人员岗位信息'!$B:$B,$D20) -> 0 | AI20: =AJ20*AK20 -> 0 | AJ20: =SUMIFS('1-2 人员岗位信息'!H:H,'1-2 人员岗位信息'!$C:$C,"劳务派遣",'1-2 人员岗位信息'!$B:$B,$D20) -> 0 | AL20: =AM20*AN20 -> 0 | AM20: =SUMIFS('1-2 人员岗位信息'!I:I,'1-2 人员岗位信息'!$C:$C,"劳务派遣",'1-2 人员岗位信息'!$B:$B,$D20) -> 0 | AO20: =AP20*AQ20 -> 0 | AP20: =SUMIFS('1-2 人员岗位信息'!J:J,'1-2 人员岗位信息'!$C:$C,"劳务派遣",'1-2 人员岗位信息'!$B:$B,$D20) -> 0 | AR20: =AS20*AT20 -> 0 | AS20: =SUMIFS('1-2 人员岗位信息'!K:K,'1-2 人员岗位信息'!$C:$C,"劳务派遣",'1-2 人员岗位信息'!$B:$B,$D20) -> 0 | AU20: =AV20*AW20 -> 0 | AV20: =SUMIFS('1-2 人员岗位信息'!L:L,'1-2 人员岗位信息'!$C:$C,"劳务派遣",'1-2 人员岗位信息'!$B:$B,$D20) -> 0 | AX20: =AY20*AZ20 -> 0 | AY20: =SUMIFS('1-2 人员岗位信息'!M:M,'1-2 人员岗位信息'!$C:$C,"劳务派遣",'1-2 人员岗位信息'!$B:$B,$D20) -> 0 | BA20: =BB20*BC20 -> 0 | BB20: =SUMIFS('1-2 人员岗位信息'!N:N,'1-2 人员岗位信息'!$C:$C,"劳务派遣",'1-2 人员岗位信息'!$B:$B,$D20) -> 0 | BD20: =BE20*BF20 -> 0 | BE20: =SUMIFS('1-2 人员岗位信息'!O:O,'1-2 人员岗位信息'!$C:$C,"劳务派遣",'1-2 人员岗位信息'!$B:$B,$D20) -> 0 | BG20: =BH20*BI20 -> 0 | BH20: =SUMIFS('1-2 人员岗位信息'!P:P,'1-2 人员岗位信息'!$C:$C,"劳务派遣",'1-2 人员岗位信息'!$B:$B,$D20) -> 0 | BJ20: =BK20*BL20 -> 0 | BK20: =SUMIFS('1-2 人员岗位信息'!Q:Q,'1-2 人员岗位信息'!$C:$C,"劳务派遣",'1-2 人员岗位信息'!$B:$B,$D20) -> 0
B21: 是 | C21: 1.1.1.1.2.6 | D21: 其他保安员工 | E21: 上述不包含的岗位可适用此项 | G21: 按月编制，汇总成年总量 | H21: =AB21 -> 0 | I21: 岗位数量 | J21: =SUM(AD21,AG21,AJ21,AM21,AP21,AS21,AV21,AY21,BB21,BE21,BH21,BK21)/N21 -> #DIV/0! | K21: 岗 | L21: =H21/N21/J21 -> #DIV/0! | M21: 元/㎡/月 | N21: =COUNTIF(AD21,">0")+COUNTIF(AG21,">0")+COUNTIF(AJ21,">0")+COUNTIF(AM21,">0")+COUNTIF(AP21,">0")+COUNTIF(AS21,">0")+COUNTIF(AV21,">0")+COUNTIF(AY21,">0")+COUNTIF(BB21,">0")+COUNTIF(BE21,">0")+COUNTIF(BH21,">0")+COUNTIF(BK21,">0") -> 0 | AB21: =SUM(AC21,AF21,AI21,AL21,AO21,AR21,AU21,AX21,BA21,BD21,BG21,BJ21) -> 0 | AC21: =AD21*AE21 -> 0 | AD21: ='1-2 人员岗位信息'!F32 -> 0 | AF21: =AG21*AH21 -> 0 | AG21: =SUMIFS('1-2 人员岗位信息'!G:G,'1-2 人员岗位信息'!$C:$C,"劳务派遣",'1-2 人员岗位信息'!$B:$B,$D21) -> 0 | AI21: =AJ21*AK21 -> 0 | AJ21: =SUMIFS('1-2 人员岗位信息'!H:H,'1-2 人员岗位信息'!$C:$C,"劳务派遣",'1-2 人员岗位信息'!$B:$B,$D21) -> 0 | AL21: =AM21*AN21 -> 0 | AM21: =SUMIFS('1-2 人员岗位信息'!I:I,'1-2 人员岗位信息'!$C:$C,"劳务派遣",'1-2 人员岗位信息'!$B:$B,$D21) -> 0 | AO21: =AP21*AQ21 -> 0 | AP21: =SUMIFS('1-2 人员岗位信息'!J:J,'1-2 人员岗位信息'!$C:$C,"劳务派遣",'1-2 人员岗位信息'!$B:$B,$D21) -> 0 | AR21: =AS21*AT21 -> 0 | AS21: =SUMIFS('1-2 人员岗位信息'!K:K,'1-2 人员岗位信息'!$C:$C,"劳务派遣",'1-2 人员岗位信息'!$B:$B,$D21) -> 0 | AU21: =AV21*AW21 -> 0 | AV21: =SUMIFS('1-2 人员岗位信息'!L:L,'1-2 人员岗位信息'!$C:$C,"劳务派遣",'1-2 人员岗位信息'!$B:$B,$D21) -> 0 | AX21: =AY21*AZ21 -> 0 | AY21: =SUMIFS('1-2 人员岗位信息'!M:M,'1-2 人员岗位信息'!$C:$C,"劳务派遣",'1-2 人员岗位信息'!$B:$B,$D21) -> 0 | BA21: =BB21*BC21 -> 0 | BB21: =SUMIFS('1-2 人员岗位信息'!N:N,'1-2 人员岗位信息'!$C:$C,"劳务派遣",'1-2 人员岗位信息'!$B:$B,$D21) -> 0 | BD21: =BE21*BF21 -> 0 | BE21: =SUMIFS('1-2 人员岗位信息'!O:O,'1-2 人员岗位信息'!$C:$C,"劳务派遣",'1-2 人员岗位信息'!$B:$B,$D21) -> 0 | BG21: =BH21*BI21 -> 0 | BH21: =SUMIFS('1-2 人员岗位信息'!P:P,'1-2 人员岗位信息'!$C:$C,"劳务派遣",'1-2 人员岗位信息'!$B:$B,$D21) -> 0 | BJ21: =BK20*BL21 -> 0 | BK21: =SUMIFS('1-2 人员岗位信息'!Q:Q,'1-2 人员岗位信息'!$C:$C,"劳务派遣",'1-2 人员岗位信息'!$B:$B,$D21) -> 0
B22: 否 | C22: 1.1.1.1.3 | D22: 专业外包 | H22: =SUM(H23:H28) -> 0 | AB22: =SUM(AB23:AB28) -> 0 | AC22: =SUM(AC23:AC28) -> 0 | AF22: =SUM(AF23:AF28) -> 0 | AI22: =SUM(AI23:AI28) -> 0 | AL22: =SUM(AL23:AL28) -> 0 | AO22: =SUM(AO23:AO28) -> 0 | AR22: =SUM(AR23:AR28) -> 0 | AU22: =SUM(AU23:AU28) -> 0 | AX22: =SUM(AX23:AX28) -> 0 | BA22: =SUM(BA23:BA28) -> 0 | BD22: =SUM(BD23:BD28) -> 0 | BG22: =SUM(BG23:BG28) -> 0 | BJ22: =SUM(BJ23:BJ28) -> 0
B23: 是 | C23: 1.1.1.1.3.1 | D23: 保安经理 | E23: 指外包保安经理 | G23: 按月编制，汇总成年总量 | H23: =AB23 -> 0 | I23: 岗位数量 | J23: =SUM(AD23,AG23,AJ23,AM23,AP23,AS23,AV23,AY23,BB23,BE23,BH23,BK23)/N23 -> #DIV/0! | K23: 岗 | L23: =H23/N23/J23 -> #DIV/0! | M23: 元/㎡/月 | N23: =COUNTIF(AD23,">0")+COUNTIF(AG23,">0")+COUNTIF(AJ23,">0")+COUNTIF(AM23,">0")+COUNTIF(AP23,">0")+COUNTIF(AS23,">0")+COUNTIF(AV23,">0")+COUNTIF(AY23,">0")+COUNTIF(BB23,">0")+COUNTIF(BE23,">0")+COUNTIF(BH23,">0")+COUNTIF(BK23,">0") -> 0 | AB23: =SUM(AC23,AF23,AI23,AL23,AO23,AR23,AU23,AX23,BA23,BD23,BG23,BJ23) -> 0 | AC23: =AD23*AE23 -> 0 | AD23: ='1-2 人员岗位信息'!F13 -> 0 | AE23: =IFERROR(预算主表!P80/(12*AD23),0) -> 0 | AF23: =AG23*AH23 -> 0 | AG23: =SUMIFS('1-2 人员岗位信息'!G:G,'1-2 人员岗位信息'!$C:$C,"专业外包",'1-2 人员岗位信息'!$B:$B,$D23) -> 0 | AH23: =AE23 -> 0 | AI23: =AJ23*AK23 -> 0 | AJ23: =SUMIFS('1-2 人员岗位信息'!H:H,'1-2 人员岗位信息'!$C:$C,"专业外包",'1-2 人员岗位信息'!$B:$B,$D23) -> 0 | AK23: =AE23 -> 0 | AL23: =AM23*AN23 -> 0 | AM23: =SUMIFS('1-2 人员岗位信息'!I:I,'1-2 人员岗位信息'!$C:$C,"专业外包",'1-2 人员岗位信息'!$B:$B,$D23) -> 0 | AN23: =AE23 -> 0 | AO23: =AP23*AQ23 -> 0 | AP23: =SUMIFS('1-2 人员岗位信息'!J:J,'1-2 人员岗位信息'!$C:$C,"专业外包",'1-2 人员岗位信息'!$B:$B,$D23) -> 0 | AQ23: =AE23 -> 0 | AR23: =AS23*AT23 -> 0 | AS23: =SUMIFS('1-2 人员岗位信息'!K:K,'1-2 人员岗位信息'!$C:$C,"专业外包",'1-2 人员岗位信息'!$B:$B,$D23) -> 0 | AT23: =AE23 -> 0 | AU23: =AV23*AW23 -> 0 | AV23: =SUMIFS('1-2 人员岗位信息'!L:L,'1-2 人员岗位信息'!$C:$C,"专业外包",'1-2 人员岗位信息'!$B:$B,$D23) -> 0 | AW23: =AE23 -> 0 | AX23: =AY23*AZ23 -> 0 | AY23: =SUMIFS('1-2 人员岗位信息'!M:M,'1-2 人员岗位信息'!$C:$C,"专业外包",'1-2 人员岗位信息'!$B:$B,$D23) -> 0 | AZ23: =AE23 -> 0 | BA23: =BB23*BC23 -> 0 | BB23: =SUMIFS('1-2 人员岗位信息'!N:N,'1-2 人员岗位信息'!$C:$C,"专业外包",'1-2 人员岗位信息'!$B:$B,$D23) -> 0 | BC23: =AE23 -> 0 | BD23: =BE23*BF23 -> 0 | BE23: =SUMIFS('1-2 人员岗位信息'!O:O,'1-2 人员岗位信息'!$C:$C,"专业外包",'1-2 人员岗位信息'!$B:$B,$D23) -> 0 | BF23: =AE23 -> 0 | BG23: =BH23*BI23 -> 0 | BH23: =SUMIFS('1-2 人员岗位信息'!P:P,'1-2 人员岗位信息'!$C:$C,"专业外包",'1-2 人员岗位信息'!$B:$B,$D23) -> 0 | BI23: =AE23 -> 0 | BJ23: =BK23*BL23 -> 0 | BK23: =SUMIFS('1-2 人员岗位信息'!Q:Q,'1-2 人员岗位信息'!$C:$C,"专业外包",'1-2 人员岗位信息'!$B:$B,$D23) -> 0 | BL23: =AE23 -> 0
B24: 是 | C24: 1.1.1.1.3.2 | D24: 保安主管 | E24: 指外包保安主管 | G24: 按月编制，汇总成年总量 | H24: =AB24 -> 0 | I24: 岗位数量 | J24: =SUM(AD24,AG24,AJ24,AM24,AP24,AS24,AV24,AY24,BB24,BE24,BH24,BK24)/N24 -> #DIV/0! | K24: 岗 | L24: =H24/N24/J24 -> #DIV/0! | M24: 元/㎡/月 | N24: =COUNTIF(AD24,">0")+COUNTIF(AG24,">0")+COUNTIF(AJ24,">0")+COUNTIF(AM24,">0")+COUNTIF(AP24,">0")+COUNTIF(AS24,">0")+COUNTIF(AV24,">0")+COUNTIF(AY24,">0")+COUNTIF(BB24,">0")+COUNTIF(BE24,">0")+COUNTIF(BH24,">0")+COUNTIF(BK24,">0") -> 0 | AB24: =SUM(AC24,AF24,AI24,AL24,AO24,AR24,AU24,AX24,BA24,BD24,BG24,BJ24) -> 0 | AC24: =AD24*AE24 -> 0 | AD24: ='1-2 人员岗位信息'!F17 -> 0 | AF24: =AG24*AH24 -> 0 | AG24: =SUMIFS('1-2 人员岗位信息'!G:G,'1-2 人员岗位信息'!$C:$C,"专业外包",'1-2 人员岗位信息'!$B:$B,$D24) -> 0 | AI24: =AJ24*AK24 -> 0 | AJ24: =SUMIFS('1-2 人员岗位信息'!H:H,'1-2 人员岗位信息'!$C:$C,"专业外包",'1-2 人员岗位信息'!$B:$B,$D24) -> 0 | AL24: =AM24*AN24 -> 0 | AM24: =SUMIFS('1-2 人员岗位信息'!I:I,'1-2 人员岗位信息'!$C:$C,"专业外包",'1-2 人员岗位信息'!$B:$B,$D24) -> 0 | AO24: =AP24*AQ24 -> 0 | AP24: =SUMIFS('1-2 人员岗位信息'!J:J,'1-2 人员岗位信息'!$C:$C,"专业外包",'1-2 人员岗位信息'!$B:$B,$D24) -> 0 | AR24: =AS24*AT24 -> 0 | AS24: =SUMIFS('1-2 人员岗位信息'!K:K,'1-2 人员岗位信息'!$C:$C,"专业外包",'1-2 人员岗位信息'!$B:$B,$D24) -> 0 | AU24: =AV24*AW24 -> 0 | AV24: =SUMIFS('1-2 人员岗位信息'!L:L,'1-2 人员岗位信息'!$C:$C,"专业外包",'1-2 人员岗位信息'!$B:$B,$D24) -> 0 | AX24: =AY24*AZ24 -> 0 | AY24: =SUMIFS('1-2 人员岗位信息'!M:M,'1-2 人员岗位信息'!$C:$C,"专业外包",'1-2 人员岗位信息'!$B:$B,$D24) -> 0 | BA24: =BB24*BC24 -> 0 | BB24: =SUMIFS('1-2 人员岗位信息'!N:N,'1-2 人员岗位信息'!$C:$C,"专业外包",'1-2 人员岗位信息'!$B:$B,$D24) -> 0 | BD24: =BE24*BF24 -> 0 | BE24: =SUMIFS('1-2 人员岗位信息'!O:O,'1-2 人员岗位信息'!$C:$C,"专业外包",'1-2 人员岗位信息'!$B:$B,$D24) -> 0 | BG24: =BH24*BI24 -> 0 | BH24: =SUMIFS('1-2 人员岗位信息'!P:P,'1-2 人员岗位信息'!$C:$C,"专业外包",'1-2 人员岗位信息'!$B:$B,$D24) -> 0 | BJ24: =BK24*BL24 -> 0 | BK24: =SUMIFS('1-2 人员岗位信息'!Q:Q,'1-2 人员岗位信息'!$C:$C,"专业外包",'1-2 人员岗位信息'!$B:$B,$D24) -> 0
B25: 是 | C25: 1.1.1.1.3.3 | D25: 门岗员工 | E25: 含车岗、形象岗、商写礼宾岗 | G25: 按月编制，汇总成年总量 | H25: =AB25 -> 0 | I25: 岗位数量 | J25: =SUM(AD25,AG25,AJ25,AM25,AP25,AS25,AV25,AY25,BB25,BE25,BH25,BK25)/N25 -> #DIV/0! | K25: 岗 | L25: =H25/N25/J25 -> #DIV/0! | M25: 元/㎡/月 | N25: =COUNTIF(AD25,">0")+COUNTIF(AG25,">0")+COUNTIF(AJ25,">0")+COUNTIF(AM25,">0")+COUNTIF(AP25,">0")+COUNTIF(AS25,">0")+COUNTIF(AV25,">0")+COUNTIF(AY25,">0")+COUNTIF(BB25,">0")+COUNTIF(BE25,">0")+COUNTIF(BH25,">0")+COUNTIF(BK25,">0") -> 0 | AB25: =SUM(AC25,AF25,AI25,AL25,AO25,AR25,AU25,AX25,BA25,BD25,BG25,BJ25) -> 0 | AC25: =AD25*AE25 -> 0 | AD25: ='1-2 人员岗位信息'!F21 -> 0 | AF25: =AG25*AH25 -> 0 | AG25: =SUMIFS('1-2 人员岗位信息'!G:G,'1-2 人员岗位信息'!$C:$C,"专业外包",'1-2 人员岗位信息'!$B:$B,$D25) -> 0 | AI25: =AJ25*AK25 -> 0 | AJ25: =SUMIFS('1-2 人员岗位信息'!H:H,'1-2 人员岗位信息'!$C:$C,"专业外包",'1-2 人员岗位信息'!$B:$B,$D25) -> 0 | AL25: =AM25*AN25 -> 0 | AM25: =SUMIFS('1-2 人员岗位信息'!I:I,'1-2 人员岗位信息'!$C:$C,"专业外包",'1-2 人员岗位信息'!$B:$B,$D25) -> 0 | AO25: =AP25*AQ25 -> 0 | AP25: =SUMIFS('1-2 人员岗位信息'!J:J,'1-2 人员岗位信息'!$C:$C,"专业外包",'1-2 人员岗位信息'!$B:$B,$D25) -> 0 | AR25: =AS25*AT25 -> 0 | AS25: =SUMIFS('1-2 人员岗位信息'!K:K,'1-2 人员岗位信息'!$C:$C,"专业外包",'1-2 人员岗位信息'!$B:$B,$D25) -> 0 | AU25: =AV25*AW25 -> 0 | AV25: =SUMIFS('1-2 人员岗位信息'!L:L,'1-2 人员岗位信息'!$C:$C,"专业外包",'1-2 人员岗位信息'!$B:$B,$D25) -> 0 | AX25: =AY25*AZ25 -> 0 | AY25: =SUMIFS('1-2 人员岗位信息'!M:M,'1-2 人员岗位信息'!$C:$C,"专业外包",'1-2 人员岗位信息'!$B:$B,$D25) -> 0 | BA25: =BB25*BC25 -> 0 | BB25: =SUMIFS('1-2 人员岗位信息'!N:N,'1-2 人员岗位信息'!$C:$C,"专业外包",'1-2 人员岗位信息'!$B:$B,$D25) -> 0 | BD25: =BE25*BF25 -> 0 | BE25: =SUMIFS('1-2 人员岗位信息'!O:O,'1-2 人员岗位信息'!$C:$C,"专业外包",'1-2 人员岗位信息'!$B:$B,$D25) -> 0 | BG25: =BH25*BI25 -> 0 | BH25: =SUMIFS('1-2 人员岗位信息'!P:P,'1-2 人员岗位信息'!$C:$C,"专业外包",'1-2 人员岗位信息'!$B:$B,$D25) -> 0 | BJ25: =BK25*BL25 -> 0 | BK25: =SUMIFS('1-2 人员岗位信息'!Q:Q,'1-2 人员岗位信息'!$C:$C,"专业外包",'1-2 人员岗位信息'!$B:$B,$D25) -> 0
B26: 是 | C26: 1.1.1.1.3.4 | D26: 巡逻岗员工 | E26: 含机动岗 | G26: 按月编制，汇总成年总量 | H26: =AB26 -> 0 | I26: 岗位数量 | J26: =SUM(AD26,AG26,AJ26,AM26,AP26,AS26,AV26,AY26,BB26,BE26,BH26,BK26)/N26 -> #DIV/0! | K26: 岗 | L26: =H26/N26/J26 -> #DIV/0! | M26: 元/㎡/月 | N26: =COUNTIF(AD26,">0")+COUNTIF(AG26,">0")+COUNTIF(AJ26,">0")+COUNTIF(AM26,">0")+COUNTIF(AP26,">0")+COUNTIF(AS26,">0")+COUNTIF(AV26,">0")+COUNTIF(AY26,">0")+COUNTIF(BB26,">0")+COUNTIF(BE26,">0")+COUNTIF(BH26,">0")+COUNTIF(BK26,">0") -> 0 | AB26: =SUM(AC26,AF26,AI26,AL26,AO26,AR26,AU26,AX26,BA26,BD26,BG26,BJ26) -> 0 | AC26: =AD26*AE26 -> 0 | AD26: ='1-2 人员岗位信息'!F25 -> 0 | AF26: =AG26*AH26 -> 0 | AG26: =SUMIFS('1-2 人员岗位信息'!G:G,'1-2 人员岗位信息'!$C:$C,"专业外包",'1-2 人员岗位信息'!$B:$B,$D26) -> 0 | AI26: =AJ26*AK26 -> 0 | AJ26: =SUMIFS('1-2 人员岗位信息'!H:H,'1-2 人员岗位信息'!$C:$C,"专业外包",'1-2 人员岗位信息'!$B:$B,$D26) -> 0 | AL26: =AM26*AN26 -> 0 | AM26: =SUMIFS('1-2 人员岗位信息'!I:I,'1-2 人员岗位信息'!$C:$C,"专业外包",'1-2 人员岗位信息'!$B:$B,$D26) -> 0 | AO26: =AP26*AQ26 -> 0 | AP26: =SUMIFS('1-2 人员岗位信息'!J:J,'1-2 人员岗位信息'!$C:$C,"专业外包",'1-2 人员岗位信息'!$B:$B,$D26) -> 0 | AR26: =AS26*AT26 -> 0 | AS26: =SUMIFS('1-2 人员岗位信息'!K:K,'1-2 人员岗位信息'!$C:$C,"专业外包",'1-2 人员岗位信息'!$B:$B,$D26) -> 0 | AU26: =AV26*AW26 -> 0 | AV26: =SUMIFS('1-2 人员岗位信息'!L:L,'1-2 人员岗位信息'!$C:$C,"专业外包",'1-2 人员岗位信息'!$B:$B,$D26) -> 0 | AX26: =AY26*AZ26 -> 0 | AY26: =SUMIFS('1-2 人员岗位信息'!M:M,'1-2 人员岗位信息'!$C:$C,"专业外包",'1-2 人员岗位信息'!$B:$B,$D26) -> 0 | BA26: =BB26*BC26 -> 0 | BB26: =SUMIFS('1-2 人员岗位信息'!N:N,'1-2 人员岗位信息'!$C:$C,"专业外包",'1-2 人员岗位信息'!$B:$B,$D26) -> 0 | BD26: =BE26*BF26 -> 0 | BE26: =SUMIFS('1-2 人员岗位信息'!O:O,'1-2 人员岗位信息'!$C:$C,"专业外包",'1-2 人员岗位信息'!$B:$B,$D26) -> 0 | BG26: =BH26*BI26 -> 0 | BH26: =SUMIFS('1-2 人员岗位信息'!P:P,'1-2 人员岗位信息'!$C:$C,"专业外包",'1-2 人员岗位信息'!$B:$B,$D26) -> 0 | BJ26: =BK26*BL26 -> 0 | BK26: =SUMIFS('1-2 人员岗位信息'!Q:Q,'1-2 人员岗位信息'!$C:$C,"专业外包",'1-2 人员岗位信息'!$B:$B,$D26) -> 0
B27: 是 | C27: 1.1.1.1.3.5 | D27: 中控岗员工 | E27: 指中控室、监控室人员 | G27: 按月编制，汇总成年总量 | H27: =AB27 -> 0 | I27: 岗位数量 | J27: =SUM(AD27,AG27,AJ27,AM27,AP27,AS27,AV27,AY27,BB27,BE27,BH27,BK27)/N27 -> #DIV/0! | K27: 岗 | L27: =H27/N27/J27 -> #DIV/0! | M27: 元/㎡/月 | N27: =COUNTIF(AD27,">0")+COUNTIF(AG27,">0")+COUNTIF(AJ27,">0")+COUNTIF(AM27,">0")+COUNTIF(AP27,">0")+COUNTIF(AS27,">0")+COUNTIF(AV27,">0")+COUNTIF(AY27,">0")+COUNTIF(BB27,">0")+COUNTIF(BE27,">0")+COUNTIF(BH27,">0")+COUNTIF(BK27,">0") -> 0 | AB27: =SUM(AC27,AF27,AI27,AL27,AO27,AR27,AU27,AX27,BA27,BD27,BG27,BJ27) -> 0 | AC27: =AD27*AE27 -> 0 | AD27: ='1-2 人员岗位信息'!F29 -> 0 | AF27: =AG27*AH27 -> 0 | AG27: =SUMIFS('1-2 人员岗位信息'!G:G,'1-2 人员岗位信息'!$C:$C,"专业外包",'1-2 人员岗位信息'!$B:$B,$D27) -> 0 | AI27: =AJ27*AK27 -> 0 | AJ27: =SUMIFS('1-2 人员岗位信息'!H:H,'1-2 人员岗位信息'!$C:$C,"专业外包",'1-2 人员岗位信息'!$B:$B,$D27) -> 0 | AL27: =AM27*AN27 -> 0 | AM27: =SUMIFS('1-2 人员岗位信息'!I:I,'1-2 人员岗位信息'!$C:$C,"专业外包",'1-2 人员岗位信息'!$B:$B,$D27) -> 0 | AO27: =AP27*AQ27 -> 0 | AP27: =SUMIFS('1-2 人员岗位信息'!J:J,'1-2 人员岗位信息'!$C:$C,"专业外包",'1-2 人员岗位信息'!$B:$B,$D27) -> 0 | AR27: =AS27*AT27 -> 0 | AS27: =SUMIFS('1-2 人员岗位信息'!K:K,'1-2 人员岗位信息'!$C:$C,"专业外包",'1-2 人员岗位信息'!$B:$B,$D27) -> 0 | AU27: =AV27*AW27 -> 0 | AV27: =SUMIFS('1-2 人员岗位信息'!L:L,'1-2 人员岗位信息'!$C:$C,"专业外包",'1-2 人员岗位信息'!$B:$B,$D27) -> 0 | AX27: =AY27*AZ27 -> 0 | AY27: =SUMIFS('1-2 人员岗位信息'!M:M,'1-2 人员岗位信息'!$C:$C,"专业外包",'1-2 人员岗位信息'!$B:$B,$D27) -> 0 | BA27: =BB27*BC27 -> 0 | BB27: =SUMIFS('1-2 人员岗位信息'!N:N,'1-2 人员岗位信息'!$C:$C,"专业外包",'1-2 人员岗位信息'!$B:$B,$D27) -> 0 | BD27: =BE27*BF27 -> 0 | BE27: =SUMIFS('1-2 人员岗位信息'!O:O,'1-2 人员岗位信息'!$C:$C,"专业外包",'1-2 人员岗位信息'!$B:$B,$D27) -> 0 | BG27: =BH27*BI27 -> 0 | BH27: =SUMIFS('1-2 人员岗位信息'!P:P,'1-2 人员岗位信息'!$C:$C,"专业外包",'1-2 人员岗位信息'!$B:$B,$D27) -> 0 | BJ27: =BK27*BL27 -> 0 | BK27: =SUMIFS('1-2 人员岗位信息'!Q:Q,'1-2 人员岗位信息'!$C:$C,"专业外包",'1-2 人员岗位信息'!$B:$B,$D27) -> 0
B28: 是 | C28: 1.1.1.1.3.6 | D28: 其他保安员工 | E28: 上述不包含的岗位可适用此项 | G28: 按月编制，汇总成年总量 | H28: =AB28 -> 0 | I28: 岗位数量 | J28: =SUM(AD28,AG28,AJ28,AM28,AP28,AS28,AV28,AY28,BB28,BE28,BH28,BK28)/N28 -> #DIV/0! | K28: 岗 | L28: =H28/N28/J28 -> #DIV/0! | M28: 元/㎡/月 | N28: =COUNTIF(AD28,">0")+COUNTIF(AG28,">0")+COUNTIF(AJ28,">0")+COUNTIF(AM28,">0")+COUNTIF(AP28,">0")+COUNTIF(AS28,">0")+COUNTIF(AV28,">0")+COUNTIF(AY28,">0")+COUNTIF(BB28,">0")+COUNTIF(BE28,">0")+COUNTIF(BH28,">0")+COUNTIF(BK28,">0") -> 0 | AB28: =SUM(AC28,AF28,AI28,AL28,AO28,AR28,AU28,AX28,BA28,BD28,BG28,BJ28) -> 0 | AC28: =AD28*AE28 -> 0 | AD28: ='1-2 人员岗位信息'!F33 -> 0 | AF28: =AG28*AH28 -> 0 | AG28: =SUMIFS('1-2 人员岗位信息'!G:G,'1-2 人员岗位信息'!$C:$C,"专业外包",'1-2 人员岗位信息'!$B:$B,$D28) -> 0 | AI28: =AJ28*AK28 -> 0 | AJ28: =SUMIFS('1-2 人员岗位信息'!H:H,'1-2 人员岗位信息'!$C:$C,"专业外包",'1-2 人员岗位信息'!$B:$B,$D28) -> 0 | AL28: =AM28*AN28 -> 0 | AM28: =SUMIFS('1-2 人员岗位信息'!I:I,'1-2 人员岗位信息'!$C:$C,"专业外包",'1-2 人员岗位信息'!$B:$B,$D28) -> 0 | AO28: =AP28*AQ28 -> 0 | AP28: =SUMIFS('1-2 人员岗位信息'!J:J,'1-2 人员岗位信息'!$C:$C,"专业外包",'1-2 人员岗位信息'!$B:$B,$D28) -> 0 | AR28: =AS28*AT28 -> 0 | AS28: =SUMIFS('1-2 人员岗位信息'!K:K,'1-2 人员岗位信息'!$C:$C,"专业外包",'1-2 人员岗位信息'!$B:$B,$D28) -> 0 | AU28: =AV28*AW28 -> 0 | AV28: =SUMIFS('1-2 人员岗位信息'!L:L,'1-2 人员岗位信息'!$C:$C,"专业外包",'1-2 人员岗位信息'!$B:$B,$D28) -> 0 | AX28: =AY28*AZ28 -> 0 | AY28: =SUMIFS('1-2 人员岗位信息'!M:M,'1-2 人员岗位信息'!$C:$C,"专业外包",'1-2 人员岗位信息'!$B:$B,$D28) -> 0 | BA28: =BB28*BC28 -> 0 | BB28: =SUMIFS('1-2 人员岗位信息'!N:N,'1-2 人员岗位信息'!$C:$C,"专业外包",'1-2 人员岗位信息'!$B:$B,$D28) -> 0 | BD28: =BE28*BF28 -> 0 | BE28: =SUMIFS('1-2 人员岗位信息'!O:O,'1-2 人员岗位信息'!$C:$C,"专业外包",'1-2 人员岗位信息'!$B:$B,$D28) -> 0 | BG28: =BH28*BI28 -> 0 | BH28: =SUMIFS('1-2 人员岗位信息'!P:P,'1-2 人员岗位信息'!$C:$C,"专业外包",'1-2 人员岗位信息'!$B:$B,$D28) -> 0 | BJ28: =BK28*BL28 -> 0 | BK28: =SUMIFS('1-2 人员岗位信息'!Q:Q,'1-2 人员岗位信息'!$C:$C,"专业外包",'1-2 人员岗位信息'!$B:$B,$D28) -> 0
B29: 否 | C29: 1.1.1.2 | D29: 客服人员 | H29: =H30+H39+H48 -> 1409128.8 | AB29: =AB30+AB39+AB48 -> 1409128.8 | AC29: =AC30+AC39+AC48 -> 120168.23 | AF29: =AF30+AF39+AF48 -> 117178.23 | AI29: =AI30+AI39+AI48 -> 117178.23 | AL29: =AL30+AL39+AL48 -> 117178.23 | AO29: =AO30+AO39+AO48 -> 117178.23 | AR29: =AR30+AR39+AR48 -> 117178.23 | AU29: =AU30+AU39+AU48 -> 117178.23 | AX29: =AX30+AX39+AX48 -> 117178.23 | BA29: =BA30+BA39+BA48 -> 117178.23 | BD29: =BD30+BD39+BD48 -> 117178.23 | BG29: =BG30+BG39+BG48 -> 117178.23 | BJ29: =BJ30+BJ39+BJ48 -> 117178.23
B30: 否 | C30: 1.1.1.2.1 | D30: 自有人员 | H30: =SUM(H31:H38) -> 1409128.8 | AB30: =SUM(AB31:AB38) -> 1409128.8 | AC30: =SUM(AC31:AC38) -> 120168.23 | AF30: =SUM(AF31:AF38) -> 117178.23 | AI30: =SUM(AI31:AI38) -> 117178.23 | AL30: =SUM(AL31:AL38) -> 117178.23 | AO30: =SUM(AO31:AO38) -> 117178.23 | AR30: =SUM(AR31:AR38) -> 117178.23 | AU30: =SUM(AU31:AU38) -> 117178.23 | AX30: =SUM(AX31:AX38) -> 117178.23 | BA30: =SUM(BA31:BA38) -> 117178.23 | BD30: =SUM(BD31:BD38) -> 117178.23 | BG30: =SUM(BG31:BG38) -> 117178.23 | BJ30: =SUM(BJ31:BJ38) -> 117178.23
B31: 是 | C31: 1.1.1.2.1.1 | D31: 客服经理 | E31: 指自有客服经理 | G31: 按月编制，汇总成年总量 | H31: =AB31 -> 1409128.8 | I31: 岗位数量 | J31: =SUM(AD31,AG31,AJ31,AM31,AP31,AS31,AV31,AY31,BB31,BE31,BH31,BK31)/N31 -> 13 | K31: 岗 | L31: =H31/N31/J31 -> 9032.8767 | M31: 元/㎡/月 | N31: =COUNTIF(AD31,">0")+COUNTIF(AG31,">0")+COUNTIF(AJ31,">0")+COUNTIF(AM31,">0")+COUNTIF(AP31,">0")+COUNTIF(AS31,">0")+COUNTIF(AV31,">0")+COUNTIF(AY31,">0")+COUNTIF(BB31,">0")+COUNTIF(BE31,">0")+COUNTIF(BH31,">0")+COUNTIF(BK31,">0") -> 12 | AB31: =SUM(AC31,AF31,AI31,AL31,AO31,AR31,AU31,AX31,BA31,BD31,BG31,BJ31) -> 1409128.8 | AC31: =AD31*AE31 -> 120168.23 | AD31: =SUMIFS('1-2 人员岗位信息'!F:F,'1-2 人员岗位信息'!$C:$C,"自有人员",'1-2 人员岗位信息'!$B:$B,$D31) -> 13 | AE31: ='自有人工预算（附表）'!E28/AD31 -> 9243.71 | AF31: =AG31*AH31 -> 117178.23 | AG31: =SUMIFS('1-2 人员岗位信息'!G:G,'1-2 人员岗位信息'!$C:$C,"自有人员",'1-2 人员岗位信息'!$B:$B,$D31) -> 13 | AH31: ='自有人工预算（附表）'!F28/AG31 -> 9013.71 | AI31: =AJ31*AK31 -> 117178.23 | AJ31: =SUMIFS('1-2 人员岗位信息'!H:H,'1-2 人员岗位信息'!$C:$C,"自有人员",'1-2 人员岗位信息'!$B:$B,$D31) -> 13 | AK31: ='自有人工预算（附表）'!G28/AJ31 -> 9013.71 | AL31: =AM31*AN31 -> 117178.23 | AM31: =SUMIFS('1-2 人员岗位信息'!I:I,'1-2 人员岗位信息'!$C:$C,"自有人员",'1-2 人员岗位信息'!$B:$B,$D31) -> 13 | AN31: ='自有人工预算（附表）'!H28/AM31 -> 9013.71 | AO31: =AP31*AQ31 -> 117178.23 | AP31: =SUMIFS('1-2 人员岗位信息'!J:J,'1-2 人员岗位信息'!$C:$C,"自有人员",'1-2 人员岗位信息'!$B:$B,$D31) -> 13 | AQ31: ='自有人工预算（附表）'!I28/AP31 -> 9013.71 | AR31: =AS31*AT31 -> 117178.23 | AS31: =SUMIFS('1-2 人员岗位信息'!K:K,'1-2 人员岗位信息'!$C:$C,"自有人员",'1-2 人员岗位信息'!$B:$B,$D31) -> 13 | AT31: ='自有人工预算（附表）'!J28/AS31 -> 9013.71 | AU31: =AV31*AW31 -> 117178.23 | AV31: =SUMIFS('1-2 人员岗位信息'!L:L,'1-2 人员岗位信息'!$C:$C,"自有人员",'1-2 人员岗位信息'!$B:$B,$D31) -> 13 | AW31: ='自有人工预算（附表）'!K28/AV31 -> 9013.71 | AX31: =AY31*AZ31 -> 117178.23 | AY31: =SUMIFS('1-2 人员岗位信息'!M:M,'1-2 人员岗位信息'!$C:$C,"自有人员",'1-2 人员岗位信息'!$B:$B,$D31) -> 13 | AZ31: ='自有人工预算（附表）'!L28/AY31 -> 9013.71 | BA31: =BB31*BC31 -> 117178.23 | BB31: =SUMIFS('1-2 人员岗位信息'!N:N,'1-2 人员岗位信息'!$C:$C,"自有人员",'1-2 人员岗位信息'!$B:$B,$D31) -> 13 | BC31: ='自有人工预算（附表）'!M28/BB31 -> 9013.71 | BD31: =BE31*BF31 -> 117178.23 | BE31: =SUMIFS('1-2 人员岗位信息'!O:O,'1-2 人员岗位信息'!$C:$C,"自有人员",'1-2 人员岗位信息'!$B:$B,$D31) -> 13 | BF31: ='自有人工预算（附表）'!N28/BE31 -> 9013.71 | BG31: =BH31*BI31 -> 117178.23 | BH31: =SUMIFS('1-2 人员岗位信息'!P:P,'1-2 人员岗位信息'!$C:$C,"自有人员",'1-2 人员岗位信息'!$B:$B,$D31) -> 13 | BI31: ='自有人工预算（附表）'!O28/BH31 -> 9013.71 | BJ31: =BK31*BL31 -> 117178.23 | BK31: =SUMIFS('1-2 人员岗位信息'!Q:Q,'1-2 人员岗位信息'!$C:$C,"自有人员",'1-2 人员岗位信息'!$B:$B,$D31) -> 13 | BL31: ='自有人工预算（附表）'!P28/BK31 -> 9013.71
B32: 是 | C32: 1.1.1.2.1.2 | D32: 客服主管 | E32: 指自有客服经理 | G32: 按月编制，汇总成年总量 | H32: =AB32 -> 0 | I32: 岗位数量 | J32: =SUM(AD32,AG32,AJ32,AM32,AP32,AS32,AV32,AY32,BB32,BE32,BH32,BK32)/N32 -> #DIV/0! | K32: 岗 | L32: =H32/N32/J32 -> #DIV/0! | M32: 元/㎡/月 | N32: =COUNTIF(AD32,">0")+COUNTIF(AG32,">0")+COUNTIF(AJ32,">0")+COUNTIF(AM32,">0")+COUNTIF(AP32,">0")+COUNTIF(AS32,">0")+COUNTIF(AV32,">0")+COUNTIF(AY32,">0")+COUNTIF(BB32,">0")+COUNTIF(BE32,">0")+COUNTIF(BH32,">0")+COUNTIF(BK32,">0") -> 0 | AB32: =SUM(AC32,AF32,AI32,AL32,AO32,AR32,AU32,AX32,BA32,BD32,BG32,BJ32) -> 0 | AC32: =AD32*AE32 -> 0 | AD32: =SUMIFS('1-2 人员岗位信息'!F:F,'1-2 人员岗位信息'!$C:$C,"自有人员",'1-2 人员岗位信息'!$B:$B,$D32) -> 0 | AF32: =AG32*AH32 -> 0 | AG32: =SUMIFS('1-2 人员岗位信息'!G:G,'1-2 人员岗位信息'!$C:$C,"自有人员",'1-2 人员岗位信息'!$B:$B,$D32) -> 0 | AI32: =AJ32*AK32 -> 0 | AJ32: =SUMIFS('1-2 人员岗位信息'!H:H,'1-2 人员岗位信息'!$C:$C,"自有人员",'1-2 人员岗位信息'!$B:$B,$D32) -> 0 | AL32: =AM32*AN32 -> 0 | AM32: =SUMIFS('1-2 人员岗位信息'!I:I,'1-2 人员岗位信息'!$C:$C,"自有人员",'1-2 人员岗位信息'!$B:$B,$D32) -> 0 | AO32: =AP32*AQ32 -> 0 | AP32: =SUMIFS('1-2 人员岗位信息'!J:J,'1-2 人员岗位信息'!$C:$C,"自有人员",'1-2 人员岗位信息'!$B:$B,$D32) -> 0 | AR32: =AS32*AT32 -> 0 | AS32: =SUMIFS('1-2 人员岗位信息'!K:K,'1-2 人员岗位信息'!$C:$C,"自有人员",'1-2 人员岗位信息'!$B:$B,$D32) -> 0 | AU32: =AV32*AW32 -> 0 | AV32: =SUMIFS('1-2 人员岗位信息'!L:L,'1-2 人员岗位信息'!$C:$C,"自有人员",'1-2 人员岗位信息'!$B:$B,$D32) -> 0 | AX32: =AY32*AZ32 -> 0 | AY32: =SUMIFS('1-2 人员岗位信息'!M:M,'1-2 人员岗位信息'!$C:$C,"自有人员",'1-2 人员岗位信息'!$B:$B,$D32) -> 0 | BA32: =BB32*BC32 -> 0 | BB32: =SUMIFS('1-2 人员岗位信息'!N:N,'1-2 人员岗位信息'!$C:$C,"自有人员",'1-2 人员岗位信息'!$B:$B,$D32) -> 0 | BD32: =BE32*BF32 -> 0 | BE32: =SUMIFS('1-2 人员岗位信息'!O:O,'1-2 人员岗位信息'!$C:$C,"自有人员",'1-2 人员岗位信息'!$B:$B,$D32) -> 0 | BG32: =BH32*BI32 -> 0 | BH32: =SUMIFS('1-2 人员岗位信息'!P:P,'1-2 人员岗位信息'!$C:$C,"自有人员",'1-2 人员岗位信息'!$B:$B,$D32) -> 0 | BJ32: =BK32*BL32 -> 0 | BK32: =SUMIFS('1-2 人员岗位信息'!Q:Q,'1-2 人员岗位信息'!$C:$C,"自有人员",'1-2 人员岗位信息'!$B:$B,$D32) -> 0
B33: 是 | C33: 1.1.1.2.1.3 | D33: 前台客服员工 | E33: 负责前台接待的客服员工 | G33: 按月编制，汇总成年总量 | H33: =AB33 -> 0 | I33: 岗位数量 | J33: =SUM(AD33,AG33,AJ33,AM33,AP33,AS33,AV33,AY33,BB33,BE33,BH33,BK33)/N33 -> #DIV/0! | K33: 岗 | L33: =H33/N33/J33 -> #DIV/0! | M33: 元/㎡/月 | N33: =COUNTIF(AD33,">0")+COUNTIF(AG33,">0")+COUNTIF(AJ33,">0")+COUNTIF(AM33,">0")+COUNTIF(AP33,">0")+COUNTIF(AS33,">0")+COUNTIF(AV33,">0")+COUNTIF(AY33,">0")+COUNTIF(BB33,">0")+COUNTIF(BE33,">0")+COUNTIF(BH33,">0")+COUNTIF(BK33,">0") -> 0 | AB33: =SUM(AC33,AF33,AI33,AL33,AO33,AR33,AU33,AX33,BA33,BD33,BG33,BJ33) -> 0 | AC33: =AD33*AE33 -> 0 | AD33: =SUMIFS('1-2 人员岗位信息'!F:F,'1-2 人员岗位信息'!$C:$C,"自有人员",'1-2 人员岗位信息'!$B:$B,$D33) -> 0 | AF33: =AG33*AH33 -> 0 | AG33: =SUMIFS('1-2 人员岗位信息'!G:G,'1-2 人员岗位信息'!$C:$C,"自有人员",'1-2 人员岗位信息'!$B:$B,$D33) -> 0 | AI33: =AJ33*AK33 -> 0 | AJ33: =SUMIFS('1-2 人员岗位信息'!H:H,'1-2 人员岗位信息'!$C:$C,"自有人员",'1-2 人员岗位信息'!$B:$B,$D33) -> 0 | AL33: =AM33*AN33 -> 0 | AM33: =SUMIFS('1-2 人员岗位信息'!I:I,'1-2 人员岗位信息'!$C:$C,"自有人员",'1-2 人员岗位信息'!$B:$B,$D33) -> 0 | AO33: =AP33*AQ33 -> 0 | AP33: =SUMIFS('1-2 人员岗位信息'!J:J,'1-2 人员岗位信息'!$C:$C,"自有人员",'1-2 人员岗位信息'!$B:$B,$D33) -> 0 | AR33: =AS33*AT33 -> 0 | AS33: =SUMIFS('1-2 人员岗位信息'!K:K,'1-2 人员岗位信息'!$C:$C,"自有人员",'1-2 人员岗位信息'!$B:$B,$D33) -> 0 | AU33: =AV33*AW33 -> 0 | AV33: =SUMIFS('1-2 人员岗位信息'!L:L,'1-2 人员岗位信息'!$C:$C,"自有人员",'1-2 人员岗位信息'!$B:$B,$D33) -> 0 | AX33: =AY33*AZ33 -> 0 | AY33: =SUMIFS('1-2 人员岗位信息'!M:M,'1-2 人员岗位信息'!$C:$C,"自有人员",'1-2 人员岗位信息'!$B:$B,$D33) -> 0 | BA33: =BB33*BC33 -> 0 | BB33: =SUMIFS('1-2 人员岗位信息'!N:N,'1-2 人员岗位信息'!$C:$C,"自有人员",'1-2 人员岗位信息'!$B:$B,$D33) -> 0 | BD33: =BE33*BF33 -> 0 | BE33: =SUMIFS('1-2 人员岗位信息'!O:O,'1-2 人员岗位信息'!$C:$C,"自有人员",'1-2 人员岗位信息'!$B:$B,$D33) -> 0 | BG33: =BH33*BI33 -> 0 | BH33: =SUMIFS('1-2 人员岗位信息'!P:P,'1-2 人员岗位信息'!$C:$C,"自有人员",'1-2 人员岗位信息'!$B:$B,$D33) -> 0 | BJ33: =BK33*BL33 -> 0 | BK33: =SUMIFS('1-2 人员岗位信息'!Q:Q,'1-2 人员岗位信息'!$C:$C,"自有人员",'1-2 人员岗位信息'!$B:$B,$D33) -> 0
B34: 是 | C34: 1.1.1.2.1.4 | D34: 普通客服员工 | E34: 负责对接非住小业主或商户的客服员工 | G34: 按月编制，汇总成年总量 | H34: =AB34 -> 0 | I34: 岗位数量 | J34: =SUM(AD34,AG34,AJ34,AM34,AP34,AS34,AV34,AY34,BB34,BE34,BH34,BK34)/N34 -> #DIV/0! | K34: 岗 | L34: =H34/N34/J34 -> #DIV/0! | M34: 元/㎡/月 | N34: =COUNTIF(AD34,">0")+COUNTIF(AG34,">0")+COUNTIF(AJ34,">0")+COUNTIF(AM34,">0")+COUNTIF(AP34,">0")+COUNTIF(AS34,">0")+COUNTIF(AV34,">0")+COUNTIF(AY34,">0")+COUNTIF(BB34,">0")+COUNTIF(BE34,">0")+COUNTIF(BH34,">0")+COUNTIF(BK34,">0") -> 0 | AB34: =SUM(AC34,AF34,AI34,AL34,AO34,AR34,AU34,AX34,BA34,BD34,BG34,BJ34) -> 0 | AC34: =AD34*AE34 -> 0 | AD34: =SUMIFS('1-2 人员岗位信息'!F:F,'1-2 人员岗位信息'!$C:$C,"自有人员",'1-2 人员岗位信息'!$B:$B,$D34) -> 0 | AF34: =AG34*AH34 -> 0 | AG34: =SUMIFS('1-2 人员岗位信息'!G:G,'1-2 人员岗位信息'!$C:$C,"自有人员",'1-2 人员岗位信息'!$B:$B,$D34) -> 0 | AI34: =AJ34*AK34 -> 0 | AJ34: =SUMIFS('1-2 人员岗位信息'!H:H,'1-2 人员岗位信息'!$C:$C,"自有人员",'1-2 人员岗位信息'!$B:$B,$D34) -> 0 | AL34: =AM34*AN34 -> 0 | AM34: =SUMIFS('1-2 人员岗位信息'!I:I,'1-2 人员岗位信息'!$C:$C,"自有人员",'1-2 人员岗位信息'!$B:$B,$D34) -> 0 | AO34: =AP34*AQ34 -> 0 | AP34: =SUMIFS('1-2 人员岗位信息'!J:J,'1-2 人员岗位信息'!$C:$C,"自有人员",'1-2 人员岗位信息'!$B:$B,$D34) -> 0 | AR34: =AS34*AT34 -> 0 | AS34: =SUMIFS('1-2 人员岗位信息'!K:K,'1-2 人员岗位信息'!$C:$C,"自有人员",'1-2 人员岗位信息'!$B:$B,$D34) -> 0 | AU34: =AV34*AW34 -> 0 | AV34: =SUMIFS('1-2 人员岗位信息'!L:L,'1-2 人员岗位信息'!$C:$C,"自有人员",'1-2 人员岗位信息'!$B:$B,$D34) -> 0 | AX34: =AY34*AZ34 -> 0 | AY34: =SUMIFS('1-2 人员岗位信息'!M:M,'1-2 人员岗位信息'!$C:$C,"自有人员",'1-2 人员岗位信息'!$B:$B,$D34) -> 0 | BA34: =BB34*BC34 -> 0 | BB34: =SUMIFS('1-2 人员岗位信息'!N:N,'1-2 人员岗位信息'!$C:$C,"自有人员",'1-2 人员岗位信息'!$B:$B,$D34) -> 0 | BD34: =BE34*BF34 -> 0 | BE34: =SUMIFS('1-2 人员岗位信息'!O:O,'1-2 人员岗位信息'!$C:$C,"自有人员",'1-2 人员岗位信息'!$B:$B,$D34) -> 0 | BG34: =BH34*BI34 -> 0 | BH34: =SUMIFS('1-2 人员岗位信息'!P:P,'1-2 人员岗位信息'!$C:$C,"自有人员",'1-2 人员岗位信息'!$B:$B,$D34) -> 0 | BJ34: =BK34*BL34 -> 0 | BK34: =SUMIFS('1-2 人员岗位信息'!Q:Q,'1-2 人员岗位信息'!$C:$C,"自有人员",'1-2 人员岗位信息'!$B:$B,$D34) -> 0
B35: 是 | C35: 1.1.1.2.1.5 | D35: 会议客服员工 | E35: 负责企业内部会议室、会议设备管理的客服员工 | G35: 按月编制，汇总成年总量 | H35: =AB35 -> 0 | I35: 岗位数量 | J35: =SUM(AD35,AG35,AJ35,AM35,AP35,AS35,AV35,AY35,BB35,BE35,BH35,BK35)/N35 -> #DIV/0! | K35: 岗 | L35: =H35/N35/J35 -> #DIV/0! | M35: 元/㎡/月 | N35: =COUNTIF(AD35,">0")+COUNTIF(AG35,">0")+COUNTIF(AJ35,">0")+COUNTIF(AM35,">0")+COUNTIF(AP35,">0")+COUNTIF(AS35,">0")+COUNTIF(AV35,">0")+COUNTIF(AY35,">0")+COUNTIF(BB35,">0")+COUNTIF(BE35,">0")+COUNTIF(BH35,">0")+COUNTIF(BK35,">0") -> 0 | AB35: =SUM(AC35,AF35,AI35,AL35,AO35,AR35,AU35,AX35,BA35,BD35,BG35,BJ35) -> 0 | AC35: =AD35*AE35 -> 0 | AD35: =SUMIFS('1-2 人员岗位信息'!F:F,'1-2 人员岗位信息'!$C:$C,"自有人员",'1-2 人员岗位信息'!$B:$B,$D35) -> 0 | AF35: =AG35*AH35 -> 0 | AG35: =SUMIFS('1-2 人员岗位信息'!G:G,'1-2 人员岗位信息'!$C:$C,"自有人员",'1-2 人员岗位信息'!$B:$B,$D35) -> 0 | AI35: =AJ35*AK35 -> 0 | AJ35: =SUMIFS('1-2 人员岗位信息'!H:H,'1-2 人员岗位信息'!$C:$C,"自有人员",'1-2 人员岗位信息'!$B:$B,$D35) -> 0 | AL35: =AM35*AN35 -> 0 | AM35: =SUMIFS('1-2 人员岗位信息'!I:I,'1-2 人员岗位信息'!$C:$C,"自有人员",'1-2 人员岗位信息'!$B:$B,$D35) -> 0 | AO35: =AP35*AQ35 -> 0 | AP35: =SUMIFS('1-2 人员岗位信息'!J:J,'1-2 人员岗位信息'!$C:$C,"自有人员",'1-2 人员岗位信息'!$B:$B,$D35) -> 0 | AR35: =AS35*AT35 -> 0 | AS35: =SUMIFS('1-2 人员岗位信息'!K:K,'1-2 人员岗位信息'!$C:$C,"自有人员",'1-2 人员岗位信息'!$B:$B,$D35) -> 0 | AU35: =AV35*AW35 -> 0 | AV35: =SUMIFS('1-2 人员岗位信息'!L:L,'1-2 人员岗位信息'!$C:$C,"自有人员",'1-2 人员岗位信息'!$B:$B,$D35) -> 0 | AX35: =AY35*AZ35 -> 0 | AY35: =SUMIFS('1-2 人员岗位信息'!M:M,'1-2 人员岗位信息'!$C:$C,"自有人员",'1-2 人员岗位信息'!$B:$B,$D35) -> 0 | BA35: =BB35*BC35 -> 0 | BB35: =SUMIFS('1-2 人员岗位信息'!N:N,'1-2 人员岗位信息'!$C:$C,"自有人员",'1-2 人员岗位信息'!$B:$B,$D35) -> 0 | BD35: =BE35*BF35 -> 0 | BE35: =SUMIFS('1-2 人员岗位信息'!O:O,'1-2 人员岗位信息'!$C:$C,"自有人员",'1-2 人员岗位信息'!$B:$B,$D35) -> 0 | BG35: =BH35*BI35 -> 0 | BH35: =SUMIFS('1-2 人员岗位信息'!P:P,'1-2 人员岗位信息'!$C:$C,"自有人员",'1-2 人员岗位信息'!$B:$B,$D35) -> 0 | BJ35: =BK35*BL35 -> 0 | BK35: =SUMIFS('1-2 人员岗位信息'!Q:Q,'1-2 人员岗位信息'!$C:$C,"自有人员",'1-2 人员岗位信息'!$B:$B,$D35) -> 0
B36: 是 | C36: 1.1.1.2.1.6 | D36: 迎宾岗员工 | E36: 负责迎宾的客服员工 | G36: 按月编制，汇总成年总量 | H36: =AB36 -> 0 | I36: 岗位数量 | J36: =SUM(AD36,AG36,AJ36,AM36,AP36,AS36,AV36,AY36,BB36,BE36,BH36,BK36)/N36 -> #DIV/0! | K36: 岗 | L36: =H36/N36/J36 -> #DIV/0! | M36: 元/㎡/月 | N36: =COUNTIF(AD36,">0")+COUNTIF(AG36,">0")+COUNTIF(AJ36,">0")+COUNTIF(AM36,">0")+COUNTIF(AP36,">0")+COUNTIF(AS36,">0")+COUNTIF(AV36,">0")+COUNTIF(AY36,">0")+COUNTIF(BB36,">0")+COUNTIF(BE36,">0")+COUNTIF(BH36,">0")+COUNTIF(BK36,">0") -> 0 | AB36: =SUM(AC36,AF36,AI36,AL36,AO36,AR36,AU36,AX36,BA36,BD36,BG36,BJ36) -> 0 | AC36: =AD36*AE36 -> 0 | AD36: =SUMIFS('1-2 人员岗位信息'!F:F,'1-2 人员岗位信息'!$C:$C,"自有人员",'1-2 人员岗位信息'!$B:$B,$D36) -> 0 | AF36: =AG36*AH36 -> 0 | AG36: =SUMIFS('1-2 人员岗位信息'!G:G,'1-2 人员岗位信息'!$C:$C,"自有人员",'1-2 人员岗位信息'!$B:$B,$D36) -> 0 | AI36: =AJ36*AK36 -> 0 | AJ36: =SUMIFS('1-2 人员岗位信息'!H:H,'1-2 人员岗位信息'!$C:$C,"自有人员",'1-2 人员岗位信息'!$B:$B,$D36) -> 0 | AL36: =AM36*AN36 -> 0 | AM36: =SUMIFS('1-2 人员岗位信息'!I:I,'1-2 人员岗位信息'!$C:$C,"自有人员",'1-2 人员岗位信息'!$B:$B,$D36) -> 0 | AO36: =AP36*AQ36 -> 0 | AP36: =SUMIFS('1-2 人员岗位信息'!J:J,'1-2 人员岗位信息'!$C:$C,"自有人员",'1-2 人员岗位信息'!$B:$B,$D36) -> 0 | AR36: =AS36*AT36 -> 0 | AS36: =SUMIFS('1-2 人员岗位信息'!K:K,'1-2 人员岗位信息'!$C:$C,"自有人员",'1-2 人员岗位信息'!$B:$B,$D36) -> 0 | AU36: =AV36*AW36 -> 0 | AV36: =SUMIFS('1-2 人员岗位信息'!L:L,'1-2 人员岗位信息'!$C:$C,"自有人员",'1-2 人员岗位信息'!$B:$B,$D36) -> 0 | AX36: =AY36*AZ36 -> 0 | AY36: =SUMIFS('1-2 人员岗位信息'!M:M,'1-2 人员岗位信息'!$C:$C,"自有人员",'1-2 人员岗位信息'!$B:$B,$D36) -> 0 | BA36: =BB36*BC36 -> 0 | BB36: =SUMIFS('1-2 人员岗位信息'!N:N,'1-2 人员岗位信息'!$C:$C,"自有人员",'1-2 人员岗位信息'!$B:$B,$D36) -> 0 | BD36: =BE36*BF36 -> 0 | BE36: =SUMIFS('1-2 人员岗位信息'!O:O,'1-2 人员岗位信息'!$C:$C,"自有人员",'1-2 人员岗位信息'!$B:$B,$D36) -> 0 | BG36: =BH36*BI36 -> 0 | BH36: =SUMIFS('1-2 人员岗位信息'!P:P,'1-2 人员岗位信息'!$C:$C,"自有人员",'1-2 人员岗位信息'!$B:$B,$D36) -> 0 | BJ36: =BK36*BL36 -> 0 | BK36: =SUMIFS('1-2 人员岗位信息'!Q:Q,'1-2 人员岗位信息'!$C:$C,"自有人员",'1-2 人员岗位信息'!$B:$B,$D36) -> 0
B37: 是 | C37: 1.1.1.2.1.7 | D37: 吧台岗员工 | E37: 负责售楼处、写字楼等非住业态水吧台服务的员工 | G37: 按月编制，汇总成年总量 | H37: =AB37 -> 0 | I37: 岗位数量 | J37: =SUM(AD37,AG37,AJ37,AM37,AP37,AS37,AV37,AY37,BB37,BE37,BH37,BK37)/N37 -> #DIV/0! | K37: 岗 | L37: =H37/N37/J37 -> #DIV/0! | M37: 元/㎡/月 | N37: =COUNTIF(AD37,">0")+COUNTIF(AG37,">0")+COUNTIF(AJ37,">0")+COUNTIF(AM37,">0")+COUNTIF(AP37,">0")+COUNTIF(AS37,">0")+COUNTIF(AV37,">0")+COUNTIF(AY37,">0")+COUNTIF(BB37,">0")+COUNTIF(BE37,">0")+COUNTIF(BH37,">0")+COUNTIF(BK37,">0") -> 0 | AB37: =SUM(AC37,AF37,AI37,AL37,AO37,AR37,AU37,AX37,BA37,BD37,BG37,BJ37) -> 0 | AC37: =AD37*AE37 -> 0 | AD37: =SUMIFS('1-2 人员岗位信息'!F:F,'1-2 人员岗位信息'!$C:$C,"自有人员",'1-2 人员岗位信息'!$B:$B,$D37) -> 0 | AF37: =AG37*AH37 -> 0 | AG37: =SUMIFS('1-2 人员岗位信息'!G:G,'1-2 人员岗位信息'!$C:$C,"自有人员",'1-2 人员岗位信息'!$B:$B,$D37) -> 0 | AI37: =AJ37*AK37 -> 0 | AJ37: =SUMIFS('1-2 人员岗位信息'!H:H,'1-2 人员岗位信息'!$C:$C,"自有人员",'1-2 人员岗位信息'!$B:$B,$D37) -> 0 | AL37: =AM37*AN37 -> 0 | AM37: =SUMIFS('1-2 人员岗位信息'!I:I,'1-2 人员岗位信息'!$C:$C,"自有人员",'1-2 人员岗位信息'!$B:$B,$D37) -> 0 | AO37: =AP37*AQ37 -> 0 | AP37: =SUMIFS('1-2 人员岗位信息'!J:J,'1-2 人员岗位信息'!$C:$C,"自有人员",'1-2 人员岗位信息'!$B:$B,$D37) -> 0 | AR37: =AS37*AT37 -> 0 | AS37: =SUMIFS('1-2 人员岗位信息'!K:K,'1-2 人员岗位信息'!$C:$C,"自有人员",'1-2 人员岗位信息'!$B:$B,$D37) -> 0 | AU37: =AV37*AW37 -> 0 | AV37: =SUMIFS('1-2 人员岗位信息'!L:L,'1-2 人员岗位信息'!$C:$C,"自有人员",'1-2 人员岗位信息'!$B:$B,$D37) -> 0 | AX37: =AY37*AZ37 -> 0 | AY37: =SUMIFS('1-2 人员岗位信息'!M:M,'1-2 人员岗位信息'!$C:$C,"自有人员",'1-2 人员岗位信息'!$B:$B,$D37) -> 0 | BA37: =BB37*BC37 -> 0 | BB37: =SUMIFS('1-2 人员岗位信息'!N:N,'1-2 人员岗位信息'!$C:$C,"自有人员",'1-2 人员岗位信息'!$B:$B,$D37) -> 0 | BD37: =BE37*BF37 -> 0 | BE37: =SUMIFS('1-2 人员岗位信息'!O:O,'1-2 人员岗位信息'!$C:$C,"自有人员",'1-2 人员岗位信息'!$B:$B,$D37) -> 0 | BG37: =BH37*BI37 -> 0 | BH37: =SUMIFS('1-2 人员岗位信息'!P:P,'1-2 人员岗位信息'!$C:$C,"自有人员",'1-2 人员岗位信息'!$B:$B,$D37) -> 0 | BJ37: =BK37*BL37 -> 0 | BK37: =SUMIFS('1-2 人员岗位信息'!Q:Q,'1-2 人员岗位信息'!$C:$C,"自有人员",'1-2 人员岗位信息'!$B:$B,$D37) -> 0
B38: 是 | C38: 1.1.1.2.1.8 | D38: 其他客服员工 | E38: 上述不包含的岗位可适用此项 | G38: 按月编制，汇总成年总量 | H38: =AB38 -> 0 | I38: 岗位数量 | J38: =SUM(AD38,AG38,AJ38,AM38,AP38,AS38,AV38,AY38,BB38,BE38,BH38,BK38)/N38 -> #DIV/0! | K38: 岗 | L38: =H38/N38/J38 -> #DIV/0! | M38: 元/㎡/月 | N38: =COUNTIF(AD38,">0")+COUNTIF(AG38,">0")+COUNTIF(AJ38,">0")+COUNTIF(AM38,">0")+COUNTIF(AP38,">0")+COUNTIF(AS38,">0")+COUNTIF(AV38,">0")+COUNTIF(AY38,">0")+COUNTIF(BB38,">0")+COUNTIF(BE38,">0")+COUNTIF(BH38,">0")+COUNTIF(BK38,">0") -> 0 | AB38: =SUM(AC38,AF38,AI38,AL38,AO38,AR38,AU38,AX38,BA38,BD38,BG38,BJ38) -> 0 | AC38: =AD38*AE38 -> 0 | AD38: =SUMIFS('1-2 人员岗位信息'!F:F,'1-2 人员岗位信息'!$C:$C,"自有人员",'1-2 人员岗位信息'!$B:$B,$D38) -> 0 | AF38: =AG38*AH38 -> 0 | AG38: =SUMIFS('1-2 人员岗位信息'!G:G,'1-2 人员岗位信息'!$C:$C,"自有人员",'1-2 人员岗位信息'!$B:$B,$D38) -> 0 | AI38: =AJ38*AK38 -> 0 | AJ38: =SUMIFS('1-2 人员岗位信息'!H:H,'1-2 人员岗位信息'!$C:$C,"自有人员",'1-2 人员岗位信息'!$B:$B,$D38) -> 0 | AL38: =AM38*AN38 -> 0 | AM38: =SUMIFS('1-2 人员岗位信息'!I:I,'1-2 人员岗位信息'!$C:$C,"自有人员",'1-2 人员岗位信息'!$B:$B,$D38) -> 0 | AO38: =AP38*AQ38 -> 0 | AP38: =SUMIFS('1-2 人员岗位信息'!J:J,'1-2 人员岗位信息'!$C:$C,"自有人员",'1-2 人员岗位信息'!$B:$B,$D38) -> 0 | AR38: =AS38*AT38 -> 0 | AS38: =SUMIFS('1-2 人员岗位信息'!K:K,'1-2 人员岗位信息'!$C:$C,"自有人员",'1-2 人员岗位信息'!$B:$B,$D38) -> 0 | AU38: =AV38*AW38 -> 0 | AV38: =SUMIFS('1-2 人员岗位信息'!L:L,'1-2 人员岗位信息'!$C:$C,"自有人员",'1-2 人员岗位信息'!$B:$B,$D38) -> 0 | AX38: =AY38*AZ38 -> 0 | AY38: =SUMIFS('1-2 人员岗位信息'!M:M,'1-2 人员岗位信息'!$C:$C,"自有人员",'1-2 人员岗位信息'!$B:$B,$D38) -> 0 | BA38: =BB38*BC38 -> 0 | BB38: =SUMIFS('1-2 人员岗位信息'!N:N,'1-2 人员岗位信息'!$C:$C,"自有人员",'1-2 人员岗位信息'!$B:$B,$D38) -> 0 | BD38: =BE38*BF38 -> 0 | BE38: =SUMIFS('1-2 人员岗位信息'!O:O,'1-2 人员岗位信息'!$C:$C,"自有人员",'1-2 人员岗位信息'!$B:$B,$D38) -> 0 | BG38: =BH38*BI38 -> 0 | BH38: =SUMIFS('1-2 人员岗位信息'!P:P,'1-2 人员岗位信息'!$C:$C,"自有人员",'1-2 人员岗位信息'!$B:$B,$D38) -> 0 | BJ38: =BK38*BL38 -> 0 | BK38: =SUMIFS('1-2 人员岗位信息'!Q:Q,'1-2 人员岗位信息'!$C:$C,"自有人员",'1-2 人员岗位信息'!$B:$B,$D38) -> 0
B39: 否 | C39: 1.1.1.2.2 | D39: 劳务派遣 | H39: =SUM(H40:H47) -> 0 | AB39: =SUM(AB40:AB47) -> 0 | AC39: =SUM(AC40:AC47) -> 0 | AF39: =SUM(AF40:AF47) -> 0 | AI39: =SUM(AI40:AI47) -> 0 | AL39: =SUM(AL40:AL47) -> 0 | AO39: =SUM(AO40:AO47) -> 0 | AR39: =SUM(AR40:AR47) -> 0 | AU39: =SUM(AU40:AU47) -> 0 | AX39: =SUM(AX40:AX47) -> 0 | BA39: =SUM(BA40:BA47) -> 0 | BD39: =SUM(BD40:BD47) -> 0 | BG39: =SUM(BG40:BG47) -> 0 | BJ39: =SUM(BJ40:BJ47) -> 0
B40: 是 | C40: 1.1.1.2.2.1 | D40: 客服经理 | E40: 指派遣客服经理 | G40: 按月编制，汇总成年总量 | H40: =AB40 -> 0 | I40: 岗位数量 | J40: =SUM(AD40,AG40,AJ40,AM40,AP40,AS40,AV40,AY40,BB40,BE40,BH40,BK40)/N40 -> #DIV/0! | K40: 岗 | L40: =H40/N40/J40 -> #DIV/0! | M40: 元/㎡/月 | N40: =COUNTIF(AD40,">0")+COUNTIF(AG40,">0")+COUNTIF(AJ40,">0")+COUNTIF(AM40,">0")+COUNTIF(AP40,">0")+COUNTIF(AS40,">0")+COUNTIF(AV40,">0")+COUNTIF(AY40,">0")+COUNTIF(BB40,">0")+COUNTIF(BE40,">0")+COUNTIF(BH40,">0")+COUNTIF(BK40,">0") -> 0 | AB40: =SUM(AC40,AF40,AI40,AL40,AO40,AR40,AU40,AX40,BA40,BD40,BG40,BJ40) -> 0 | AC40: =AD40*AE40 -> 0 | AD40: =SUMIFS('1-2 人员岗位信息'!F:F,'1-2 人员岗位信息'!$C:$C,"劳务派遣",'1-2 人员岗位信息'!$B:$B,$D40) -> 0 | AF40: =AG40*AH40 -> 0 | AG40: =SUMIFS('1-2 人员岗位信息'!G:G,'1-2 人员岗位信息'!$C:$C,"劳务派遣",'1-2 人员岗位信息'!$B:$B,$D40) -> 0 | AI40: =AJ40*AK40 -> 0 | AJ40: =SUMIFS('1-2 人员岗位信息'!H:H,'1-2 人员岗位信息'!$C:$C,"劳务派遣",'1-2 人员岗位信息'!$B:$B,$D40) -> 0 | AL40: =AM40*AN40 -> 0 | AM40: =SUMIFS('1-2 人员岗位信息'!I:I,'1-2 人员岗位信息'!$C:$C,"劳务派遣",'1-2 人员岗位信息'!$B:$B,$D40) -> 0 | AO40: =AP40*AQ40 -> 0 | AP40: =SUMIFS('1-2 人员岗位信息'!J:J,'1-2 人员岗位信息'!$C:$C,"劳务派遣",'1-2 人员岗位信息'!$B:$B,$D40) -> 0 | AR40: =AS40*AT40 -> 0 | AS40: =SUMIFS('1-2 人员岗位信息'!K:K,'1-2 人员岗位信息'!$C:$C,"劳务派遣",'1-2 人员岗位信息'!$B:$B,$D40) -> 0 | AU40: =AV40*AW40 -> 0 | AV40: =SUMIFS('1-2 人员岗位信息'!L:L,'1-2 人员岗位信息'!$C:$C,"劳务派遣",'1-2 人员岗位信息'!$B:$B,$D40) -> 0 | AX40: =AY40*AZ40 -> 0 | AY40: =SUMIFS('1-2 人员岗位信息'!M:M,'1-2 人员岗位信息'!$C:$C,"劳务派遣",'1-2 人员岗位信息'!$B:$B,$D40) -> 0 | BA40: =BB40*BC40 -> 0 | BB40: =SUMIFS('1-2 人员岗位信息'!N:N,'1-2 人员岗位信息'!$C:$C,"劳务派遣",'1-2 人员岗位信息'!$B:$B,$D40) -> 0 | BD40: =BE40*BF40 -> 0 | BE40: =SUMIFS('1-2 人员岗位信息'!O:O,'1-2 人员岗位信息'!$C:$C,"劳务派遣",'1-2 人员岗位信息'!$B:$B,$D40) -> 0 | BG40: =BH40*BI40 -> 0 | BH40: =SUMIFS('1-2 人员岗位信息'!P:P,'1-2 人员岗位信息'!$C:$C,"劳务派遣",'1-2 人员岗位信息'!$B:$B,$D40) -> 0 | BJ40: =BK40*BL40 -> 0 | BK40: =SUMIFS('1-2 人员岗位信息'!Q:Q,'1-2 人员岗位信息'!$C:$C,"劳务派遣",'1-2 人员岗位信息'!$B:$B,$D40) -> 0
B41: 是 | C41: 1.1.1.2.2.2 | D41: 客服主管 | E41: 指派遣客服经理 | G41: 按月编制，汇总成年总量 | H41: =AB41 -> 0 | I41: 岗位数量 | J41: =SUM(AD41,AG41,AJ41,AM41,AP41,AS41,AV41,AY41,BB41,BE41,BH41,BK41)/N41 -> #DIV/0! | K41: 岗 | L41: =H41/N41/J41 -> #DIV/0! | M41: 元/㎡/月 | N41: =COUNTIF(AD41,">0")+COUNTIF(AG41,">0")+COUNTIF(AJ41,">0")+COUNTIF(AM41,">0")+COUNTIF(AP41,">0")+COUNTIF(AS41,">0")+COUNTIF(AV41,">0")+COUNTIF(AY41,">0")+COUNTIF(BB41,">0")+COUNTIF(BE41,">0")+COUNTIF(BH41,">0")+COUNTIF(BK41,">0") -> 0 | AB41: =SUM(AC41,AF41,AI41,AL41,AO41,AR41,AU41,AX41,BA41,BD41,BG41,BJ41) -> 0 | AC41: =AD41*AE41 -> 0 | AD41: =SUMIFS('1-2 人员岗位信息'!F:F,'1-2 人员岗位信息'!$C:$C,"劳务派遣",'1-2 人员岗位信息'!$B:$B,$D41) -> 0 | AF41: =AG41*AH41 -> 0 | AG41: =SUMIFS('1-2 人员岗位信息'!G:G,'1-2 人员岗位信息'!$C:$C,"劳务派遣",'1-2 人员岗位信息'!$B:$B,$D41) -> 0 | AI41: =AJ41*AK41 -> 0 | AJ41: =SUMIFS('1-2 人员岗位信息'!H:H,'1-2 人员岗位信息'!$C:$C,"劳务派遣",'1-2 人员岗位信息'!$B:$B,$D41) -> 0 | AL41: =AM41*AN41 -> 0 | AM41: =SUMIFS('1-2 人员岗位信息'!I:I,'1-2 人员岗位信息'!$C:$C,"劳务派遣",'1-2 人员岗位信息'!$B:$B,$D41) -> 0 | AO41: =AP41*AQ41 -> 0 | AP41: =SUMIFS('1-2 人员岗位信息'!J:J,'1-2 人员岗位信息'!$C:$C,"劳务派遣",'1-2 人员岗位信息'!$B:$B,$D41) -> 0 | AR41: =AS41*AT41 -> 0 | AS41: =SUMIFS('1-2 人员岗位信息'!K:K,'1-2 人员岗位信息'!$C:$C,"劳务派遣",'1-2 人员岗位信息'!$B:$B,$D41) -> 0 | AU41: =AV41*AW41 -> 0 | AV41: =SUMIFS('1-2 人员岗位信息'!L:L,'1-2 人员岗位信息'!$C:$C,"劳务派遣",'1-2 人员岗位信息'!$B:$B,$D41) -> 0 | AX41: =AY41*AZ41 -> 0 | AY41: =SUMIFS('1-2 人员岗位信息'!M:M,'1-2 人员岗位信息'!$C:$C,"劳务派遣",'1-2 人员岗位信息'!$B:$B,$D41) -> 0 | BA41: =BB41*BC41 -> 0 | BB41: =SUMIFS('1-2 人员岗位信息'!N:N,'1-2 人员岗位信息'!$C:$C,"劳务派遣",'1-2 人员岗位信息'!$B:$B,$D41) -> 0 | BD41: =BE41*BF41 -> 0 | BE41: =SUMIFS('1-2 人员岗位信息'!O:O,'1-2 人员岗位信息'!$C:$C,"劳务派遣",'1-2 人员岗位信息'!$B:$B,$D41) -> 0 | BG41: =BH41*BI41 -> 0 | BH41: =SUMIFS('1-2 人员岗位信息'!P:P,'1-2 人员岗位信息'!$C:$C,"劳务派遣",'1-2 人员岗位信息'!$B:$B,$D41) -> 0 | BJ41: =BK41*BL41 -> 0 | BK41: =SUMIFS('1-2 人员岗位信息'!Q:Q,'1-2 人员岗位信息'!$C:$C,"劳务派遣",'1-2 人员岗位信息'!$B:$B,$D41) -> 0
B42: 是 | C42: 1.1.1.2.2.3 | D42: 前台客服员工 | E42: 负责前台接待的客服员工 | G42: 按月编制，汇总成年总量 | H42: =AB42 -> 0 | I42: 岗位数量 | J42: =SUM(AD42,AG42,AJ42,AM42,AP42,AS42,AV42,AY42,BB42,BE42,BH42,BK42)/N42 -> #DIV/0! | K42: 岗 | L42: =H42/N42/J42 -> #DIV/0! | M42: 元/㎡/月 | N42: =COUNTIF(AD42,">0")+COUNTIF(AG42,">0")+COUNTIF(AJ42,">0")+COUNTIF(AM42,">0")+COUNTIF(AP42,">0")+COUNTIF(AS42,">0")+COUNTIF(AV42,">0")+COUNTIF(AY42,">0")+COUNTIF(BB42,">0")+COUNTIF(BE42,">0")+COUNTIF(BH42,">0")+COUNTIF(BK42,">0") -> 0 | AB42: =SUM(AC42,AF42,AI42,AL42,AO42,AR42,AU42,AX42,BA42,BD42,BG42,BJ42) -> 0 | AC42: =AD42*AE42 -> 0 | AD42: =SUMIFS('1-2 人员岗位信息'!F:F,'1-2 人员岗位信息'!$C:$C,"劳务派遣",'1-2 人员岗位信息'!$B:$B,$D42) -> 0 | AF42: =AG42*AH42 -> 0 | AG42: =SUMIFS('1-2 人员岗位信息'!G:G,'1-2 人员岗位信息'!$C:$C,"劳务派遣",'1-2 人员岗位信息'!$B:$B,$D42) -> 0 | AI42: =AJ42*AK42 -> 0 | AJ42: =SUMIFS('1-2 人员岗位信息'!H:H,'1-2 人员岗位信息'!$C:$C,"劳务派遣",'1-2 人员岗位信息'!$B:$B,$D42) -> 0 | AL42: =AM42*AN42 -> 0 | AM42: =SUMIFS('1-2 人员岗位信息'!I:I,'1-2 人员岗位信息'!$C:$C,"劳务派遣",'1-2 人员岗位信息'!$B:$B,$D42) -> 0 | AO42: =AP42*AQ42 -> 0 | AP42: =SUMIFS('1-2 人员岗位信息'!J:J,'1-2 人员岗位信息'!$C:$C,"劳务派遣",'1-2 人员岗位信息'!$B:$B,$D42) -> 0 | AR42: =AS42*AT42 -> 0 | AS42: =SUMIFS('1-2 人员岗位信息'!K:K,'1-2 人员岗位信息'!$C:$C,"劳务派遣",'1-2 人员岗位信息'!$B:$B,$D42) -> 0 | AU42: =AV42*AW42 -> 0 | AV42: =SUMIFS('1-2 人员岗位信息'!L:L,'1-2 人员岗位信息'!$C:$C,"劳务派遣",'1-2 人员岗位信息'!$B:$B,$D42) -> 0 | AX42: =AY42*AZ42 -> 0 | AY42: =SUMIFS('1-2 人员岗位信息'!M:M,'1-2 人员岗位信息'!$C:$C,"劳务派遣",'1-2 人员岗位信息'!$B:$B,$D42) -> 0 | BA42: =BB42*BC42 -> 0 | BB42: =SUMIFS('1-2 人员岗位信息'!N:N,'1-2 人员岗位信息'!$C:$C,"劳务派遣",'1-2 人员岗位信息'!$B:$B,$D42) -> 0 | BD42: =BE42*BF42 -> 0 | BE42: =SUMIFS('1-2 人员岗位信息'!O:O,'1-2 人员岗位信息'!$C:$C,"劳务派遣",'1-2 人员岗位信息'!$B:$B,$D42) -> 0 | BG42: =BH42*BI42 -> 0 | BH42: =SUMIFS('1-2 人员岗位信息'!P:P,'1-2 人员岗位信息'!$C:$C,"劳务派遣",'1-2 人员岗位信息'!$B:$B,$D42) -> 0 | BJ42: =BK42*BL42 -> 0 | BK42: =SUMIFS('1-2 人员岗位信息'!Q:Q,'1-2 人员岗位信息'!$C:$C,"劳务派遣",'1-2 人员岗位信息'!$B:$B,$D42) -> 0
B43: 是 | C43: 1.1.1.2.2.4 | D43: 普通客服员工 | E43: 负责对接非住小业主或商户的客服员工 | G43: 按月编制，汇总成年总量 | H43: =AB43 -> 0 | I43: 岗位数量 | J43: =SUM(AD43,AG43,AJ43,AM43,AP43,AS43,AV43,AY43,BB43,BE43,BH43,BK43)/N43 -> #DIV/0! | K43: 岗 | L43: =H43/N43/J43 -> #DIV/0! | M43: 元/㎡/月 | N43: =COUNTIF(AD43,">0")+COUNTIF(AG43,">0")+COUNTIF(AJ43,">0")+COUNTIF(AM43,">0")+COUNTIF(AP43,">0")+COUNTIF(AS43,">0")+COUNTIF(AV43,">0")+COUNTIF(AY43,">0")+COUNTIF(BB43,">0")+COUNTIF(BE43,">0")+COUNTIF(BH43,">0")+COUNTIF(BK43,">0") -> 0 | AB43: =SUM(AC43,AF43,AI43,AL43,AO43,AR43,AU43,AX43,BA43,BD43,BG43,BJ43) -> 0 | AC43: =AD43*AE43 -> 0 | AD43: =SUMIFS('1-2 人员岗位信息'!F:F,'1-2 人员岗位信息'!$C:$C,"劳务派遣",'1-2 人员岗位信息'!$B:$B,$D43) -> 0 | AF43: =AG43*AH43 -> 0 | AG43: =SUMIFS('1-2 人员岗位信息'!G:G,'1-2 人员岗位信息'!$C:$C,"劳务派遣",'1-2 人员岗位信息'!$B:$B,$D43) -> 0 | AI43: =AJ43*AK43 -> 0 | AJ43: =SUMIFS('1-2 人员岗位信息'!H:H,'1-2 人员岗位信息'!$C:$C,"劳务派遣",'1-2 人员岗位信息'!$B:$B,$D43) -> 0 | AL43: =AM43*AN43 -> 0 | AM43: =SUMIFS('1-2 人员岗位信息'!I:I,'1-2 人员岗位信息'!$C:$C,"劳务派遣",'1-2 人员岗位信息'!$B:$B,$D43) -> 0 | AO43: =AP43*AQ43 -> 0 | AP43: =SUMIFS('1-2 人员岗位信息'!J:J,'1-2 人员岗位信息'!$C:$C,"劳务派遣",'1-2 人员岗位信息'!$B:$B,$D43) -> 0 | AR43: =AS43*AT43 -> 0 | AS43: =SUMIFS('1-2 人员岗位信息'!K:K,'1-2 人员岗位信息'!$C:$C,"劳务派遣",'1-2 人员岗位信息'!$B:$B,$D43) -> 0 | AU43: =AV43*AW43 -> 0 | AV43: =SUMIFS('1-2 人员岗位信息'!L:L,'1-2 人员岗位信息'!$C:$C,"劳务派遣",'1-2 人员岗位信息'!$B:$B,$D43) -> 0 | AX43: =AY43*AZ43 -> 0 | AY43: =SUMIFS('1-2 人员岗位信息'!M:M,'1-2 人员岗位信息'!$C:$C,"劳务派遣",'1-2 人员岗位信息'!$B:$B,$D43) -> 0 | BA43: =BB43*BC43 -> 0 | BB43: =SUMIFS('1-2 人员岗位信息'!N:N,'1-2 人员岗位信息'!$C:$C,"劳务派遣",'1-2 人员岗位信息'!$B:$B,$D43) -> 0 | BD43: =BE43*BF43 -> 0 | BE43: =SUMIFS('1-2 人员岗位信息'!O:O,'1-2 人员岗位信息'!$C:$C,"劳务派遣",'1-2 人员岗位信息'!$B:$B,$D43) -> 0 | BG43: =BH43*BI43 -> 0 | BH43: =SUMIFS('1-2 人员岗位信息'!P:P,'1-2 人员岗位信息'!$C:$C,"劳务派遣",'1-2 人员岗位信息'!$B:$B,$D43) -> 0 | BJ43: =BK43*BL43 -> 0 | BK43: =SUMIFS('1-2 人员岗位信息'!Q:Q,'1-2 人员岗位信息'!$C:$C,"劳务派遣",'1-2 人员岗位信息'!$B:$B,$D43) -> 0
B44: 是 | C44: 1.1.1.2.2.5 | D44: 会议客服员工 | E44: 负责企业内部会议室、会议设备管理的客服员工 | G44: 按月编制，汇总成年总量 | H44: =AB44 -> 0 | I44: 岗位数量 | J44: =SUM(AD44,AG44,AJ44,AM44,AP44,AS44,AV44,AY44,BB44,BE44,BH44,BK44)/N44 -> #DIV/0! | K44: 岗 | L44: =H44/N44/J44 -> #DIV/0! | M44: 元/㎡/月 | N44: =COUNTIF(AD44,">0")+COUNTIF(AG44,">0")+COUNTIF(AJ44,">0")+COUNTIF(AM44,">0")+COUNTIF(AP44,">0")+COUNTIF(AS44,">0")+COUNTIF(AV44,">0")+COUNTIF(AY44,">0")+COUNTIF(BB44,">0")+COUNTIF(BE44,">0")+COUNTIF(BH44,">0")+COUNTIF(BK44,">0") -> 0 | AB44: =SUM(AC44,AF44,AI44,AL44,AO44,AR44,AU44,AX44,BA44,BD44,BG44,BJ44) -> 0 | AC44: =AD44*AE44 -> 0 | AD44: =SUMIFS('1-2 人员岗位信息'!F:F,'1-2 人员岗位信息'!$C:$C,"劳务派遣",'1-2 人员岗位信息'!$B:$B,$D44) -> 0 | AF44: =AG44*AH44 -> 0 | AG44: =SUMIFS('1-2 人员岗位信息'!G:G,'1-2 人员岗位信息'!$C:$C,"劳务派遣",'1-2 人员岗位信息'!$B:$B,$D44) -> 0 | AI44: =AJ44*AK44 -> 0 | AJ44: =SUMIFS('1-2 人员岗位信息'!H:H,'1-2 人员岗位信息'!$C:$C,"劳务派遣",'1-2 人员岗位信息'!$B:$B,$D44) -> 0 | AL44: =AM44*AN44 -> 0 | AM44: =SUMIFS('1-2 人员岗位信息'!I:I,'1-2 人员岗位信息'!$C:$C,"劳务派遣",'1-2 人员岗位信息'!$B:$B,$D44) -> 0 | AO44: =AP44*AQ44 -> 0 | AP44: =SUMIFS('1-2 人员岗位信息'!J:J,'1-2 人员岗位信息'!$C:$C,"劳务派遣",'1-2 人员岗位信息'!$B:$B,$D44) -> 0 | AR44: =AS44*AT44 -> 0 | AS44: =SUMIFS('1-2 人员岗位信息'!K:K,'1-2 人员岗位信息'!$C:$C,"劳务派遣",'1-2 人员岗位信息'!$B:$B,$D44) -> 0 | AU44: =AV44*AW44 -> 0 | AV44: =SUMIFS('1-2 人员岗位信息'!L:L,'1-2 人员岗位信息'!$C:$C,"劳务派遣",'1-2 人员岗位信息'!$B:$B,$D44) -> 0 | AX44: =AY44*AZ44 -> 0 | AY44: =SUMIFS('1-2 人员岗位信息'!M:M,'1-2 人员岗位信息'!$C:$C,"劳务派遣",'1-2 人员岗位信息'!$B:$B,$D44) -> 0 | BA44: =BB44*BC44 -> 0 | BB44: =SUMIFS('1-2 人员岗位信息'!N:N,'1-2 人员岗位信息'!$C:$C,"劳务派遣",'1-2 人员岗位信息'!$B:$B,$D44) -> 0 | BD44: =BE44*BF44 -> 0 | BE44: =SUMIFS('1-2 人员岗位信息'!O:O,'1-2 人员岗位信息'!$C:$C,"劳务派遣",'1-2 人员岗位信息'!$B:$B,$D44) -> 0 | BG44: =BH44*BI44 -> 0 | BH44: =SUMIFS('1-2 人员岗位信息'!P:P,'1-2 人员岗位信息'!$C:$C,"劳务派遣",'1-2 人员岗位信息'!$B:$B,$D44) -> 0 | BJ44: =BK44*BL44 -> 0 | BK44: =SUMIFS('1-2 人员岗位信息'!Q:Q,'1-2 人员岗位信息'!$C:$C,"劳务派遣",'1-2 人员岗位信息'!$B:$B,$D44) -> 0
B45: 是 | C45: 1.1.1.2.2.6 | D45: 迎宾岗员工 | E45: 负责迎宾的客服员工 | G45: 按月编制，汇总成年总量 | H45: =AB45 -> 0 | I45: 岗位数量 | J45: =SUM(AD45,AG45,AJ45,AM45,AP45,AS45,AV45,AY45,BB45,BE45,BH45,BK45)/N45 -> #DIV/0! | K45: 岗 | L45: =H45/N45/J45 -> #DIV/0! | M45: 元/㎡/月 | N45: =COUNTIF(AD45,">0")+COUNTIF(AG45,">0")+COUNTIF(AJ45,">0")+COUNTIF(AM45,">0")+COUNTIF(AP45,">0")+COUNTIF(AS45,">0")+COUNTIF(AV45,">0")+COUNTIF(AY45,">0")+COUNTIF(BB45,">0")+COUNTIF(BE45,">0")+COUNTIF(BH45,">0")+COUNTIF(BK45,">0") -> 0 | AB45: =SUM(AC45,AF45,AI45,AL45,AO45,AR45,AU45,AX45,BA45,BD45,BG45,BJ45) -> 0 | AC45: =AD45*AE45 -> 0 | AD45: =SUMIFS('1-2 人员岗位信息'!F:F,'1-2 人员岗位信息'!$C:$C,"劳务派遣",'1-2 人员岗位信息'!$B:$B,$D45) -> 0 | AF45: =AG45*AH45 -> 0 | AG45: =SUMIFS('1-2 人员岗位信息'!G:G,'1-2 人员岗位信息'!$C:$C,"劳务派遣",'1-2 人员岗位信息'!$B:$B,$D45) -> 0 | AI45: =AJ45*AK45 -> 0 | AJ45: =SUMIFS('1-2 人员岗位信息'!H:H,'1-2 人员岗位信息'!$C:$C,"劳务派遣",'1-2 人员岗位信息'!$B:$B,$D45) -> 0 | AL45: =AM45*AN45 -> 0 | AM45: =SUMIFS('1-2 人员岗位信息'!I:I,'1-2 人员岗位信息'!$C:$C,"劳务派遣",'1-2 人员岗位信息'!$B:$B,$D45) -> 0 | AO45: =AP45*AQ45 -> 0 | AP45: =SUMIFS('1-2 人员岗位信息'!J:J,'1-2 人员岗位信息'!$C:$C,"劳务派遣",'1-2 人员岗位信息'!$B:$B,$D45) -> 0 | AR45: =AS45*AT45 -> 0 | AS45: =SUMIFS('1-2 人员岗位信息'!K:K,'1-2 人员岗位信息'!$C:$C,"劳务派遣",'1-2 人员岗位信息'!$B:$B,$D45) -> 0 | AU45: =AV45*AW45 -> 0 | AV45: =SUMIFS('1-2 人员岗位信息'!L:L,'1-2 人员岗位信息'!$C:$C,"劳务派遣",'1-2 人员岗位信息'!$B:$B,$D45) -> 0 | AX45: =AY45*AZ45 -> 0 | AY45: =SUMIFS('1-2 人员岗位信息'!M:M,'1-2 人员岗位信息'!$C:$C,"劳务派遣",'1-2 人员岗位信息'!$B:$B,$D45) -> 0 | BA45: =BB45*BC45 -> 0 | BB45: =SUMIFS('1-2 人员岗位信息'!N:N,'1-2 人员岗位信息'!$C:$C,"劳务派遣",'1-2 人员岗位信息'!$B:$B,$D45) -> 0 | BD45: =BE45*BF45 -> 0 | BE45: =SUMIFS('1-2 人员岗位信息'!O:O,'1-2 人员岗位信息'!$C:$C,"劳务派遣",'1-2 人员岗位信息'!$B:$B,$D45) -> 0 | BG45: =BH45*BI45 -> 0 | BH45: =SUMIFS('1-2 人员岗位信息'!P:P,'1-2 人员岗位信息'!$C:$C,"劳务派遣",'1-2 人员岗位信息'!$B:$B,$D45) -> 0 | BJ45: =BK45*BL45 -> 0 | BK45: =SUMIFS('1-2 人员岗位信息'!Q:Q,'1-2 人员岗位信息'!$C:$C,"劳务派遣",'1-2 人员岗位信息'!$B:$B,$D45) -> 0
B46: 是 | C46: 1.1.1.2.2.7 | D46: 吧台岗员工 | E46: 负责售楼处、写字楼等非住业态水吧台服务的员工 | G46: 按月编制，汇总成年总量 | H46: =AB46 -> 0 | I46: 岗位数量 | J46: =SUM(AD46,AG46,AJ46,AM46,AP46,AS46,AV46,AY46,BB46,BE46,BH46,BK46)/N46 -> #DIV/0! | K46: 岗 | L46: =H46/N46/J46 -> #DIV/0! | M46: 元/㎡/月 | N46: =COUNTIF(AD46,">0")+COUNTIF(AG46,">0")+COUNTIF(AJ46,">0")+COUNTIF(AM46,">0")+COUNTIF(AP46,">0")+COUNTIF(AS46,">0")+COUNTIF(AV46,">0")+COUNTIF(AY46,">0")+COUNTIF(BB46,">0")+COUNTIF(BE46,">0")+COUNTIF(BH46,">0")+COUNTIF(BK46,">0") -> 0 | AB46: =SUM(AC46,AF46,AI46,AL46,AO46,AR46,AU46,AX46,BA46,BD46,BG46,BJ46) -> 0 | AC46: =AD46*AE46 -> 0 | AD46: =SUMIFS('1-2 人员岗位信息'!F:F,'1-2 人员岗位信息'!$C:$C,"劳务派遣",'1-2 人员岗位信息'!$B:$B,$D46) -> 0 | AF46: =AG46*AH46 -> 0 | AG46: =SUMIFS('1-2 人员岗位信息'!G:G,'1-2 人员岗位信息'!$C:$C,"劳务派遣",'1-2 人员岗位信息'!$B:$B,$D46) -> 0 | AI46: =AJ46*AK46 -> 0 | AJ46: =SUMIFS('1-2 人员岗位信息'!H:H,'1-2 人员岗位信息'!$C:$C,"劳务派遣",'1-2 人员岗位信息'!$B:$B,$D46) -> 0 | AL46: =AM46*AN46 -> 0 | AM46: =SUMIFS('1-2 人员岗位信息'!I:I,'1-2 人员岗位信息'!$C:$C,"劳务派遣",'1-2 人员岗位信息'!$B:$B,$D46) -> 0 | AO46: =AP46*AQ46 -> 0 | AP46: =SUMIFS('1-2 人员岗位信息'!J:J,'1-2 人员岗位信息'!$C:$C,"劳务派遣",'1-2 人员岗位信息'!$B:$B,$D46) -> 0 | AR46: =AS46*AT46 -> 0 | AS46: =SUMIFS('1-2 人员岗位信息'!K:K,'1-2 人员岗位信息'!$C:$C,"劳务派遣",'1-2 人员岗位信息'!$B:$B,$D46) -> 0 | AU46: =AV46*AW46 -> 0 | AV46: =SUMIFS('1-2 人员岗位信息'!L:L,'1-2 人员岗位信息'!$C:$C,"劳务派遣",'1-2 人员岗位信息'!$B:$B,$D46) -> 0 | AX46: =AY46*AZ46 -> 0 | AY46: =SUMIFS('1-2 人员岗位信息'!M:M,'1-2 人员岗位信息'!$C:$C,"劳务派遣",'1-2 人员岗位信息'!$B:$B,$D46) -> 0 | BA46: =BB46*BC46 -> 0 | BB46: =SUMIFS('1-2 人员岗位信息'!N:N,'1-2 人员岗位信息'!$C:$C,"劳务派遣",'1-2 人员岗位信息'!$B:$B,$D46) -> 0 | BD46: =BE46*BF46 -> 0 | BE46: =SUMIFS('1-2 人员岗位信息'!O:O,'1-2 人员岗位信息'!$C:$C,"劳务派遣",'1-2 人员岗位信息'!$B:$B,$D46) -> 0 | BG46: =BH46*BI46 -> 0 | BH46: =SUMIFS('1-2 人员岗位信息'!P:P,'1-2 人员岗位信息'!$C:$C,"劳务派遣",'1-2 人员岗位信息'!$B:$B,$D46) -> 0 | BJ46: =BK46*BL46 -> 0 | BK46: =SUMIFS('1-2 人员岗位信息'!Q:Q,'1-2 人员岗位信息'!$C:$C,"劳务派遣",'1-2 人员岗位信息'!$B:$B,$D46) -> 0
B47: 是 | C47: 1.1.1.2.2.8 | D47: 其他客服员工 | E47: 上述不包含的岗位可适用此项 | G47: 按月编制，汇总成年总量 | H47: =AB47 -> 0 | I47: 岗位数量 | J47: =SUM(AD47,AG47,AJ47,AM47,AP47,AS47,AV47,AY47,BB47,BE47,BH47,BK47)/N47 -> #DIV/0! | K47: 岗 | L47: =H47/N47/J47 -> #DIV/0! | M47: 元/㎡/月 | N47: =COUNTIF(AD47,">0")+COUNTIF(AG47,">0")+COUNTIF(AJ47,">0")+COUNTIF(AM47,">0")+COUNTIF(AP47,">0")+COUNTIF(AS47,">0")+COUNTIF(AV47,">0")+COUNTIF(AY47,">0")+COUNTIF(BB47,">0")+COUNTIF(BE47,">0")+COUNTIF(BH47,">0")+COUNTIF(BK47,">0") -> 0 | AB47: =SUM(AC47,AF47,AI47,AL47,AO47,AR47,AU47,AX47,BA47,BD47,BG47,BJ47) -> 0 | AC47: =AD47*AE47 -> 0 | AD47: =SUMIFS('1-2 人员岗位信息'!F:F,'1-2 人员岗位信息'!$C:$C,"劳务派遣",'1-2 人员岗位信息'!$B:$B,$D47) -> 0 | AF47: =AG47*AH47 -> 0 | AG47: =SUMIFS('1-2 人员岗位信息'!G:G,'1-2 人员岗位信息'!$C:$C,"劳务派遣",'1-2 人员岗位信息'!$B:$B,$D47) -> 0 | AI47: =AJ47*AK47 -> 0 | AJ47: =SUMIFS('1-2 人员岗位信息'!H:H,'1-2 人员岗位信息'!$C:$C,"劳务派遣",'1-2 人员岗位信息'!$B:$B,$D47) -> 0 | AL47: =AM47*AN47 -> 0 | AM47: =SUMIFS('1-2 人员岗位信息'!I:I,'1-2 人员岗位信息'!$C:$C,"劳务派遣",'1-2 人员岗位信息'!$B:$B,$D47) -> 0 | AO47: =AP47*AQ47 -> 0 | AP47: =SUMIFS('1-2 人员岗位信息'!J:J,'1-2 人员岗位信息'!$C:$C,"劳务派遣",'1-2 人员岗位信息'!$B:$B,$D47) -> 0 | AR47: =AS47*AT47 -> 0 | AS47: =SUMIFS('1-2 人员岗位信息'!K:K,'1-2 人员岗位信息'!$C:$C,"劳务派遣",'1-2 人员岗位信息'!$B:$B,$D47) -> 0 | AU47: =AV47*AW47 -> 0 | AV47: =SUMIFS('1-2 人员岗位信息'!L:L,'1-2 人员岗位信息'!$C:$C,"劳务派遣",'1-2 人员岗位信息'!$B:$B,$D47) -> 0 | AX47: =AY47*AZ47 -> 0 | AY47: =SUMIFS('1-2 人员岗位信息'!M:M,'1-2 人员岗位信息'!$C:$C,"劳务派遣",'1-2 人员岗位信息'!$B:$B,$D47) -> 0 | BA47: =BB47*BC47 -> 0 | BB47: =SUMIFS('1-2 人员岗位信息'!N:N,'1-2 人员岗位信息'!$C:$C,"劳务派遣",'1-2 人员岗位信息'!$B:$B,$D47) -> 0 | BD47: =BE47*BF47 -> 0 | BE47: =SUMIFS('1-2 人员岗位信息'!O:O,'1-2 人员岗位信息'!$C:$C,"劳务派遣",'1-2 人员岗位信息'!$B:$B,$D47) -> 0 | BG47: =BH47*BI47 -> 0 | BH47: =SUMIFS('1-2 人员岗位信息'!P:P,'1-2 人员岗位信息'!$C:$C,"劳务派遣",'1-2 人员岗位信息'!$B:$B,$D47) -> 0 | BJ47: =BK47*BL47 -> 0 | BK47: =SUMIFS('1-2 人员岗位信息'!Q:Q,'1-2 人员岗位信息'!$C:$C,"劳务派遣",'1-2 人员岗位信息'!$B:$B,$D47) -> 0
B48: 否 | C48: 1.1.1.2.3 | D48: 专业外包 | H48: =SUM(H49:H56) -> 0 | AB48: =SUM(AB49:AB56) -> 0 | AC48: =SUM(AC49:AC56) -> 0 | AF48: =SUM(AF49:AF56) -> 0 | AI48: =SUM(AI49:AI56) -> 0 | AL48: =SUM(AL49:AL56) -> 0 | AO48: =SUM(AO49:AO56) -> 0 | AR48: =SUM(AR49:AR56) -> 0 | AU48: =SUM(AU49:AU56) -> 0 | AX48: =SUM(AX49:AX56) -> 0 | BA48: =SUM(BA49:BA56) -> 0 | BD48: =SUM(BD49:BD56) -> 0 | BG48: =SUM(BG49:BG56) -> 0 | BJ48: =SUM(BJ49:BJ56) -> 0
B49: 是 | C49: 1.1.1.2.3.1 | D49: 客服经理 | E49: 指外包客服驻场负责人 | G49: 按月编制，汇总成年总量 | H49: =AB49 -> 0 | I49: 岗位数量 | J49: =SUM(AD49,AG49,AJ49,AM49,AP49,AS49,AV49,AY49,BB49,BE49,BH49,BK49)/N49 -> #DIV/0! | K49: 岗 | L49: =H49/N49/J49 -> #DIV/0! | M49: 元/㎡/月 | N49: =COUNTIF(AD49,">0")+COUNTIF(AG49,">0")+COUNTIF(AJ49,">0")+COUNTIF(AM49,">0")+COUNTIF(AP49,">0")+COUNTIF(AS49,">0")+COUNTIF(AV49,">0")+COUNTIF(AY49,">0")+COUNTIF(BB49,">0")+COUNTIF(BE49,">0")+COUNTIF(BH49,">0")+COUNTIF(BK49,">0") -> 0 | AB49: =SUM(AC49,AF49,AI49,AL49,AO49,AR49,AU49,AX49,BA49,BD49,BG49,BJ49) -> 0 | AC49: =AD49*AE49 -> 0 | AD49: =SUMIFS('1-2 人员岗位信息'!F:F,'1-2 人员岗位信息'!$C:$C,"专业外包",'1-2 人员岗位信息'!$B:$B,$D49) -> 0 | AF49: =AG49*AH49 -> 0 | AG49: =SUMIFS('1-2 人员岗位信息'!G:G,'1-2 人员岗位信息'!$C:$C,"专业外包",'1-2 人员岗位信息'!$B:$B,$D49) -> 0 | AI49: =AJ49*AK49 -> 0 | AJ49: =SUMIFS('1-2 人员岗位信息'!H:H,'1-2 人员岗位信息'!$C:$C,"专业外包",'1-2 人员岗位信息'!$B:$B,$D49) -> 0 | AL49: =AM49*AN49 -> 0 | AM49: =SUMIFS('1-2 人员岗位信息'!I:I,'1-2 人员岗位信息'!$C:$C,"专业外包",'1-2 人员岗位信息'!$B:$B,$D49) -> 0 | AO49: =AP49*AQ49 -> 0 | AP49: =SUMIFS('1-2 人员岗位信息'!J:J,'1-2 人员岗位信息'!$C:$C,"专业外包",'1-2 人员岗位信息'!$B:$B,$D49) -> 0 | AR49: =AS49*AT49 -> 0 | AS49: =SUMIFS('1-2 人员岗位信息'!K:K,'1-2 人员岗位信息'!$C:$C,"专业外包",'1-2 人员岗位信息'!$B:$B,$D49) -> 0 | AU49: =AV49*AW49 -> 0 | AV49: =SUMIFS('1-2 人员岗位信息'!L:L,'1-2 人员岗位信息'!$C:$C,"专业外包",'1-2 人员岗位信息'!$B:$B,$D49) -> 0 | AX49: =AY49*AZ49 -> 0 | AY49: =SUMIFS('1-2 人员岗位信息'!M:M,'1-2 人员岗位信息'!$C:$C,"专业外包",'1-2 人员岗位信息'!$B:$B,$D49) -> 0 | BA49: =BB49*BC49 -> 0 | BB49: =SUMIFS('1-2 人员岗位信息'!N:N,'1-2 人员岗位信息'!$C:$C,"专业外包",'1-2 人员岗位信息'!$B:$B,$D49) -> 0 | BD49: =BE49*BF49 -> 0 | BE49: =SUMIFS('1-2 人员岗位信息'!O:O,'1-2 人员岗位信息'!$C:$C,"专业外包",'1-2 人员岗位信息'!$B:$B,$D49) -> 0 | BG49: =BH49*BI49 -> 0 | BH49: =SUMIFS('1-2 人员岗位信息'!P:P,'1-2 人员岗位信息'!$C:$C,"专业外包",'1-2 人员岗位信息'!$B:$B,$D49) -> 0 | BJ49: =BK49*BL49 -> 0 | BK49: =SUMIFS('1-2 人员岗位信息'!Q:Q,'1-2 人员岗位信息'!$C:$C,"专业外包",'1-2 人员岗位信息'!$B:$B,$D49) -> 0
B50: 是 | C50: 1.1.1.2.3.2 | D50: 客服主管 | E50: 指外包客服主管 | G50: 按月编制，汇总成年总量 | H50: =AB50 -> 0 | I50: 岗位数量 | J50: =SUM(AD50,AG50,AJ50,AM50,AP50,AS50,AV50,AY50,BB50,BE50,BH50,BK50)/N50 -> #DIV/0! | K50: 岗 | L50: =H50/N50/J50 -> #DIV/0! | M50: 元/㎡/月 | N50: =COUNTIF(AD50,">0")+COUNTIF(AG50,">0")+COUNTIF(AJ50,">0")+COUNTIF(AM50,">0")+COUNTIF(AP50,">0")+COUNTIF(AS50,">0")+COUNTIF(AV50,">0")+COUNTIF(AY50,">0")+COUNTIF(BB50,">0")+COUNTIF(BE50,">0")+COUNTIF(BH50,">0")+COUNTIF(BK50,">0") -> 0 | AB50: =SUM(AC50,AF50,AI50,AL50,AO50,AR50,AU50,AX50,BA50,BD50,BG50,BJ50) -> 0 | AC50: =AD50*AE50 -> 0 | AD50: =SUMIFS('1-2 人员岗位信息'!F:F,'1-2 人员岗位信息'!$C:$C,"专业外包",'1-2 人员岗位信息'!$B:$B,$D50) -> 0 | AF50: =AG50*AH50 -> 0 | AG50: =SUMIFS('1-2 人员岗位信息'!G:G,'1-2 人员岗位信息'!$C:$C,"专业外包",'1-2 人员岗位信息'!$B:$B,$D50) -> 0 | AI50: =AJ50*AK50 -> 0 | AJ50: =SUMIFS('1-2 人员岗位信息'!H:H,'1-2 人员岗位信息'!$C:$C,"专业外包",'1-2 人员岗位信息'!$B:$B,$D50) -> 0 | AL50: =AM50*AN50 -> 0 | AM50: =SUMIFS('1-2 人员岗位信息'!I:I,'1-2 人员岗位信息'!$C:$C,"专业外包",'1-2 人员岗位信息'!$B:$B,$D50) -> 0 | AO50: =AP50*AQ50 -> 0 | AP50: =SUMIFS('1-2 人员岗位信息'!J:J,'1-2 人员岗位信息'!$C:$C,"专业外包",'1-2 人员岗位信息'!$B:$B,$D50) -> 0 | AR50: =AS50*AT50 -> 0 | AS50: =SUMIFS('1-2 人员岗位信息'!K:K,'1-2 人员岗位信息'!$C:$C,"专业外包",'1-2 人员岗位信息'!$B:$B,$D50) -> 0 | AU50: =AV50*AW50 -> 0 | AV50: =SUMIFS('1-2 人员岗位信息'!L:L,'1-2 人员岗位信息'!$C:$C,"专业外包",'1-2 人员岗位信息'!$B:$B,$D50) -> 0 | AX50: =AY50*AZ50 -> 0 | AY50: =SUMIFS('1-2 人员岗位信息'!M:M,'1-2 人员岗位信息'!$C:$C,"专业外包",'1-2 人员岗位信息'!$B:$B,$D50) -> 0 | BA50: =BB50*BC50 -> 0 | BB50: =SUMIFS('1-2 人员岗位信息'!N:N,'1-2 人员岗位信息'!$C:$C,"专业外包",'1-2 人员岗位信息'!$B:$B,$D50) -> 0 | BD50: =BE50*BF50 -> 0 | BE50: =SUMIFS('1-2 人员岗位信息'!O:O,'1-2 人员岗位信息'!$C:$C,"专业外包",'1-2 人员岗位信息'!$B:$B,$D50) -> 0 | BG50: =BH50*BI50 -> 0 | BH50: =SUMIFS('1-2 人员岗位信息'!P:P,'1-2 人员岗位信息'!$C:$C,"专业外包",'1-2 人员岗位信息'!$B:$B,$D50) -> 0 | BJ50: =BK50*BL50 -> 0 | BK50: =SUMIFS('1-2 人员岗位信息'!Q:Q,'1-2 人员岗位信息'!$C:$C,"专业外包",'1-2 人员岗位信息'!$B:$B,$D50) -> 0
B51: 是 | C51: 1.1.1.2.3.3 | D51: 前台客服员工 | E51: 负责前台接待的客服员工 | G51: 按月编制，汇总成年总量 | H51: =AB51 -> 0 | I51: 岗位数量 | J51: =SUM(AD51,AG51,AJ51,AM51,AP51,AS51,AV51,AY51,BB51,BE51,BH51,BK51)/N51 -> #DIV/0! | K51: 岗 | L51: =H51/N51/J51 -> #DIV/0! | M51: 元/㎡/月 | N51: =COUNTIF(AD51,">0")+COUNTIF(AG51,">0")+COUNTIF(AJ51,">0")+COUNTIF(AM51,">0")+COUNTIF(AP51,">0")+COUNTIF(AS51,">0")+COUNTIF(AV51,">0")+COUNTIF(AY51,">0")+COUNTIF(BB51,">0")+COUNTIF(BE51,">0")+COUNTIF(BH51,">0")+COUNTIF(BK51,">0") -> 0 | AB51: =SUM(AC51,AF51,AI51,AL51,AO51,AR51,AU51,AX51,BA51,BD51,BG51,BJ51) -> 0 | AC51: =AD51*AE51 -> 0 | AD51: =SUMIFS('1-2 人员岗位信息'!F:F,'1-2 人员岗位信息'!$C:$C,"专业外包",'1-2 人员岗位信息'!$B:$B,$D51) -> 0 | AF51: =AG51*AH51 -> 0 | AG51: =SUMIFS('1-2 人员岗位信息'!G:G,'1-2 人员岗位信息'!$C:$C,"专业外包",'1-2 人员岗位信息'!$B:$B,$D51) -> 0 | AI51: =AJ51*AK51 -> 0 | AJ51: =SUMIFS('1-2 人员岗位信息'!H:H,'1-2 人员岗位信息'!$C:$C,"专业外包",'1-2 人员岗位信息'!$B:$B,$D51) -> 0 | AL51: =AM51*AN51 -> 0 | AM51: =SUMIFS('1-2 人员岗位信息'!I:I,'1-2 人员岗位信息'!$C:$C,"专业外包",'1-2 人员岗位信息'!$B:$B,$D51) -> 0 | AO51: =AP51*AQ51 -> 0 | AP51: =SUMIFS('1-2 人员岗位信息'!J:J,'1-2 人员岗位信息'!$C:$C,"专业外包",'1-2 人员岗位信息'!$B:$B,$D51) -> 0 | AR51: =AS51*AT51 -> 0 | AS51: =SUMIFS('1-2 人员岗位信息'!K:K,'1-2 人员岗位信息'!$C:$C,"专业外包",'1-2 人员岗位信息'!$B:$B,$D51) -> 0 | AU51: =AV51*AW51 -> 0 | AV51: =SUMIFS('1-2 人员岗位信息'!L:L,'1-2 人员岗位信息'!$C:$C,"专业外包",'1-2 人员岗位信息'!$B:$B,$D51) -> 0 | AX51: =AY51*AZ51 -> 0 | AY51: =SUMIFS('1-2 人员岗位信息'!M:M,'1-2 人员岗位信息'!$C:$C,"专业外包",'1-2 人员岗位信息'!$B:$B,$D51) -> 0 | BA51: =BB51*BC51 -> 0 | BB51: =SUMIFS('1-2 人员岗位信息'!N:N,'1-2 人员岗位信息'!$C:$C,"专业外包",'1-2 人员岗位信息'!$B:$B,$D51) -> 0 | BD51: =BE51*BF51 -> 0 | BE51: =SUMIFS('1-2 人员岗位信息'!O:O,'1-2 人员岗位信息'!$C:$C,"专业外包",'1-2 人员岗位信息'!$B:$B,$D51) -> 0 | BG51: =BH51*BI51 -> 0 | BH51: =SUMIFS('1-2 人员岗位信息'!P:P,'1-2 人员岗位信息'!$C:$C,"专业外包",'1-2 人员岗位信息'!$B:$B,$D51) -> 0 | BJ51: =BK51*BL51 -> 0 | BK51: =SUMIFS('1-2 人员岗位信息'!Q:Q,'1-2 人员岗位信息'!$C:$C,"专业外包",'1-2 人员岗位信息'!$B:$B,$D51) -> 0
B52: 是 | C52: 1.1.1.2.3.4 | D52: 普通客服员工 | E52: 负责对接非住小业主或商户的客服员工 | G52: 按月编制，汇总成年总量 | H52: =AB52 -> 0 | I52: 岗位数量 | J52: =SUM(AD52,AG52,AJ52,AM52,AP52,AS52,AV52,AY52,BB52,BE52,BH52,BK52)/N52 -> #DIV/0! | K52: 岗 | L52: =H52/N52/J52 -> #DIV/0! | M52: 元/㎡/月 | N52: =COUNTIF(AD52,">0")+COUNTIF(AG52,">0")+COUNTIF(AJ52,">0")+COUNTIF(AM52,">0")+COUNTIF(AP52,">0")+COUNTIF(AS52,">0")+COUNTIF(AV52,">0")+COUNTIF(AY52,">0")+COUNTIF(BB52,">0")+COUNTIF(BE52,">0")+COUNTIF(BH52,">0")+COUNTIF(BK52,">0") -> 0 | AB52: =SUM(AC52,AF52,AI52,AL52,AO52,AR52,AU52,AX52,BA52,BD52,BG52,BJ52) -> 0 | AC52: =AD52*AE52 -> 0 | AD52: =SUMIFS('1-2 人员岗位信息'!F:F,'1-2 人员岗位信息'!$C:$C,"专业外包",'1-2 人员岗位信息'!$B:$B,$D52) -> 0 | AF52: =AG52*AH52 -> 0 | AG52: =SUMIFS('1-2 人员岗位信息'!G:G,'1-2 人员岗位信息'!$C:$C,"专业外包",'1-2 人员岗位信息'!$B:$B,$D52) -> 0 | AI52: =AJ52*AK52 -> 0 | AJ52: =SUMIFS('1-2 人员岗位信息'!H:H,'1-2 人员岗位信息'!$C:$C,"专业外包",'1-2 人员岗位信息'!$B:$B,$D52) -> 0 | AL52: =AM52*AN52 -> 0 | AM52: =SUMIFS('1-2 人员岗位信息'!I:I,'1-2 人员岗位信息'!$C:$C,"专业外包",'1-2 人员岗位信息'!$B:$B,$D52) -> 0 | AO52: =AP52*AQ52 -> 0 | AP52: =SUMIFS('1-2 人员岗位信息'!J:J,'1-2 人员岗位信息'!$C:$C,"专业外包",'1-2 人员岗位信息'!$B:$B,$D52) -> 0 | AR52: =AS52*AT52 -> 0 | AS52: =SUMIFS('1-2 人员岗位信息'!K:K,'1-2 人员岗位信息'!$C:$C,"专业外包",'1-2 人员岗位信息'!$B:$B,$D52) -> 0 | AU52: =AV52*AW52 -> 0 | AV52: =SUMIFS('1-2 人员岗位信息'!L:L,'1-2 人员岗位信息'!$C:$C,"专业外包",'1-2 人员岗位信息'!$B:$B,$D52) -> 0 | AX52: =AY52*AZ52 -> 0 | AY52: =SUMIFS('1-2 人员岗位信息'!M:M,'1-2 人员岗位信息'!$C:$C,"专业外包",'1-2 人员岗位信息'!$B:$B,$D52) -> 0 | BA52: =BB52*BC52 -> 0 | BB52: =SUMIFS('1-2 人员岗位信息'!N:N,'1-2 人员岗位信息'!$C:$C,"专业外包",'1-2 人员岗位信息'!$B:$B,$D52) -> 0 | BD52: =BE52*BF52 -> 0 | BE52: =SUMIFS('1-2 人员岗位信息'!O:O,'1-2 人员岗位信息'!$C:$C,"专业外包",'1-2 人员岗位信息'!$B:$B,$D52) -> 0 | BG52: =BH52*BI52 -> 0 | BH52: =SUMIFS('1-2 人员岗位信息'!P:P,'1-2 人员岗位信息'!$C:$C,"专业外包",'1-2 人员岗位信息'!$B:$B,$D52) -> 0 | BJ52: =BK52*BL52 -> 0 | BK52: =SUMIFS('1-2 人员岗位信息'!Q:Q,'1-2 人员岗位信息'!$C:$C,"专业外包",'1-2 人员岗位信息'!$B:$B,$D52) -> 0
B53: 是 | C53: 1.1.1.2.3.5 | D53: 会议客服员工 | E53: 负责企业内部会议室、会议设备管理的客服员工 | G53: 按月编制，汇总成年总量 | H53: =AB53 -> 0 | I53: 岗位数量 | J53: =SUM(AD53,AG53,AJ53,AM53,AP53,AS53,AV53,AY53,BB53,BE53,BH53,BK53)/N53 -> #DIV/0! | K53: 岗 | L53: =H53/N53/J53 -> #DIV/0! | M53: 元/㎡/月 | N53: =COUNTIF(AD53,">0")+COUNTIF(AG53,">0")+COUNTIF(AJ53,">0")+COUNTIF(AM53,">0")+COUNTIF(AP53,">0")+COUNTIF(AS53,">0")+COUNTIF(AV53,">0")+COUNTIF(AY53,">0")+COUNTIF(BB53,">0")+COUNTIF(BE53,">0")+COUNTIF(BH53,">0")+COUNTIF(BK53,">0") -> 0 | AB53: =SUM(AC53,AF53,AI53,AL53,AO53,AR53,AU53,AX53,BA53,BD53,BG53,BJ53) -> 0 | AC53: =AD53*AE53 -> 0 | AD53: =SUMIFS('1-2 人员岗位信息'!F:F,'1-2 人员岗位信息'!$C:$C,"专业外包",'1-2 人员岗位信息'!$B:$B,$D53) -> 0 | AF53: =AG53*AH53 -> 0 | AG53: =SUMIFS('1-2 人员岗位信息'!G:G,'1-2 人员岗位信息'!$C:$C,"专业外包",'1-2 人员岗位信息'!$B:$B,$D53) -> 0 | AI53: =AJ53*AK53 -> 0 | AJ53: =SUMIFS('1-2 人员岗位信息'!H:H,'1-2 人员岗位信息'!$C:$C,"专业外包",'1-2 人员岗位信息'!$B:$B,$D53) -> 0 | AL53: =AM53*AN53 -> 0 | AM53: =SUMIFS('1-2 人员岗位信息'!I:I,'1-2 人员岗位信息'!$C:$C,"专业外包",'1-2 人员岗位信息'!$B:$B,$D53) -> 0 | AO53: =AP53*AQ53 -> 0 | AP53: =SUMIFS('1-2 人员岗位信息'!J:J,'1-2 人员岗位信息'!$C:$C,"专业外包",'1-2 人员岗位信息'!$B:$B,$D53) -> 0 | AR53: =AS53*AT53 -> 0 | AS53: =SUMIFS('1-2 人员岗位信息'!K:K,'1-2 人员岗位信息'!$C:$C,"专业外包",'1-2 人员岗位信息'!$B:$B,$D53) -> 0 | AU53: =AV53*AW53 -> 0 | AV53: =SUMIFS('1-2 人员岗位信息'!L:L,'1-2 人员岗位信息'!$C:$C,"专业外包",'1-2 人员岗位信息'!$B:$B,$D53) -> 0 | AX53: =AY53*AZ53 -> 0 | AY53: =SUMIFS('1-2 人员岗位信息'!M:M,'1-2 人员岗位信息'!$C:$C,"专业外包",'1-2 人员岗位信息'!$B:$B,$D53) -> 0 | BA53: =BB53*BC53 -> 0 | BB53: =SUMIFS('1-2 人员岗位信息'!N:N,'1-2 人员岗位信息'!$C:$C,"专业外包",'1-2 人员岗位信息'!$B:$B,$D53) -> 0 | BD53: =BE53*BF53 -> 0 | BE53: =SUMIFS('1-2 人员岗位信息'!O:O,'1-2 人员岗位信息'!$C:$C,"专业外包",'1-2 人员岗位信息'!$B:$B,$D53) -> 0 | BG53: =BH53*BI53 -> 0 | BH53: =SUMIFS('1-2 人员岗位信息'!P:P,'1-2 人员岗位信息'!$C:$C,"专业外包",'1-2 人员岗位信息'!$B:$B,$D53) -> 0 | BJ53: =BK53*BL53 -> 0 | BK53: =SUMIFS('1-2 人员岗位信息'!Q:Q,'1-2 人员岗位信息'!$C:$C,"专业外包",'1-2 人员岗位信息'!$B:$B,$D53) -> 0
B54: 是 | C54: 1.1.1.2.3.6 | D54: 迎宾岗员工 | E54: 负责迎宾的客服员工 | G54: 按月编制，汇总成年总量 | H54: =AB54 -> 0 | I54: 岗位数量 | J54: =SUM(AD54,AG54,AJ54,AM54,AP54,AS54,AV54,AY54,BB54,BE54,BH54,BK54)/N54 -> #DIV/0! | K54: 岗 | L54: =H54/N54/J54 -> #DIV/0! | M54: 元/㎡/月 | N54: =COUNTIF(AD54,">0")+COUNTIF(AG54,">0")+COUNTIF(AJ54,">0")+COUNTIF(AM54,">0")+COUNTIF(AP54,">0")+COUNTIF(AS54,">0")+COUNTIF(AV54,">0")+COUNTIF(AY54,">0")+COUNTIF(BB54,">0")+COUNTIF(BE54,">0")+COUNTIF(BH54,">0")+COUNTIF(BK54,">0") -> 0 | AB54: =SUM(AC54,AF54,AI54,AL54,AO54,AR54,AU54,AX54,BA54,BD54,BG54,BJ54) -> 0 | AC54: =AD54*AE54 -> 0 | AD54: =SUMIFS('1-2 人员岗位信息'!F:F,'1-2 人员岗位信息'!$C:$C,"专业外包",'1-2 人员岗位信息'!$B:$B,$D54) -> 0 | AF54: =AG54*AH54 -> 0 | AG54: =SUMIFS('1-2 人员岗位信息'!G:G,'1-2 人员岗位信息'!$C:$C,"专业外包",'1-2 人员岗位信息'!$B:$B,$D54) -> 0 | AI54: =AJ54*AK54 -> 0 | AJ54: =SUMIFS('1-2 人员岗位信息'!H:H,'1-2 人员岗位信息'!$C:$C,"专业外包",'1-2 人员岗位信息'!$B:$B,$D54) -> 0 | AL54: =AM54*AN54 -> 0 | AM54: =SUMIFS('1-2 人员岗位信息'!I:I,'1-2 人员岗位信息'!$C:$C,"专业外包",'1-2 人员岗位信息'!$B:$B,$D54) -> 0 | AO54: =AP54*AQ54 -> 0 | AP54: =SUMIFS('1-2 人员岗位信息'!J:J,'1-2 人员岗位信息'!$C:$C,"专业外包",'1-2 人员岗位信息'!$B:$B,$D54) -> 0 | AR54: =AS54*AT54 -> 0 | AS54: =SUMIFS('1-2 人员岗位信息'!K:K,'1-2 人员岗位信息'!$C:$C,"专业外包",'1-2 人员岗位信息'!$B:$B,$D54) -> 0 | AU54: =AV54*AW54 -> 0 | AV54: =SUMIFS('1-2 人员岗位信息'!L:L,'1-2 人员岗位信息'!$C:$C,"专业外包",'1-2 人员岗位信息'!$B:$B,$D54) -> 0 | AX54: =AY54*AZ54 -> 0 | AY54: =SUMIFS('1-2 人员岗位信息'!M:M,'1-2 人员岗位信息'!$C:$C,"专业外包",'1-2 人员岗位信息'!$B:$B,$D54) -> 0 | BA54: =BB54*BC54 -> 0 | BB54: =SUMIFS('1-2 人员岗位信息'!N:N,'1-2 人员岗位信息'!$C:$C,"专业外包",'1-2 人员岗位信息'!$B:$B,$D54) -> 0 | BD54: =BE54*BF54 -> 0 | BE54: =SUMIFS('1-2 人员岗位信息'!O:O,'1-2 人员岗位信息'!$C:$C,"专业外包",'1-2 人员岗位信息'!$B:$B,$D54) -> 0 | BG54: =BH54*BI54 -> 0 | BH54: =SUMIFS('1-2 人员岗位信息'!P:P,'1-2 人员岗位信息'!$C:$C,"专业外包",'1-2 人员岗位信息'!$B:$B,$D54) -> 0 | BJ54: =BK54*BL54 -> 0 | BK54: =SUMIFS('1-2 人员岗位信息'!Q:Q,'1-2 人员岗位信息'!$C:$C,"专业外包",'1-2 人员岗位信息'!$B:$B,$D54) -> 0
B55: 是 | C55: 1.1.1.2.3.7 | D55: 吧台岗员工 | E55: 负责售楼处、写字楼等非住业态水吧台服务的员工 | G55: 按月编制，汇总成年总量 | H55: =AB55 -> 0 | I55: 岗位数量 | J55: =SUM(AD55,AG55,AJ55,AM55,AP55,AS55,AV55,AY55,BB55,BE55,BH55,BK55)/N55 -> #DIV/0! | K55: 岗 | L55: =H55/N55/J55 -> #DIV/0! | M55: 元/㎡/月 | N55: =COUNTIF(AD55,">0")+COUNTIF(AG55,">0")+COUNTIF(AJ55,">0")+COUNTIF(AM55,">0")+COUNTIF(AP55,">0")+COUNTIF(AS55,">0")+COUNTIF(AV55,">0")+COUNTIF(AY55,">0")+COUNTIF(BB55,">0")+COUNTIF(BE55,">0")+COUNTIF(BH55,">0")+COUNTIF(BK55,">0") -> 0 | AB55: =SUM(AC55,AF55,AI55,AL55,AO55,AR55,AU55,AX55,BA55,BD55,BG55,BJ55) -> 0 | AC55: =AD55*AE55 -> 0 | AD55: =SUMIFS('1-2 人员岗位信息'!F:F,'1-2 人员岗位信息'!$C:$C,"专业外包",'1-2 人员岗位信息'!$B:$B,$D55) -> 0 | AF55: =AG55*AH55 -> 0 | AG55: =SUMIFS('1-2 人员岗位信息'!G:G,'1-2 人员岗位信息'!$C:$C,"专业外包",'1-2 人员岗位信息'!$B:$B,$D55) -> 0 | AI55: =AJ55*AK55 -> 0 | AJ55: =SUMIFS('1-2 人员岗位信息'!H:H,'1-2 人员岗位信息'!$C:$C,"专业外包",'1-2 人员岗位信息'!$B:$B,$D55) -> 0 | AL55: =AM55*AN55 -> 0 | AM55: =SUMIFS('1-2 人员岗位信息'!I:I,'1-2 人员岗位信息'!$C:$C,"专业外包",'1-2 人员岗位信息'!$B:$B,$D55) -> 0 | AO55: =AP55*AQ55 -> 0 | AP55: =SUMIFS('1-2 人员岗位信息'!J:J,'1-2 人员岗位信息'!$C:$C,"专业外包",'1-2 人员岗位信息'!$B:$B,$D55) -> 0 | AR55: =AS55*AT55 -> 0 | AS55: =SUMIFS('1-2 人员岗位信息'!K:K,'1-2 人员岗位信息'!$C:$C,"专业外包",'1-2 人员岗位信息'!$B:$B,$D55) -> 0 | AU55: =AV55*AW55 -> 0 | AV55: =SUMIFS('1-2 人员岗位信息'!L:L,'1-2 人员岗位信息'!$C:$C,"专业外包",'1-2 人员岗位信息'!$B:$B,$D55) -> 0 | AX55: =AY55*AZ55 -> 0 | AY55: =SUMIFS('1-2 人员岗位信息'!M:M,'1-2 人员岗位信息'!$C:$C,"专业外包",'1-2 人员岗位信息'!$B:$B,$D55) -> 0 | BA55: =BB55*BC55 -> 0 | BB55: =SUMIFS('1-2 人员岗位信息'!N:N,'1-2 人员岗位信息'!$C:$C,"专业外包",'1-2 人员岗位信息'!$B:$B,$D55) -> 0 | BD55: =BE55*BF55 -> 0 | BE55: =SUMIFS('1-2 人员岗位信息'!O:O,'1-2 人员岗位信息'!$C:$C,"专业外包",'1-2 人员岗位信息'!$B:$B,$D55) -> 0 | BG55: =BH55*BI55 -> 0 | BH55: =SUMIFS('1-2 人员岗位信息'!P:P,'1-2 人员岗位信息'!$C:$C,"专业外包",'1-2 人员岗位信息'!$B:$B,$D55) -> 0 | BJ55: =BK55*BL55 -> 0 | BK55: =SUMIFS('1-2 人员岗位信息'!Q:Q,'1-2 人员岗位信息'!$C:$C,"专业外包",'1-2 人员岗位信息'!$B:$B,$D55) -> 0
B56: 是 | C56: 1.1.1.2.3.8 | D56: 其他客服员工 | E56: 上述不包含的岗位可适用此项 | G56: 按月编制，汇总成年总量 | H56: =AB56 -> 0 | I56: 岗位数量 | J56: =SUM(AD56,AG56,AJ56,AM56,AP56,AS56,AV56,AY56,BB56,BE56,BH56,BK56)/N56 -> #DIV/0! | K56: 岗 | L56: =H56/N56/J56 -> #DIV/0! | M56: 元/㎡/月 | N56: =COUNTIF(AD56,">0")+COUNTIF(AG56,">0")+COUNTIF(AJ56,">0")+COUNTIF(AM56,">0")+COUNTIF(AP56,">0")+COUNTIF(AS56,">0")+COUNTIF(AV56,">0")+COUNTIF(AY56,">0")+COUNTIF(BB56,">0")+COUNTIF(BE56,">0")+COUNTIF(BH56,">0")+COUNTIF(BK56,">0") -> 0 | AB56: =SUM(AC56,AF56,AI56,AL56,AO56,AR56,AU56,AX56,BA56,BD56,BG56,BJ56) -> 0 | AC56: =AD56*AE56 -> 0 | AD56: =SUMIFS('1-2 人员岗位信息'!F:F,'1-2 人员岗位信息'!$C:$C,"专业外包",'1-2 人员岗位信息'!$B:$B,$D56) -> 0 | AF56: =AG56*AH56 -> 0 | AG56: =SUMIFS('1-2 人员岗位信息'!G:G,'1-2 人员岗位信息'!$C:$C,"专业外包",'1-2 人员岗位信息'!$B:$B,$D56) -> 0 | AI56: =AJ56*AK56 -> 0 | AJ56: =SUMIFS('1-2 人员岗位信息'!H:H,'1-2 人员岗位信息'!$C:$C,"专业外包",'1-2 人员岗位信息'!$B:$B,$D56) -> 0 | AL56: =AM56*AN56 -> 0 | AM56: =SUMIFS('1-2 人员岗位信息'!I:I,'1-2 人员岗位信息'!$C:$C,"专业外包",'1-2 人员岗位信息'!$B:$B,$D56) -> 0 | AO56: =AP56*AQ56 -> 0 | AP56: =SUMIFS('1-2 人员岗位信息'!J:J,'1-2 人员岗位信息'!$C:$C,"专业外包",'1-2 人员岗位信息'!$B:$B,$D56) -> 0 | AR56: =AS56*AT56 -> 0 | AS56: =SUMIFS('1-2 人员岗位信息'!K:K,'1-2 人员岗位信息'!$C:$C,"专业外包",'1-2 人员岗位信息'!$B:$B,$D56) -> 0 | AU56: =AV56*AW56 -> 0 | AV56: =SUMIFS('1-2 人员岗位信息'!L:L,'1-2 人员岗位信息'!$C:$C,"专业外包",'1-2 人员岗位信息'!$B:$B,$D56) -> 0 | AX56: =AY56*AZ56 -> 0 | AY56: =SUMIFS('1-2 人员岗位信息'!M:M,'1-2 人员岗位信息'!$C:$C,"专业外包",'1-2 人员岗位信息'!$B:$B,$D56) -> 0 | BA56: =BB56*BC56 -> 0 | BB56: =SUMIFS('1-2 人员岗位信息'!N:N,'1-2 人员岗位信息'!$C:$C,"专业外包",'1-2 人员岗位信息'!$B:$B,$D56) -> 0 | BD56: =BE56*BF56 -> 0 | BE56: =SUMIFS('1-2 人员岗位信息'!O:O,'1-2 人员岗位信息'!$C:$C,"专业外包",'1-2 人员岗位信息'!$B:$B,$D56) -> 0 | BG56: =BH56*BI56 -> 0 | BH56: =SUMIFS('1-2 人员岗位信息'!P:P,'1-2 人员岗位信息'!$C:$C,"专业外包",'1-2 人员岗位信息'!$B:$B,$D56) -> 0 | BJ56: =BK56*BL56 -> 0 | BK56: =SUMIFS('1-2 人员岗位信息'!Q:Q,'1-2 人员岗位信息'!$C:$C,"专业外包",'1-2 人员岗位信息'!$B:$B,$D56) -> 0
B57: 否 | C57: 1.1.1.3 | D57: 保洁人员 | H57: =H58+H69+H80+H91 -> 1255991.3 | AB57: =AB58+AB69+AB80+AB91 -> 1255991.3 | AC57: =AC58+AC69+AC80+AC91 -> 104665.94 | AF57: =AF58+AF69+AF80+AF91 -> 104665.94 | AI57: =AI58+AI69+AI80+AI91 -> 104665.94 | AL57: =AL58+AL69+AL80+AL91 -> 104665.94 | AO57: =AO58+AO69+AO80+AO91 -> 104665.94 | AR57: =AR58+AR69+AR80+AR91 -> 104665.94 | AU57: =AU58+AU69+AU80+AU91 -> 104665.94 | AX57: =AX58+AX69+AX80+AX91 -> 104665.94 | BA57: =BA58+BA69+BA80+BA91 -> 104665.94 | BD57: =BD58+BD69+BD80+BD91 -> 104665.94 | BG57: =BG58+BG69+BG80+BG91 -> 104665.94 | BJ57: =BJ58+BJ69+BJ80+BJ91 -> 104665.94
B58: 否 | C58: 1.1.1.3.1 | D58: 自有人员 | H58: =SUM(H59:H68) -> 0 | AB58: =SUM(AB59:AB68) -> 0 | AC58: =SUM(AC59:AC68) -> 0 | AF58: =SUM(AF59:AF68) -> 0 | AI58: =SUM(AI59:AI68) -> 0 | AL58: =SUM(AL59:AL68) -> 0 | AO58: =SUM(AO59:AO68) -> 0 | AR58: =SUM(AR59:AR68) -> 0 | AU58: =SUM(AU59:AU68) -> 0 | AX58: =SUM(AX59:AX68) -> 0 | BA58: =SUM(BA59:BA68) -> 0 | BD58: =SUM(BD59:BD68) -> 0 | BG58: =SUM(BG59:BG68) -> 0 | BJ58: =SUM(BJ59:BJ68) -> 0
B59: 是 | C59: 1.1.1.3.1.1 | D59: 保洁经理 | E59: 指自有保洁经理 | G59: 按月编制，汇总成年总量 | H59: =AB59 -> 0 | I59: 岗位数量 | J59: =SUM(AD59,AG59,AJ59,AM59,AP59,AS59,AV59,AY59,BB59,BE59,BH59,BK59)/N59 -> #DIV/0! | K59: 岗 | L59: =H59/N59/J59 -> #DIV/0! | M59: 元/㎡/月 | N59: =COUNTIF(AD59,">0")+COUNTIF(AG59,">0")+COUNTIF(AJ59,">0")+COUNTIF(AM59,">0")+COUNTIF(AP59,">0")+COUNTIF(AS59,">0")+COUNTIF(AV59,">0")+COUNTIF(AY59,">0")+COUNTIF(BB59,">0")+COUNTIF(BE59,">0")+COUNTIF(BH59,">0")+COUNTIF(BK59,">0") -> 0 | AB59: =SUM(AC59,AF59,AI59,AL59,AO59,AR59,AU59,AX59,BA59,BD59,BG59,BJ59) -> 0 | AC59: =AD59*AE59 -> 0 | AD59: =SUMIFS('1-2 人员岗位信息'!F:F,'1-2 人员岗位信息'!$C:$C,"自有人员",'1-2 人员岗位信息'!$B:$B,$D59) -> 0 | AF59: =AG59*AH59 -> 0 | AG59: =SUMIFS('1-2 人员岗位信息'!G:G,'1-2 人员岗位信息'!$C:$C,"自有人员",'1-2 人员岗位信息'!$B:$B,$D59) -> 0 | AI59: =AJ59*AK59 -> 0 | AJ59: =SUMIFS('1-2 人员岗位信息'!H:H,'1-2 人员岗位信息'!$C:$C,"自有人员",'1-2 人员岗位信息'!$B:$B,$D59) -> 0 | AL59: =AM59*AN59 -> 0 | AM59: =SUMIFS('1-2 人员岗位信息'!I:I,'1-2 人员岗位信息'!$C:$C,"自有人员",'1-2 人员岗位信息'!$B:$B,$D59) -> 0 | AO59: =AP59*AQ59 -> 0 | AP59: =SUMIFS('1-2 人员岗位信息'!J:J,'1-2 人员岗位信息'!$C:$C,"自有人员",'1-2 人员岗位信息'!$B:$B,$D59) -> 0 | AR59: =AS59*AT59 -> 0 | AS59: =SUMIFS('1-2 人员岗位信息'!K:K,'1-2 人员岗位信息'!$C:$C,"自有人员",'1-2 人员岗位信息'!$B:$B,$D59) -> 0 | AU59: =AV59*AW59 -> 0 | AV59: =SUMIFS('1-2 人员岗位信息'!L:L,'1-2 人员岗位信息'!$C:$C,"自有人员",'1-2 人员岗位信息'!$B:$B,$D59) -> 0 | AX59: =AY59*AZ59 -> 0 | AY59: =SUMIFS('1-2 人员岗位信息'!M:M,'1-2 人员岗位信息'!$C:$C,"自有人员",'1-2 人员岗位信息'!$B:$B,$D59) -> 0 | BA59: =BB59*BC59 -> 0 | BB59: =SUMIFS('1-2 人员岗位信息'!N:N,'1-2 人员岗位信息'!$C:$C,"自有人员",'1-2 人员岗位信息'!$B:$B,$D59) -> 0 | BD59: =BE59*BF59 -> 0 | BE59: =SUMIFS('1-2 人员岗位信息'!O:O,'1-2 人员岗位信息'!$C:$C,"自有人员",'1-2 人员岗位信息'!$B:$B,$D59) -> 0 | BG59: =BH59*BI59 -> 0 | BH59: =SUMIFS('1-2 人员岗位信息'!P:P,'1-2 人员岗位信息'!$C:$C,"自有人员",'1-2 人员岗位信息'!$B:$B,$D59) -> 0 | BJ59: =BK59*BL59 -> 0 | BK59: =SUMIFS('1-2 人员岗位信息'!Q:Q,'1-2 人员岗位信息'!$C:$C,"自有人员",'1-2 人员岗位信息'!$B:$B,$D59) -> 0
B60: 是 | C60: 1.1.1.3.1.2 | D60: 保洁主管 | E60: 指自有保洁主管 | G60: 按月编制，汇总成年总量 | H60: =AB60 -> 0 | I60: 岗位数量 | J60: =SUM(AD60,AG60,AJ60,AM60,AP60,AS60,AV60,AY60,BB60,BE60,BH60,BK60)/N60 -> #DIV/0! | K60: 岗 | L60: =H60/N60/J60 -> #DIV/0! | M60: 元/㎡/月 | N60: =COUNTIF(AD60,">0")+COUNTIF(AG60,">0")+COUNTIF(AJ60,">0")+COUNTIF(AM60,">0")+COUNTIF(AP60,">0")+COUNTIF(AS60,">0")+COUNTIF(AV60,">0")+COUNTIF(AY60,">0")+COUNTIF(BB60,">0")+COUNTIF(BE60,">0")+COUNTIF(BH60,">0")+COUNTIF(BK60,">0") -> 0 | AB60: =SUM(AC60,AF60,AI60,AL60,AO60,AR60,AU60,AX60,BA60,BD60,BG60,BJ60) -> 0 | AC60: =AD60*AE60 -> 0 | AD60: =SUMIFS('1-2 人员岗位信息'!F:F,'1-2 人员岗位信息'!$C:$C,"自有人员",'1-2 人员岗位信息'!$B:$B,$D60) -> 0 | AF60: =AG60*AH60 -> 0 | AG60: =SUMIFS('1-2 人员岗位信息'!G:G,'1-2 人员岗位信息'!$C:$C,"自有人员",'1-2 人员岗位信息'!$B:$B,$D60) -> 0 | AI60: =AJ60*AK60 -> 0 | AJ60: =SUMIFS('1-2 人员岗位信息'!H:H,'1-2 人员岗位信息'!$C:$C,"自有人员",'1-2 人员岗位信息'!$B:$B,$D60) -> 0 | AL60: =AM60*AN60 -> 0 | AM60: =SUMIFS('1-2 人员岗位信息'!I:I,'1-2 人员岗位信息'!$C:$C,"自有人员",'1-2 人员岗位信息'!$B:$B,$D60) -> 0 | AO60: =AP60*AQ60 -> 0 | AP60: =SUMIFS('1-2 人员岗位信息'!J:J,'1-2 人员岗位信息'!$C:$C,"自有人员",'1-2 人员岗位信息'!$B:$B,$D60) -> 0 | AR60: =AS60*AT60 -> 0 | AS60: =SUMIFS('1-2 人员岗位信息'!K:K,'1-2 人员岗位信息'!$C:$C,"自有人员",'1-2 人员岗位信息'!$B:$B,$D60) -> 0 | AU60: =AV60*AW60 -> 0 | AV60: =SUMIFS('1-2 人员岗位信息'!L:L,'1-2 人员岗位信息'!$C:$C,"自有人员",'1-2 人员岗位信息'!$B:$B,$D60) -> 0 | AX60: =AY60*AZ60 -> 0 | AY60: =SUMIFS('1-2 人员岗位信息'!M:M,'1-2 人员岗位信息'!$C:$C,"自有人员",'1-2 人员岗位信息'!$B:$B,$D60) -> 0 | BA60: =BB60*BC60 -> 0 | BB60: =SUMIFS('1-2 人员岗位信息'!N:N,'1-2 人员岗位信息'!$C:$C,"自有人员",'1-2 人员岗位信息'!$B:$B,$D60) -> 0 | BD60: =BE60*BF60 -> 0 | BE60: =SUMIFS('1-2 人员岗位信息'!O:O,'1-2 人员岗位信息'!$C:$C,"自有人员",'1-2 人员岗位信息'!$B:$B,$D60) -> 0 | BG60: =BH60*BI60 -> 0 | BH60: =SUMIFS('1-2 人员岗位信息'!P:P,'1-2 人员岗位信息'!$C:$C,"自有人员",'1-2 人员岗位信息'!$B:$B,$D60) -> 0 | BJ60: =BK60*BL60 -> 0 | BK60: =SUMIFS('1-2 人员岗位信息'!Q:Q,'1-2 人员岗位信息'!$C:$C,"自有人员",'1-2 人员岗位信息'!$B:$B,$D60) -> 0
B61: 是 | C61: 1.1.1.3.1.3 | D61: 楼内保洁员工 | E61: 住宅或非住项目的楼内公共区域保洁员工 | G61: 按月编制，汇总成年总量 | H61: =AB61 -> 0 | I61: 岗位数量 | J61: =SUM(AD61,AG61,AJ61,AM61,AP61,AS61,AV61,AY61,BB61,BE61,BH61,BK61)/N61 -> #DIV/0! | K61: 岗 | L61: =H61/N61/J61 -> #DIV/0! | M61: 元/㎡/月 | N61: =COUNTIF(AD61,">0")+COUNTIF(AG61,">0")+COUNTIF(AJ61,">0")+COUNTIF(AM61,">0")+COUNTIF(AP61,">0")+COUNTIF(AS61,">0")+COUNTIF(AV61,">0")+COUNTIF(AY61,">0")+COUNTIF(BB61,">0")+COUNTIF(BE61,">0")+COUNTIF(BH61,">0")+COUNTIF(BK61,">0") -> 0 | AB61: =SUM(AC61,AF61,AI61,AL61,AO61,AR61,AU61,AX61,BA61,BD61,BG61,BJ61) -> 0 | AC61: =AD61*AE61 -> 0 | AD61: =SUMIFS('1-2 人员岗位信息'!F:F,'1-2 人员岗位信息'!$C:$C,"自有人员",'1-2 人员岗位信息'!$B:$B,$D61) -> 0 | AF61: =AG61*AH61 -> 0 | AG61: =SUMIFS('1-2 人员岗位信息'!G:G,'1-2 人员岗位信息'!$C:$C,"自有人员",'1-2 人员岗位信息'!$B:$B,$D61) -> 0 | AI61: =AJ61*AK61 -> 0 | AJ61: =SUMIFS('1-2 人员岗位信息'!H:H,'1-2 人员岗位信息'!$C:$C,"自有人员",'1-2 人员岗位信息'!$B:$B,$D61) -> 0 | AL61: =AM61*AN61 -> 0 | AM61: =SUMIFS('1-2 人员岗位信息'!I:I,'1-2 人员岗位信息'!$C:$C,"自有人员",'1-2 人员岗位信息'!$B:$B,$D61) -> 0 | AO61: =AP61*AQ61 -> 0 | AP61: =SUMIFS('1-2 人员岗位信息'!J:J,'1-2 人员岗位信息'!$C:$C,"自有人员",'1-2 人员岗位信息'!$B:$B,$D61) -> 0 | AR61: =AS61*AT61 -> 0 | AS61: =SUMIFS('1-2 人员岗位信息'!K:K,'1-2 人员岗位信息'!$C:$C,"自有人员",'1-2 人员岗位信息'!$B:$B,$D61) -> 0 | AU61: =AV61*AW61 -> 0 | AV61: =SUMIFS('1-2 人员岗位信息'!L:L,'1-2 人员岗位信息'!$C:$C,"自有人员",'1-2 人员岗位信息'!$B:$B,$D61) -> 0 | AX61: =AY61*AZ61 -> 0 | AY61: =SUMIFS('1-2 人员岗位信息'!M:M,'1-2 人员岗位信息'!$C:$C,"自有人员",'1-2 人员岗位信息'!$B:$B,$D61) -> 0 | BA61: =BB61*BC61 -> 0 | BB61: =SUMIFS('1-2 人员岗位信息'!N:N,'1-2 人员岗位信息'!$C:$C,"自有人员",'1-2 人员岗位信息'!$B:$B,$D61) -> 0 | BD61: =BE61*BF61 -> 0 | BE61: =SUMIFS('1-2 人员岗位信息'!O:O,'1-2 人员岗位信息'!$C:$C,"自有人员",'1-2 人员岗位信息'!$B:$B,$D61) -> 0 | BG61: =BH61*BI61 -> 0 | BH61: =SUMIFS('1-2 人员岗位信息'!P:P,'1-2 人员岗位信息'!$C:$C,"自有人员",'1-2 人员岗位信息'!$B:$B,$D61) -> 0 | BJ61: =BK61*BL61 -> 0 | BK61: =SUMIFS('1-2 人员岗位信息'!Q:Q,'1-2 人员岗位信息'!$C:$C,"自有人员",'1-2 人员岗位信息'!$B:$B,$D61) -> 0
B62: 是 | C62: 1.1.1.3.1.4 | D62: 园区保洁员工 | E62: 住宅或非住项目的园区保洁员工 | G62: 按月编制，汇总成年总量 | H62: =AB62 -> 0 | I62: 岗位数量 | J62: =SUM(AD62,AG62,AJ62,AM62,AP62,AS62,AV62,AY62,BB62,BE62,BH62,BK62)/N62 -> #DIV/0! | K62: 岗 | L62: =H62/N62/J62 -> #DIV/0! | M62: 元/㎡/月 | N62: =COUNTIF(AD62,">0")+COUNTIF(AG62,">0")+COUNTIF(AJ62,">0")+COUNTIF(AM62,">0")+COUNTIF(AP62,">0")+COUNTIF(AS62,">0")+COUNTIF(AV62,">0")+COUNTIF(AY62,">0")+COUNTIF(BB62,">0")+COUNTIF(BE62,">0")+COUNTIF(BH62,">0")+COUNTIF(BK62,">0") -> 0 | AB62: =SUM(AC62,AF62,AI62,AL62,AO62,AR62,AU62,AX62,BA62,BD62,BG62,BJ62) -> 0 | AC62: =AD62*AE62 -> 0 | AD62: =SUMIFS('1-2 人员岗位信息'!F:F,'1-2 人员岗位信息'!$C:$C,"自有人员",'1-2 人员岗位信息'!$B:$B,$D62) -> 0 | AF62: =AG62*AH62 -> 0 | AG62: =SUMIFS('1-2 人员岗位信息'!G:G,'1-2 人员岗位信息'!$C:$C,"自有人员",'1-2 人员岗位信息'!$B:$B,$D62) -> 0 | AI62: =AJ62*AK62 -> 0 | AJ62: =SUMIFS('1-2 人员岗位信息'!H:H,'1-2 人员岗位信息'!$C:$C,"自有人员",'1-2 人员岗位信息'!$B:$B,$D62) -> 0 | AL62: =AM62*AN62 -> 0 | AM62: =SUMIFS('1-2 人员岗位信息'!I:I,'1-2 人员岗位信息'!$C:$C,"自有人员",'1-2 人员岗位信息'!$B:$B,$D62) -> 0 | AO62: =AP62*AQ62 -> 0 | AP62: =SUMIFS('1-2 人员岗位信息'!J:J,'1-2 人员岗位信息'!$C:$C,"自有人员",'1-2 人员岗位信息'!$B:$B,$D62) -> 0 | AR62: =AS62*AT62 -> 0 | AS62: =SUMIFS('1-2 人员岗位信息'!K:K,'1-2 人员岗位信息'!$C:$C,"自有人员",'1-2 人员岗位信息'!$B:$B,$D62) -> 0 | AU62: =AV62*AW62 -> 0 | AV62: =SUMIFS('1-2 人员岗位信息'!L:L,'1-2 人员岗位信息'!$C:$C,"自有人员",'1-2 人员岗位信息'!$B:$B,$D62) -> 0 | AX62: =AY62*AZ62 -> 0 | AY62: =SUMIFS('1-2 人员岗位信息'!M:M,'1-2 人员岗位信息'!$C:$C,"自有人员",'1-2 人员岗位信息'!$B:$B,$D62) -> 0 | BA62: =BB62*BC62 -> 0 | BB62: =SUMIFS('1-2 人员岗位信息'!N:N,'1-2 人员岗位信息'!$C:$C,"自有人员",'1-2 人员岗位信息'!$B:$B,$D62) -> 0 | BD62: =BE62*BF62 -> 0 | BE62: =SUMIFS('1-2 人员岗位信息'!O:O,'1-2 人员岗位信息'!$C:$C,"自有人员",'1-2 人员岗位信息'!$B:$B,$D62) -> 0 | BG62: =BH62*BI62 -> 0 | BH62: =SUMIFS('1-2 人员岗位信息'!P:P,'1-2 人员岗位信息'!$C:$C,"自有人员",'1-2 人员岗位信息'!$B:$B,$D62) -> 0 | BJ62: =BK62*BL62 -> 0 | BK62: =SUMIFS('1-2 人员岗位信息'!Q:Q,'1-2 人员岗位信息'!$C:$C,"自有人员",'1-2 人员岗位信息'!$B:$B,$D62) -> 0
B63: 是 | C63: 1.1.1.3.1.5 | D63: 地库保洁员工 | E63: 住宅或非住项目的地库保洁员工 | G63: 按月编制，汇总成年总量 | H63: =AB63 -> 0 | I63: 岗位数量 | J63: =SUM(AD63,AG63,AJ63,AM63,AP63,AS63,AV63,AY63,BB63,BE63,BH63,BK63)/N63 -> #DIV/0! | K63: 岗 | L63: =H63/N63/J63 -> #DIV/0! | M63: 元/㎡/月 | N63: =COUNTIF(AD63,">0")+COUNTIF(AG63,">0")+COUNTIF(AJ63,">0")+COUNTIF(AM63,">0")+COUNTIF(AP63,">0")+COUNTIF(AS63,">0")+COUNTIF(AV63,">0")+COUNTIF(AY63,">0")+COUNTIF(BB63,">0")+COUNTIF(BE63,">0")+COUNTIF(BH63,">0")+COUNTIF(BK63,">0") -> 0 | AB63: =SUM(AC63,AF63,AI63,AL63,AO63,AR63,AU63,AX63,BA63,BD63,BG63,BJ63) -> 0 | AC63: =AD63*AE63 -> 0 | AD63: =SUMIFS('1-2 人员岗位信息'!F:F,'1-2 人员岗位信息'!$C:$C,"自有人员",'1-2 人员岗位信息'!$B:$B,$D63) -> 0 | AF63: =AG63*AH63 -> 0 | AG63: =SUMIFS('1-2 人员岗位信息'!G:G,'1-2 人员岗位信息'!$C:$C,"自有人员",'1-2 人员岗位信息'!$B:$B,$D63) -> 0 | AI63: =AJ63*AK63 -> 0 | AJ63: =SUMIFS('1-2 人员岗位信息'!H:H,'1-2 人员岗位信息'!$C:$C,"自有人员",'1-2 人员岗位信息'!$B:$B,$D63) -> 0 | AL63: =AM63*AN63 -> 0 | AM63: =SUMIFS('1-2 人员岗位信息'!I:I,'1-2 人员岗位信息'!$C:$C,"自有人员",'1-2 人员岗位信息'!$B:$B,$D63) -> 0 | AO63: =AP63*AQ63 -> 0 | AP63: =SUMIFS('1-2 人员岗位信息'!J:J,'1-2 人员岗位信息'!$C:$C,"自有人员",'1-2 人员岗位信息'!$B:$B,$D63) -> 0 | AR63: =AS63*AT63 -> 0 | AS63: =SUMIFS('1-2 人员岗位信息'!K:K,'1-2 人员岗位信息'!$C:$C,"自有人员",'1-2 人员岗位信息'!$B:$B,$D63) -> 0 | AU63: =AV63*AW63 -> 0 | AV63: =SUMIFS('1-2 人员岗位信息'!L:L,'1-2 人员岗位信息'!$C:$C,"自有人员",'1-2 人员岗位信息'!$B:$B,$D63) -> 0 | AX63: =AY63*AZ63 -> 0 | AY63: =SUMIFS('1-2 人员岗位信息'!M:M,'1-2 人员岗位信息'!$C:$C,"自有人员",'1-2 人员岗位信息'!$B:$B,$D63) -> 0 | BA63: =BB63*BC63 -> 0 | BB63: =SUMIFS('1-2 人员岗位信息'!N:N,'1-2 人员岗位信息'!$C:$C,"自有人员",'1-2 人员岗位信息'!$B:$B,$D63) -> 0 | BD63: =BE63*BF63 -> 0 | BE63: =SUMIFS('1-2 人员岗位信息'!O:O,'1-2 人员岗位信息'!$C:$C,"自有人员",'1-2 人员岗位信息'!$B:$B,$D63) -> 0 | BG63: =BH63*BI63 -> 0 | BH63: =SUMIFS('1-2 人员岗位信息'!P:P,'1-2 人员岗位信息'!$C:$C,"自有人员",'1-2 人员岗位信息'!$B:$B,$D63) -> 0 | BJ63: =BK63*BL63 -> 0 | BK63: =SUMIFS('1-2 人员岗位信息'!Q:Q,'1-2 人员岗位信息'!$C:$C,"自有人员",'1-2 人员岗位信息'!$B:$B,$D63) -> 0
B64: 是 | C64: 1.1.1.3.1.6 | D64: 外围保洁员工 | E64: 住宅或非住项目的园区外围保洁员工 | G64: 按月编制，汇总成年总量 | H64: =AB64 -> 0 | I64: 岗位数量 | J64: =SUM(AD64,AG64,AJ64,AM64,AP64,AS64,AV64,AY64,BB64,BE64,BH64,BK64)/N64 -> #DIV/0! | K64: 岗 | L64: =H64/N64/J64 -> #DIV/0! | M64: 元/㎡/月 | N64: =COUNTIF(AD64,">0")+COUNTIF(AG64,">0")+COUNTIF(AJ64,">0")+COUNTIF(AM64,">0")+COUNTIF(AP64,">0")+COUNTIF(AS64,">0")+COUNTIF(AV64,">0")+COUNTIF(AY64,">0")+COUNTIF(BB64,">0")+COUNTIF(BE64,">0")+COUNTIF(BH64,">0")+COUNTIF(BK64,">0") -> 0 | AB64: =SUM(AC64,AF64,AI64,AL64,AO64,AR64,AU64,AX64,BA64,BD64,BG64,BJ64) -> 0 | AC64: =AD64*AE64 -> 0 | AD64: =SUMIFS('1-2 人员岗位信息'!F:F,'1-2 人员岗位信息'!$C:$C,"自有人员",'1-2 人员岗位信息'!$B:$B,$D64) -> 0 | AF64: =AG64*AH64 -> 0 | AG64: =SUMIFS('1-2 人员岗位信息'!G:G,'1-2 人员岗位信息'!$C:$C,"自有人员",'1-2 人员岗位信息'!$B:$B,$D64) -> 0 | AI64: =AJ64*AK64 -> 0 | AJ64: =SUMIFS('1-2 人员岗位信息'!H:H,'1-2 人员岗位信息'!$C:$C,"自有人员",'1-2 人员岗位信息'!$B:$B,$D64) -> 0 | AL64: =AM64*AN64 -> 0 | AM64: =SUMIFS('1-2 人员岗位信息'!I:I,'1-2 人员岗位信息'!$C:$C,"自有人员",'1-2 人员岗位信息'!$B:$B,$D64) -> 0 | AO64: =AP64*AQ64 -> 0 | AP64: =SUMIFS('1-2 人员岗位信息'!J:J,'1-2 人员岗位信息'!$C:$C,"自有人员",'1-2 人员岗位信息'!$B:$B,$D64) -> 0 | AR64: =AS64*AT64 -> 0 | AS64: =SUMIFS('1-2 人员岗位信息'!K:K,'1-2 人员岗位信息'!$C:$C,"自有人员",'1-2 人员岗位信息'!$B:$B,$D64) -> 0 | AU64: =AV64*AW64 -> 0 | AV64: =SUMIFS('1-2 人员岗位信息'!L:L,'1-2 人员岗位信息'!$C:$C,"自有人员",'1-2 人员岗位信息'!$B:$B,$D64) -> 0 | AX64: =AY64*AZ64 -> 0 | AY64: =SUMIFS('1-2 人员岗位信息'!M:M,'1-2 人员岗位信息'!$C:$C,"自有人员",'1-2 人员岗位信息'!$B:$B,$D64) -> 0 | BA64: =BB64*BC64 -> 0 | BB64: =SUMIFS('1-2 人员岗位信息'!N:N,'1-2 人员岗位信息'!$C:$C,"自有人员",'1-2 人员岗位信息'!$B:$B,$D64) -> 0 | BD64: =BE64*BF64 -> 0 | BE64: =SUMIFS('1-2 人员岗位信息'!O:O,'1-2 人员岗位信息'!$C:$C,"自有人员",'1-2 人员岗位信息'!$B:$B,$D64) -> 0 | BG64: =BH64*BI64 -> 0 | BH64: =SUMIFS('1-2 人员岗位信息'!P:P,'1-2 人员岗位信息'!$C:$C,"自有人员",'1-2 人员岗位信息'!$B:$B,$D64) -> 0 | BJ64: =BK64*BL64 -> 0 | BK64: =SUMIFS('1-2 人员岗位信息'!Q:Q,'1-2 人员岗位信息'!$C:$C,"自有人员",'1-2 人员岗位信息'!$B:$B,$D64) -> 0
B65: 是 | C65: 1.1.1.3.1.7 | D65: 垃圾分拣员工 | E65: 住宅或非住项目需进行垃圾分类而设置的垃圾分拣专岗保洁员工 | G65: 按月编制，汇总成年总量 | H65: =AB65 -> 0 | I65: 岗位数量 | J65: =SUM(AD65,AG65,AJ65,AM65,AP65,AS65,AV65,AY65,BB65,BE65,BH65,BK65)/N65 -> #DIV/0! | K65: 岗 | L65: =H65/N65/J65 -> #DIV/0! | M65: 元/㎡/月 | N65: =COUNTIF(AD65,">0")+COUNTIF(AG65,">0")+COUNTIF(AJ65,">0")+COUNTIF(AM65,">0")+COUNTIF(AP65,">0")+COUNTIF(AS65,">0")+COUNTIF(AV65,">0")+COUNTIF(AY65,">0")+COUNTIF(BB65,">0")+COUNTIF(BE65,">0")+COUNTIF(BH65,">0")+COUNTIF(BK65,">0") -> 0 | AB65: =SUM(AC65,AF65,AI65,AL65,AO65,AR65,AU65,AX65,BA65,BD65,BG65,BJ65) -> 0 | AC65: =AD65*AE65 -> 0 | AD65: =SUMIFS('1-2 人员岗位信息'!F:F,'1-2 人员岗位信息'!$C:$C,"自有人员",'1-2 人员岗位信息'!$B:$B,$D65) -> 0 | AF65: =AG65*AH65 -> 0 | AG65: =SUMIFS('1-2 人员岗位信息'!G:G,'1-2 人员岗位信息'!$C:$C,"自有人员",'1-2 人员岗位信息'!$B:$B,$D65) -> 0 | AI65: =AJ65*AK65 -> 0 | AJ65: =SUMIFS('1-2 人员岗位信息'!H:H,'1-2 人员岗位信息'!$C:$C,"自有人员",'1-2 人员岗位信息'!$B:$B,$D65) -> 0 | AL65: =AM65*AN65 -> 0 | AM65: =SUMIFS('1-2 人员岗位信息'!I:I,'1-2 人员岗位信息'!$C:$C,"自有人员",'1-2 人员岗位信息'!$B:$B,$D65) -> 0 | AO65: =AP65*AQ65 -> 0 | AP65: =SUMIFS('1-2 人员岗位信息'!J:J,'1-2 人员岗位信息'!$C:$C,"自有人员",'1-2 人员岗位信息'!$B:$B,$D65) -> 0 | AR65: =AS65*AT65 -> 0 | AS65: =SUMIFS('1-2 人员岗位信息'!K:K,'1-2 人员岗位信息'!$C:$C,"自有人员",'1-2 人员岗位信息'!$B:$B,$D65) -> 0 | AU65: =AV65*AW65 -> 0 | AV65: =SUMIFS('1-2 人员岗位信息'!L:L,'1-2 人员岗位信息'!$C:$C,"自有人员",'1-2 人员岗位信息'!$B:$B,$D65) -> 0 | AX65: =AY65*AZ65 -> 0 | AY65: =SUMIFS('1-2 人员岗位信息'!M:M,'1-2 人员岗位信息'!$C:$C,"自有人员",'1-2 人员岗位信息'!$B:$B,$D65) -> 0 | BA65: =BB65*BC65 -> 0 | BB65: =SUMIFS('1-2 人员岗位信息'!N:N,'1-2 人员岗位信息'!$C:$C,"自有人员",'1-2 人员岗位信息'!$B:$B,$D65) -> 0 | BD65: =BE65*BF65 -> 0 | BE65: =SUMIFS('1-2 人员岗位信息'!O:O,'1-2 人员岗位信息'!$C:$C,"自有人员",'1-2 人员岗位信息'!$B:$B,$D65) -> 0 | BG65: =BH65*BI65 -> 0 | BH65: =SUMIFS('1-2 人员岗位信息'!P:P,'1-2 人员岗位信息'!$C:$C,"自有人员",'1-2 人员岗位信息'!$B:$B,$D65) -> 0 | BJ65: =BK65*BL65 -> 0 | BK65: =SUMIFS('1-2 人员岗位信息'!Q:Q,'1-2 人员岗位信息'!$C:$C,"自有人员",'1-2 人员岗位信息'!$B:$B,$D65) -> 0
B66: 是 | C66: 1.1.1.3.1.8 | D66: 道路清扫员工 | E66: 适用于城市服务项目道路清扫岗位员工 | G66: 按月编制，汇总成年总量 | H66: =AB66 -> 0 | I66: 岗位数量 | J66: =SUM(AD66,AG66,AJ66,AM66,AP66,AS66,AV66,AY66,BB66,BE66,BH66,BK66)/N66 -> #DIV/0! | K66: 岗 | L66: =H66/N66/J66 -> #DIV/0! | M66: 元/㎡/月 | N66: =COUNTIF(AD66,">0")+COUNTIF(AG66,">0")+COUNTIF(AJ66,">0")+COUNTIF(AM66,">0")+COUNTIF(AP66,">0")+COUNTIF(AS66,">0")+COUNTIF(AV66,">0")+COUNTIF(AY66,">0")+COUNTIF(BB66,">0")+COUNTIF(BE66,">0")+COUNTIF(BH66,">0")+COUNTIF(BK66,">0") -> 0 | AB66: =SUM(AC66,AF66,AI66,AL66,AO66,AR66,AU66,AX66,BA66,BD66,BG66,BJ66) -> 0 | AC66: =AD66*AE66 -> 0 | AD66: =SUMIFS('1-2 人员岗位信息'!F:F,'1-2 人员岗位信息'!$C:$C,"自有人员",'1-2 人员岗位信息'!$B:$B,$D66) -> 0 | AF66: =AG66*AH66 -> 0 | AG66: =SUMIFS('1-2 人员岗位信息'!G:G,'1-2 人员岗位信息'!$C:$C,"自有人员",'1-2 人员岗位信息'!$B:$B,$D66) -> 0 | AI66: =AJ66*AK66 -> 0 | AJ66: =SUMIFS('1-2 人员岗位信息'!H:H,'1-2 人员岗位信息'!$C:$C,"自有人员",'1-2 人员岗位信息'!$B:$B,$D66) -> 0 | AL66: =AM66*AN66 -> 0 | AM66: =SUMIFS('1-2 人员岗位信息'!I:I,'1-2 人员岗位信息'!$C:$C,"自有人员",'1-2 人员岗位信息'!$B:$B,$D66) -> 0 | AO66: =AP66*AQ66 -> 0 | AP66: =SUMIFS('1-2 人员岗位信息'!J:J,'1-2 人员岗位信息'!$C:$C,"自有人员",'1-2 人员岗位信息'!$B:$B,$D66) -> 0 | AR66: =AS66*AT66 -> 0 | AS66: =SUMIFS('1-2 人员岗位信息'!K:K,'1-2 人员岗位信息'!$C:$C,"自有人员",'1-2 人员岗位信息'!$B:$B,$D66) -> 0 | AU66: =AV66*AW66 -> 0 | AV66: =SUMIFS('1-2 人员岗位信息'!L:L,'1-2 人员岗位信息'!$C:$C,"自有人员",'1-2 人员岗位信息'!$B:$B,$D66) -> 0 | AX66: =AY66*AZ66 -> 0 | AY66: =SUMIFS('1-2 人员岗位信息'!M:M,'1-2 人员岗位信息'!$C:$C,"自有人员",'1-2 人员岗位信息'!$B:$B,$D66) -> 0 | BA66: =BB66*BC66 -> 0 | BB66: =SUMIFS('1-2 人员岗位信息'!N:N,'1-2 人员岗位信息'!$C:$C,"自有人员",'1-2 人员岗位信息'!$B:$B,$D66) -> 0 | BD66: =BE66*BF66 -> 0 | BE66: =SUMIFS('1-2 人员岗位信息'!O:O,'1-2 人员岗位信息'!$C:$C,"自有人员",'1-2 人员岗位信息'!$B:$B,$D66) -> 0 | BG66: =BH66*BI66 -> 0 | BH66: =SUMIFS('1-2 人员岗位信息'!P:P,'1-2 人员岗位信息'!$C:$C,"自有人员",'1-2 人员岗位信息'!$B:$B,$D66) -> 0 | BJ66: =BK66*BL66 -> 0 | BK66: =SUMIFS('1-2 人员岗位信息'!Q:Q,'1-2 人员岗位信息'!$C:$C,"自有人员",'1-2 人员岗位信息'!$B:$B,$D66) -> 0
B67: 是 | C67: 1.1.1.3.1.9 | D67: 卫生间保洁员工 | E67: 适用于写字楼、商业等非住业态的卫生间专岗 | G67: 按月编制，汇总成年总量 | H67: =AB67 -> 0 | I67: 岗位数量 | J67: =SUM(AD67,AG67,AJ67,AM67,AP67,AS67,AV67,AY67,BB67,BE67,BH67,BK67)/N67 -> #DIV/0! | K67: 岗 | L67: =H67/N67/J67 -> #DIV/0! | M67: 元/㎡/月 | N67: =COUNTIF(AD67,">0")+COUNTIF(AG67,">0")+COUNTIF(AJ67,">0")+COUNTIF(AM67,">0")+COUNTIF(AP67,">0")+COUNTIF(AS67,">0")+COUNTIF(AV67,">0")+COUNTIF(AY67,">0")+COUNTIF(BB67,">0")+COUNTIF(BE67,">0")+COUNTIF(BH67,">0")+COUNTIF(BK67,">0") -> 0 | AB67: =SUM(AC67,AF67,AI67,AL67,AO67,AR67,AU67,AX67,BA67,BD67,BG67,BJ67) -> 0 | AC67: =AD67*AE67 -> 0 | AD67: =SUMIFS('1-2 人员岗位信息'!F:F,'1-2 人员岗位信息'!$C:$C,"自有人员",'1-2 人员岗位信息'!$B:$B,$D67) -> 0 | AF67: =AG67*AH67 -> 0 | AG67: =SUMIFS('1-2 人员岗位信息'!G:G,'1-2 人员岗位信息'!$C:$C,"自有人员",'1-2 人员岗位信息'!$B:$B,$D67) -> 0 | AI67: =AJ67*AK67 -> 0 | AJ67: =SUMIFS('1-2 人员岗位信息'!H:H,'1-2 人员岗位信息'!$C:$C,"自有人员",'1-2 人员岗位信息'!$B:$B,$D67) -> 0 | AL67: =AM67*AN67 -> 0 | AM67: =SUMIFS('1-2 人员岗位信息'!I:I,'1-2 人员岗位信息'!$C:$C,"自有人员",'1-2 人员岗位信息'!$B:$B,$D67) -> 0 | AO67: =AP67*AQ67 -> 0 | AP67: =SUMIFS('1-2 人员岗位信息'!J:J,'1-2 人员岗位信息'!$C:$C,"自有人员",'1-2 人员岗位信息'!$B:$B,$D67) -> 0 | AR67: =AS67*AT67 -> 0 | AS67: =SUMIFS('1-2 人员岗位信息'!K:K,'1-2 人员岗位信息'!$C:$C,"自有人员",'1-2 人员岗位信息'!$B:$B,$D67) -> 0 | AU67: =AV67*AW67 -> 0 | AV67: =SUMIFS('1-2 人员岗位信息'!L:L,'1-2 人员岗位信息'!$C:$C,"自有人员",'1-2 人员岗位信息'!$B:$B,$D67) -> 0 | AX67: =AY67*AZ67 -> 0 | AY67: =SUMIFS('1-2 人员岗位信息'!M:M,'1-2 人员岗位信息'!$C:$C,"自有人员",'1-2 人员岗位信息'!$B:$B,$D67) -> 0 | BA67: =BB67*BC67 -> 0 | BB67: =SUMIFS('1-2 人员岗位信息'!N:N,'1-2 人员岗位信息'!$C:$C,"自有人员",'1-2 人员岗位信息'!$B:$B,$D67) -> 0 | BD67: =BE67*BF67 -> 0 | BE67: =SUMIFS('1-2 人员岗位信息'!O:O,'1-2 人员岗位信息'!$C:$C,"自有人员",'1-2 人员岗位信息'!$B:$B,$D67) -> 0 | BG67: =BH67*BI67 -> 0 | BH67: =SUMIFS('1-2 人员岗位信息'!P:P,'1-2 人员岗位信息'!$C:$C,"自有人员",'1-2 人员岗位信息'!$B:$B,$D67) -> 0 | BJ67: =BK67*BL67 -> 0 | BK67: =SUMIFS('1-2 人员岗位信息'!Q:Q,'1-2 人员岗位信息'!$C:$C,"自有人员",'1-2 人员岗位信息'!$B:$B,$D67) -> 0
B68: 是 | C68: 1.1.1.3.1.10 | D68: 其他保洁员工 | E68: 上述不包含的岗位可适用此项 | G68: 按月编制，汇总成年总量 | H68: =AB68 -> 0 | I68: 岗位数量 | J68: =SUM(AD68,AG68,AJ68,AM68,AP68,AS68,AV68,AY68,BB68,BE68,BH68,BK68)/N68 -> #DIV/0! | K68: 岗 | L68: =H68/N68/J68 -> #DIV/0! | M68: 元/㎡/月 | N68: =COUNTIF(AD68,">0")+COUNTIF(AG68,">0")+COUNTIF(AJ68,">0")+COUNTIF(AM68,">0")+COUNTIF(AP68,">0")+COUNTIF(AS68,">0")+COUNTIF(AV68,">0")+COUNTIF(AY68,">0")+COUNTIF(BB68,">0")+COUNTIF(BE68,">0")+COUNTIF(BH68,">0")+COUNTIF(BK68,">0") -> 0 | AB68: =SUM(AC68,AF68,AI68,AL68,AO68,AR68,AU68,AX68,BA68,BD68,BG68,BJ68) -> 0 | AC68: =AD68*AE68 -> 0 | AD68: =SUMIFS('1-2 人员岗位信息'!F:F,'1-2 人员岗位信息'!$C:$C,"自有人员",'1-2 人员岗位信息'!$B:$B,$D68) -> 0 | AF68: =AG68*AH68 -> 0 | AG68: =SUMIFS('1-2 人员岗位信息'!G:G,'1-2 人员岗位信息'!$C:$C,"自有人员",'1-2 人员岗位信息'!$B:$B,$D68) -> 0 | AI68: =AJ68*AK68 -> 0 | AJ68: =SUMIFS('1-2 人员岗位信息'!H:H,'1-2 人员岗位信息'!$C:$C,"自有人员",'1-2 人员岗位信息'!$B:$B,$D68) -> 0 | AL68: =AM68*AN68 -> 0 | AM68: =SUMIFS('1-2 人员岗位信息'!I:I,'1-2 人员岗位信息'!$C:$C,"自有人员",'1-2 人员岗位信息'!$B:$B,$D68) -> 0 | AO68: =AP68*AQ68 -> 0 | AP68: =SUMIFS('1-2 人员岗位信息'!J:J,'1-2 人员岗位信息'!$C:$C,"自有人员",'1-2 人员岗位信息'!$B:$B,$D68) -> 0 | AR68: =AS68*AT68 -> 0 | AS68: =SUMIFS('1-2 人员岗位信息'!K:K,'1-2 人员岗位信息'!$C:$C,"自有人员",'1-2 人员岗位信息'!$B:$B,$D68) -> 0 | AU68: =AV68*AW68 -> 0 | AV68: =SUMIFS('1-2 人员岗位信息'!L:L,'1-2 人员岗位信息'!$C:$C,"自有人员",'1-2 人员岗位信息'!$B:$B,$D68) -> 0 | AX68: =AY68*AZ68 -> 0 | AY68: =SUMIFS('1-2 人员岗位信息'!M:M,'1-2 人员岗位信息'!$C:$C,"自有人员",'1-2 人员岗位信息'!$B:$B,$D68) -> 0 | BA68: =BB68*BC68 -> 0 | BB68: =SUMIFS('1-2 人员岗位信息'!N:N,'1-2 人员岗位信息'!$C:$C,"自有人员",'1-2 人员岗位信息'!$B:$B,$D68) -> 0 | BD68: =BE68*BF68 -> 0 | BE68: =SUMIFS('1-2 人员岗位信息'!O:O,'1-2 人员岗位信息'!$C:$C,"自有人员",'1-2 人员岗位信息'!$B:$B,$D68) -> 0 | BG68: =BH68*BI68 -> 0 | BH68: =SUMIFS('1-2 人员岗位信息'!P:P,'1-2 人员岗位信息'!$C:$C,"自有人员",'1-2 人员岗位信息'!$B:$B,$D68) -> 0 | BJ68: =BK68*BL68 -> 0 | BK68: =SUMIFS('1-2 人员岗位信息'!Q:Q,'1-2 人员岗位信息'!$C:$C,"自有人员",'1-2 人员岗位信息'!$B:$B,$D68) -> 0
B69: 否 | C69: 1.1.1.3.2 | D69: 劳务派遣 | H69: =SUM(H70:H79) -> 0 | AB69: =SUM(AB70:AB79) -> 0 | AC69: =SUM(AC70:AC79) -> 0 | AF69: =SUM(AF70:AF79) -> 0 | AI69: =SUM(AI70:AI79) -> 0 | AL69: =SUM(AL70:AL79) -> 0 | AO69: =SUM(AO70:AO79) -> 0 | AR69: =SUM(AR70:AR79) -> 0 | AU69: =SUM(AU70:AU79) -> 0 | AX69: =SUM(AX70:AX79) -> 0 | BA69: =SUM(BA70:BA79) -> 0 | BD69: =SUM(BD70:BD79) -> 0 | BG69: =SUM(BG70:BG79) -> 0 | BJ69: =SUM(BJ70:BJ79) -> 0
B70: 是 | C70: 1.1.1.3.2.1 | D70: 保洁经理 | E70: 指派遣保洁经理 | G70: 按月编制，汇总成年总量 | H70: =AB70 -> 0 | I70: 岗位数量 | J70: =SUM(AD70,AG70,AJ70,AM70,AP70,AS70,AV70,AY70,BB70,BE70,BH70,BK70)/N70 -> #DIV/0! | K70: 岗 | L70: =H70/N70/J70 -> #DIV/0! | M70: 元/㎡/月 | N70: =COUNTIF(AD70,">0")+COUNTIF(AG70,">0")+COUNTIF(AJ70,">0")+COUNTIF(AM70,">0")+COUNTIF(AP70,">0")+COUNTIF(AS70,">0")+COUNTIF(AV70,">0")+COUNTIF(AY70,">0")+COUNTIF(BB70,">0")+COUNTIF(BE70,">0")+COUNTIF(BH70,">0")+COUNTIF(BK70,">0") -> 0 | AB70: =SUM(AC70,AF70,AI70,AL70,AO70,AR70,AU70,AX70,BA70,BD70,BG70,BJ70) -> 0 | AC70: =AD70*AE70 -> 0 | AD70: =SUMIFS('1-2 人员岗位信息'!F:F,'1-2 人员岗位信息'!$C:$C,"劳务派遣",'1-2 人员岗位信息'!$B:$B,$D70) -> 0 | AF70: =AG70*AH70 -> 0 | AG70: =SUMIFS('1-2 人员岗位信息'!G:G,'1-2 人员岗位信息'!$C:$C,"劳务派遣",'1-2 人员岗位信息'!$B:$B,$D70) -> 0 | AI70: =AJ70*AK70 -> 0 | AJ70: =SUMIFS('1-2 人员岗位信息'!H:H,'1-2 人员岗位信息'!$C:$C,"劳务派遣",'1-2 人员岗位信息'!$B:$B,$D70) -> 0 | AL70: =AM70*AN70 -> 0 | AM70: =SUMIFS('1-2 人员岗位信息'!I:I,'1-2 人员岗位信息'!$C:$C,"劳务派遣",'1-2 人员岗位信息'!$B:$B,$D70) -> 0 | AO70: =AP70*AQ70 -> 0 | AP70: =SUMIFS('1-2 人员岗位信息'!J:J,'1-2 人员岗位信息'!$C:$C,"劳务派遣",'1-2 人员岗位信息'!$B:$B,$D70) -> 0 | AR70: =AS70*AT70 -> 0 | AS70: =SUMIFS('1-2 人员岗位信息'!K:K,'1-2 人员岗位信息'!$C:$C,"劳务派遣",'1-2 人员岗位信息'!$B:$B,$D70) -> 0 | AU70: =AV70*AW70 -> 0 | AV70: =SUMIFS('1-2 人员岗位信息'!L:L,'1-2 人员岗位信息'!$C:$C,"劳务派遣",'1-2 人员岗位信息'!$B:$B,$D70) -> 0 | AX70: =AY70*AZ70 -> 0 | AY70: =SUMIFS('1-2 人员岗位信息'!M:M,'1-2 人员岗位信息'!$C:$C,"劳务派遣",'1-2 人员岗位信息'!$B:$B,$D70) -> 0 | BA70: =BB70*BC70 -> 0 | BB70: =SUMIFS('1-2 人员岗位信息'!N:N,'1-2 人员岗位信息'!$C:$C,"劳务派遣",'1-2 人员岗位信息'!$B:$B,$D70) -> 0 | BD70: =BE70*BF70 -> 0 | BE70: =SUMIFS('1-2 人员岗位信息'!O:O,'1-2 人员岗位信息'!$C:$C,"劳务派遣",'1-2 人员岗位信息'!$B:$B,$D70) -> 0 | BG70: =BH70*BI70 -> 0 | BH70: =SUMIFS('1-2 人员岗位信息'!P:P,'1-2 人员岗位信息'!$C:$C,"劳务派遣",'1-2 人员岗位信息'!$B:$B,$D70) -> 0 | BJ70: =BK70*BL70 -> 0 | BK70: =SUMIFS('1-2 人员岗位信息'!Q:Q,'1-2 人员岗位信息'!$C:$C,"劳务派遣",'1-2 人员岗位信息'!$B:$B,$D70) -> 0
B71: 是 | C71: 1.1.1.3.2.2 | D71: 保洁主管 | E71: 指派遣保洁主管 | G71: 按月编制，汇总成年总量 | H71: =AB71 -> 0 | I71: 岗位数量 | J71: =SUM(AD71,AG71,AJ71,AM71,AP71,AS71,AV71,AY71,BB71,BE71,BH71,BK71)/N71 -> #DIV/0! | K71: 岗 | L71: =H71/N71/J71 -> #DIV/0! | M71: 元/㎡/月 | N71: =COUNTIF(AD71,">0")+COUNTIF(AG71,">0")+COUNTIF(AJ71,">0")+COUNTIF(AM71,">0")+COUNTIF(AP71,">0")+COUNTIF(AS71,">0")+COUNTIF(AV71,">0")+COUNTIF(AY71,">0")+COUNTIF(BB71,">0")+COUNTIF(BE71,">0")+COUNTIF(BH71,">0")+COUNTIF(BK71,">0") -> 0 | AB71: =SUM(AC71,AF71,AI71,AL71,AO71,AR71,AU71,AX71,BA71,BD71,BG71,BJ71) -> 0 | AC71: =AD71*AE71 -> 0 | AD71: =SUMIFS('1-2 人员岗位信息'!F:F,'1-2 人员岗位信息'!$C:$C,"劳务派遣",'1-2 人员岗位信息'!$B:$B,$D71) -> 0 | AF71: =AG71*AH71 -> 0 | AG71: =SUMIFS('1-2 人员岗位信息'!G:G,'1-2 人员岗位信息'!$C:$C,"劳务派遣",'1-2 人员岗位信息'!$B:$B,$D71) -> 0 | AI71: =AJ71*AK71 -> 0 | AJ71: =SUMIFS('1-2 人员岗位信息'!H:H,'1-2 人员岗位信息'!$C:$C,"劳务派遣",'1-2 人员岗位信息'!$B:$B,$D71) -> 0 | AL71: =AM71*AN71 -> 0 | AM71: =SUMIFS('1-2 人员岗位信息'!I:I,'1-2 人员岗位信息'!$C:$C,"劳务派遣",'1-2 人员岗位信息'!$B:$B,$D71) -> 0 | AO71: =AP71*AQ71 -> 0 | AP71: =SUMIFS('1-2 人员岗位信息'!J:J,'1-2 人员岗位信息'!$C:$C,"劳务派遣",'1-2 人员岗位信息'!$B:$B,$D71) -> 0 | AR71: =AS71*AT71 -> 0 | AS71: =SUMIFS('1-2 人员岗位信息'!K:K,'1-2 人员岗位信息'!$C:$C,"劳务派遣",'1-2 人员岗位信息'!$B:$B,$D71) -> 0 | AU71: =AV71*AW71 -> 0 | AV71: =SUMIFS('1-2 人员岗位信息'!L:L,'1-2 人员岗位信息'!$C:$C,"劳务派遣",'1-2 人员岗位信息'!$B:$B,$D71) -> 0 | AX71: =AY71*AZ71 -> 0 | AY71: =SUMIFS('1-2 人员岗位信息'!M:M,'1-2 人员岗位信息'!$C:$C,"劳务派遣",'1-2 人员岗位信息'!$B:$B,$D71) -> 0 | BA71: =BB71*BC71 -> 0 | BB71: =SUMIFS('1-2 人员岗位信息'!N:N,'1-2 人员岗位信息'!$C:$C,"劳务派遣",'1-2 人员岗位信息'!$B:$B,$D71) -> 0 | BD71: =BE71*BF71 -> 0 | BE71: =SUMIFS('1-2 人员岗位信息'!O:O,'1-2 人员岗位信息'!$C:$C,"劳务派遣",'1-2 人员岗位信息'!$B:$B,$D71) -> 0 | BG71: =BH71*BI71 -> 0 | BH71: =SUMIFS('1-2 人员岗位信息'!P:P,'1-2 人员岗位信息'!$C:$C,"劳务派遣",'1-2 人员岗位信息'!$B:$B,$D71) -> 0 | BJ71: =BK71*BL71 -> 0 | BK71: =SUMIFS('1-2 人员岗位信息'!Q:Q,'1-2 人员岗位信息'!$C:$C,"劳务派遣",'1-2 人员岗位信息'!$B:$B,$D71) -> 0
B72: 是 | C72: 1.1.1.3.2.3 | D72: 楼内保洁员工 | E72: 住宅或非住项目的楼内公共区域保洁员工 | G72: 按月编制，汇总成年总量 | H72: =AB72 -> 0 | I72: 岗位数量 | J72: =SUM(AD72,AG72,AJ72,AM72,AP72,AS72,AV72,AY72,BB72,BE72,BH72,BK72)/N72 -> #DIV/0! | K72: 岗 | L72: =H72/N72/J72 -> #DIV/0! | M72: 元/㎡/月 | N72: =COUNTIF(AD72,">0")+COUNTIF(AG72,">0")+COUNTIF(AJ72,">0")+COUNTIF(AM72,">0")+COUNTIF(AP72,">0")+COUNTIF(AS72,">0")+COUNTIF(AV72,">0")+COUNTIF(AY72,">0")+COUNTIF(BB72,">0")+COUNTIF(BE72,">0")+COUNTIF(BH72,">0")+COUNTIF(BK72,">0") -> 0 | AB72: =SUM(AC72,AF72,AI72,AL72,AO72,AR72,AU72,AX72,BA72,BD72,BG72,BJ72) -> 0 | AC72: =AD72*AE72 -> 0 | AD72: =SUMIFS('1-2 人员岗位信息'!F:F,'1-2 人员岗位信息'!$C:$C,"劳务派遣",'1-2 人员岗位信息'!$B:$B,$D72) -> 0 | AF72: =AG72*AH72 -> 0 | AG72: =SUMIFS('1-2 人员岗位信息'!G:G,'1-2 人员岗位信息'!$C:$C,"劳务派遣",'1-2 人员岗位信息'!$B:$B,$D72) -> 0 | AI72: =AJ72*AK72 -> 0 | AJ72: =SUMIFS('1-2 人员岗位信息'!H:H,'1-2 人员岗位信息'!$C:$C,"劳务派遣",'1-2 人员岗位信息'!$B:$B,$D72) -> 0 | AL72: =AM72*AN72 -> 0 | AM72: =SUMIFS('1-2 人员岗位信息'!I:I,'1-2 人员岗位信息'!$C:$C,"劳务派遣",'1-2 人员岗位信息'!$B:$B,$D72) -> 0 | AO72: =AP72*AQ72 -> 0 | AP72: =SUMIFS('1-2 人员岗位信息'!J:J,'1-2 人员岗位信息'!$C:$C,"劳务派遣",'1-2 人员岗位信息'!$B:$B,$D72) -> 0 | AR72: =AS72*AT72 -> 0 | AS72: =SUMIFS('1-2 人员岗位信息'!K:K,'1-2 人员岗位信息'!$C:$C,"劳务派遣",'1-2 人员岗位信息'!$B:$B,$D72) -> 0 | AU72: =AV72*AW72 -> 0 | AV72: =SUMIFS('1-2 人员岗位信息'!L:L,'1-2 人员岗位信息'!$C:$C,"劳务派遣",'1-2 人员岗位信息'!$B:$B,$D72) -> 0 | AX72: =AY72*AZ72 -> 0 | AY72: =SUMIFS('1-2 人员岗位信息'!M:M,'1-2 人员岗位信息'!$C:$C,"劳务派遣",'1-2 人员岗位信息'!$B:$B,$D72) -> 0 | BA72: =BB72*BC72 -> 0 | BB72: =SUMIFS('1-2 人员岗位信息'!N:N,'1-2 人员岗位信息'!$C:$C,"劳务派遣",'1-2 人员岗位信息'!$B:$B,$D72) -> 0 | BD72: =BE72*BF72 -> 0 | BE72: =SUMIFS('1-2 人员岗位信息'!O:O,'1-2 人员岗位信息'!$C:$C,"劳务派遣",'1-2 人员岗位信息'!$B:$B,$D72) -> 0 | BG72: =BH72*BI72 -> 0 | BH72: =SUMIFS('1-2 人员岗位信息'!P:P,'1-2 人员岗位信息'!$C:$C,"劳务派遣",'1-2 人员岗位信息'!$B:$B,$D72) -> 0 | BJ72: =BK72*BL72 -> 0 | BK72: =SUMIFS('1-2 人员岗位信息'!Q:Q,'1-2 人员岗位信息'!$C:$C,"劳务派遣",'1-2 人员岗位信息'!$B:$B,$D72) -> 0
B73: 是 | C73: 1.1.1.3.2.4 | D73: 园区保洁员工 | E73: 住宅或非住项目的园区保洁员工 | G73: 按月编制，汇总成年总量 | H73: =AB73 -> 0 | I73: 岗位数量 | J73: =SUM(AD73,AG73,AJ73,AM73,AP73,AS73,AV73,AY73,BB73,BE73,BH73,BK73)/N73 -> #DIV/0! | K73: 岗 | L73: =H73/N73/J73 -> #DIV/0! | M73: 元/㎡/月 | N73: =COUNTIF(AD73,">0")+COUNTIF(AG73,">0")+COUNTIF(AJ73,">0")+COUNTIF(AM73,">0")+COUNTIF(AP73,">0")+COUNTIF(AS73,">0")+COUNTIF(AV73,">0")+COUNTIF(AY73,">0")+COUNTIF(BB73,">0")+COUNTIF(BE73,">0")+COUNTIF(BH73,">0")+COUNTIF(BK73,">0") -> 0 | AB73: =SUM(AC73,AF73,AI73,AL73,AO73,AR73,AU73,AX73,BA73,BD73,BG73,BJ73) -> 0 | AC73: =AD73*AE73 -> 0 | AD73: =SUMIFS('1-2 人员岗位信息'!F:F,'1-2 人员岗位信息'!$C:$C,"劳务派遣",'1-2 人员岗位信息'!$B:$B,$D73) -> 0 | AF73: =AG73*AH73 -> 0 | AG73: =SUMIFS('1-2 人员岗位信息'!G:G,'1-2 人员岗位信息'!$C:$C,"劳务派遣",'1-2 人员岗位信息'!$B:$B,$D73) -> 0 | AI73: =AJ73*AK73 -> 0 | AJ73: =SUMIFS('1-2 人员岗位信息'!H:H,'1-2 人员岗位信息'!$C:$C,"劳务派遣",'1-2 人员岗位信息'!$B:$B,$D73) -> 0 | AL73: =AM73*AN73 -> 0 | AM73: =SUMIFS('1-2 人员岗位信息'!I:I,'1-2 人员岗位信息'!$C:$C,"劳务派遣",'1-2 人员岗位信息'!$B:$B,$D73) -> 0 | AO73: =AP73*AQ73 -> 0 | AP73: =SUMIFS('1-2 人员岗位信息'!J:J,'1-2 人员岗位信息'!$C:$C,"劳务派遣",'1-2 人员岗位信息'!$B:$B,$D73) -> 0 | AR73: =AS73*AT73 -> 0 | AS73: =SUMIFS('1-2 人员岗位信息'!K:K,'1-2 人员岗位信息'!$C:$C,"劳务派遣",'1-2 人员岗位信息'!$B:$B,$D73) -> 0 | AU73: =AV73*AW73 -> 0 | AV73: =SUMIFS('1-2 人员岗位信息'!L:L,'1-2 人员岗位信息'!$C:$C,"劳务派遣",'1-2 人员岗位信息'!$B:$B,$D73) -> 0 | AX73: =AY73*AZ73 -> 0 | AY73: =SUMIFS('1-2 人员岗位信息'!M:M,'1-2 人员岗位信息'!$C:$C,"劳务派遣",'1-2 人员岗位信息'!$B:$B,$D73) -> 0 | BA73: =BB73*BC73 -> 0 | BB73: =SUMIFS('1-2 人员岗位信息'!N:N,'1-2 人员岗位信息'!$C:$C,"劳务派遣",'1-2 人员岗位信息'!$B:$B,$D73) -> 0 | BD73: =BE73*BF73 -> 0 | BE73: =SUMIFS('1-2 人员岗位信息'!O:O,'1-2 人员岗位信息'!$C:$C,"劳务派遣",'1-2 人员岗位信息'!$B:$B,$D73) -> 0 | BG73: =BH73*BI73 -> 0 | BH73: =SUMIFS('1-2 人员岗位信息'!P:P,'1-2 人员岗位信息'!$C:$C,"劳务派遣",'1-2 人员岗位信息'!$B:$B,$D73) -> 0 | BJ73: =BK73*BL73 -> 0 | BK73: =SUMIFS('1-2 人员岗位信息'!Q:Q,'1-2 人员岗位信息'!$C:$C,"劳务派遣",'1-2 人员岗位信息'!$B:$B,$D73) -> 0
B74: 是 | C74: 1.1.1.3.2.5 | D74: 地库保洁员工 | E74: 住宅或非住项目的地库保洁员工 | G74: 按月编制，汇总成年总量 | H74: =AB74 -> 0 | I74: 岗位数量 | J74: =SUM(AD74,AG74,AJ74,AM74,AP74,AS74,AV74,AY74,BB74,BE74,BH74,BK74)/N74 -> #DIV/0! | K74: 岗 | L74: =H74/N74/J74 -> #DIV/0! | M74: 元/㎡/月 | N74: =COUNTIF(AD74,">0")+COUNTIF(AG74,">0")+COUNTIF(AJ74,">0")+COUNTIF(AM74,">0")+COUNTIF(AP74,">0")+COUNTIF(AS74,">0")+COUNTIF(AV74,">0")+COUNTIF(AY74,">0")+COUNTIF(BB74,">0")+COUNTIF(BE74,">0")+COUNTIF(BH74,">0")+COUNTIF(BK74,">0") -> 0 | AB74: =SUM(AC74,AF74,AI74,AL74,AO74,AR74,AU74,AX74,BA74,BD74,BG74,BJ74) -> 0 | AC74: =AD74*AE74 -> 0 | AD74: =SUMIFS('1-2 人员岗位信息'!F:F,'1-2 人员岗位信息'!$C:$C,"劳务派遣",'1-2 人员岗位信息'!$B:$B,$D74) -> 0 | AF74: =AG74*AH74 -> 0 | AG74: =SUMIFS('1-2 人员岗位信息'!G:G,'1-2 人员岗位信息'!$C:$C,"劳务派遣",'1-2 人员岗位信息'!$B:$B,$D74) -> 0 | AI74: =AJ74*AK74 -> 0 | AJ74: =SUMIFS('1-2 人员岗位信息'!H:H,'1-2 人员岗位信息'!$C:$C,"劳务派遣",'1-2 人员岗位信息'!$B:$B,$D74) -> 0 | AL74: =AM74*AN74 -> 0 | AM74: =SUMIFS('1-2 人员岗位信息'!I:I,'1-2 人员岗位信息'!$C:$C,"劳务派遣",'1-2 人员岗位信息'!$B:$B,$D74) -> 0 | AO74: =AP74*AQ74 -> 0 | AP74: =SUMIFS('1-2 人员岗位信息'!J:J,'1-2 人员岗位信息'!$C:$C,"劳务派遣",'1-2 人员岗位信息'!$B:$B,$D74) -> 0 | AR74: =AS74*AT74 -> 0 | AS74: =SUMIFS('1-2 人员岗位信息'!K:K,'1-2 人员岗位信息'!$C:$C,"劳务派遣",'1-2 人员岗位信息'!$B:$B,$D74) -> 0 | AU74: =AV74*AW74 -> 0 | AV74: =SUMIFS('1-2 人员岗位信息'!L:L,'1-2 人员岗位信息'!$C:$C,"劳务派遣",'1-2 人员岗位信息'!$B:$B,$D74) -> 0 | AX74: =AY74*AZ74 -> 0 | AY74: =SUMIFS('1-2 人员岗位信息'!M:M,'1-2 人员岗位信息'!$C:$C,"劳务派遣",'1-2 人员岗位信息'!$B:$B,$D74) -> 0 | BA74: =BB74*BC74 -> 0 | BB74: =SUMIFS('1-2 人员岗位信息'!N:N,'1-2 人员岗位信息'!$C:$C,"劳务派遣",'1-2 人员岗位信息'!$B:$B,$D74) -> 0 | BD74: =BE74*BF74 -> 0 | BE74: =SUMIFS('1-2 人员岗位信息'!O:O,'1-2 人员岗位信息'!$C:$C,"劳务派遣",'1-2 人员岗位信息'!$B:$B,$D74) -> 0 | BG74: =BH74*BI74 -> 0 | BH74: =SUMIFS('1-2 人员岗位信息'!P:P,'1-2 人员岗位信息'!$C:$C,"劳务派遣",'1-2 人员岗位信息'!$B:$B,$D74) -> 0 | BJ74: =BK74*BL74 -> 0 | BK74: =SUMIFS('1-2 人员岗位信息'!Q:Q,'1-2 人员岗位信息'!$C:$C,"劳务派遣",'1-2 人员岗位信息'!$B:$B,$D74) -> 0
B75: 是 | C75: 1.1.1.3.2.6 | D75: 外围保洁员工 | E75: 住宅或非住项目的园区外围保洁员工 | G75: 按月编制，汇总成年总量 | H75: =AB75 -> 0 | I75: 岗位数量 | J75: =SUM(AD75,AG75,AJ75,AM75,AP75,AS75,AV75,AY75,BB75,BE75,BH75,BK75)/N75 -> #DIV/0! | K75: 岗 | L75: =H75/N75/J75 -> #DIV/0! | M75: 元/㎡/月 | N75: =COUNTIF(AD75,">0")+COUNTIF(AG75,">0")+COUNTIF(AJ75,">0")+COUNTIF(AM75,">0")+COUNTIF(AP75,">0")+COUNTIF(AS75,">0")+COUNTIF(AV75,">0")+COUNTIF(AY75,">0")+COUNTIF(BB75,">0")+COUNTIF(BE75,">0")+COUNTIF(BH75,">0")+COUNTIF(BK75,">0") -> 0 | AB75: =SUM(AC75,AF75,AI75,AL75,AO75,AR75,AU75,AX75,BA75,BD75,BG75,BJ75) -> 0 | AC75: =AD75*AE75 -> 0 | AD75: =SUMIFS('1-2 人员岗位信息'!F:F,'1-2 人员岗位信息'!$C:$C,"劳务派遣",'1-2 人员岗位信息'!$B:$B,$D75) -> 0 | AF75: =AG75*AH75 -> 0 | AG75: =SUMIFS('1-2 人员岗位信息'!G:G,'1-2 人员岗位信息'!$C:$C,"劳务派遣",'1-2 人员岗位信息'!$B:$B,$D75) -> 0 | AI75: =AJ75*AK75 -> 0 | AJ75: =SUMIFS('1-2 人员岗位信息'!H:H,'1-2 人员岗位信息'!$C:$C,"劳务派遣",'1-2 人员岗位信息'!$B:$B,$D75) -> 0 | AL75: =AM75*AN75 -> 0 | AM75: =SUMIFS('1-2 人员岗位信息'!I:I,'1-2 人员岗位信息'!$C:$C,"劳务派遣",'1-2 人员岗位信息'!$B:$B,$D75) -> 0 | AO75: =AP75*AQ75 -> 0 | AP75: =SUMIFS('1-2 人员岗位信息'!J:J,'1-2 人员岗位信息'!$C:$C,"劳务派遣",'1-2 人员岗位信息'!$B:$B,$D75) -> 0 | AR75: =AS75*AT75 -> 0 | AS75: =SUMIFS('1-2 人员岗位信息'!K:K,'1-2 人员岗位信息'!$C:$C,"劳务派遣",'1-2 人员岗位信息'!$B:$B,$D75) -> 0 | AU75: =AV75*AW75 -> 0 | AV75: =SUMIFS('1-2 人员岗位信息'!L:L,'1-2 人员岗位信息'!$C:$C,"劳务派遣",'1-2 人员岗位信息'!$B:$B,$D75) -> 0 | AX75: =AY75*AZ75 -> 0 | AY75: =SUMIFS('1-2 人员岗位信息'!M:M,'1-2 人员岗位信息'!$C:$C,"劳务派遣",'1-2 人员岗位信息'!$B:$B,$D75) -> 0 | BA75: =BB75*BC75 -> 0 | BB75: =SUMIFS('1-2 人员岗位信息'!N:N,'1-2 人员岗位信息'!$C:$C,"劳务派遣",'1-2 人员岗位信息'!$B:$B,$D75) -> 0 | BD75: =BE75*BF75 -> 0 | BE75: =SUMIFS('1-2 人员岗位信息'!O:O,'1-2 人员岗位信息'!$C:$C,"劳务派遣",'1-2 人员岗位信息'!$B:$B,$D75) -> 0 | BG75: =BH75*BI75 -> 0 | BH75: =SUMIFS('1-2 人员岗位信息'!P:P,'1-2 人员岗位信息'!$C:$C,"劳务派遣",'1-2 人员岗位信息'!$B:$B,$D75) -> 0 | BJ75: =BK75*BL75 -> 0 | BK75: =SUMIFS('1-2 人员岗位信息'!Q:Q,'1-2 人员岗位信息'!$C:$C,"劳务派遣",'1-2 人员岗位信息'!$B:$B,$D75) -> 0
B76: 是 | C76: 1.1.1.3.2.7 | D76: 垃圾分拣员工 | E76: 住宅或非住项目需进行垃圾分类而设置的垃圾分拣专岗保洁员工 | G76: 按月编制，汇总成年总量 | H76: =AB76 -> 0 | I76: 岗位数量 | J76: =SUM(AD76,AG76,AJ76,AM76,AP76,AS76,AV76,AY76,BB76,BE76,BH76,BK76)/N76 -> #DIV/0! | K76: 岗 | L76: =H76/N76/J76 -> #DIV/0! | M76: 元/㎡/月 | N76: =COUNTIF(AD76,">0")+COUNTIF(AG76,">0")+COUNTIF(AJ76,">0")+COUNTIF(AM76,">0")+COUNTIF(AP76,">0")+COUNTIF(AS76,">0")+COUNTIF(AV76,">0")+COUNTIF(AY76,">0")+COUNTIF(BB76,">0")+COUNTIF(BE76,">0")+COUNTIF(BH76,">0")+COUNTIF(BK76,">0") -> 0 | AB76: =SUM(AC76,AF76,AI76,AL76,AO76,AR76,AU76,AX76,BA76,BD76,BG76,BJ76) -> 0 | AC76: =AD76*AE76 -> 0 | AD76: =SUMIFS('1-2 人员岗位信息'!F:F,'1-2 人员岗位信息'!$C:$C,"劳务派遣",'1-2 人员岗位信息'!$B:$B,$D76) -> 0 | AF76: =AG76*AH76 -> 0 | AG76: =SUMIFS('1-2 人员岗位信息'!G:G,'1-2 人员岗位信息'!$C:$C,"劳务派遣",'1-2 人员岗位信息'!$B:$B,$D76) -> 0 | AI76: =AJ76*AK76 -> 0 | AJ76: =SUMIFS('1-2 人员岗位信息'!H:H,'1-2 人员岗位信息'!$C:$C,"劳务派遣",'1-2 人员岗位信息'!$B:$B,$D76) -> 0 | AL76: =AM76*AN76 -> 0 | AM76: =SUMIFS('1-2 人员岗位信息'!I:I,'1-2 人员岗位信息'!$C:$C,"劳务派遣",'1-2 人员岗位信息'!$B:$B,$D76) -> 0 | AO76: =AP76*AQ76 -> 0 | AP76: =SUMIFS('1-2 人员岗位信息'!J:J,'1-2 人员岗位信息'!$C:$C,"劳务派遣",'1-2 人员岗位信息'!$B:$B,$D76) -> 0 | AR76: =AS76*AT76 -> 0 | AS76: =SUMIFS('1-2 人员岗位信息'!K:K,'1-2 人员岗位信息'!$C:$C,"劳务派遣",'1-2 人员岗位信息'!$B:$B,$D76) -> 0 | AU76: =AV76*AW76 -> 0 | AV76: =SUMIFS('1-2 人员岗位信息'!L:L,'1-2 人员岗位信息'!$C:$C,"劳务派遣",'1-2 人员岗位信息'!$B:$B,$D76) -> 0 | AX76: =AY76*AZ76 -> 0 | AY76: =SUMIFS('1-2 人员岗位信息'!M:M,'1-2 人员岗位信息'!$C:$C,"劳务派遣",'1-2 人员岗位信息'!$B:$B,$D76) -> 0 | BA76: =BB76*BC76 -> 0 | BB76: =SUMIFS('1-2 人员岗位信息'!N:N,'1-2 人员岗位信息'!$C:$C,"劳务派遣",'1-2 人员岗位信息'!$B:$B,$D76) -> 0 | BD76: =BE76*BF76 -> 0 | BE76: =SUMIFS('1-2 人员岗位信息'!O:O,'1-2 人员岗位信息'!$C:$C,"劳务派遣",'1-2 人员岗位信息'!$B:$B,$D76) -> 0 | BG76: =BH76*BI76 -> 0 | BH76: =SUMIFS('1-2 人员岗位信息'!P:P,'1-2 人员岗位信息'!$C:$C,"劳务派遣",'1-2 人员岗位信息'!$B:$B,$D76) -> 0 | BJ76: =BK76*BL76 -> 0 | BK76: =SUMIFS('1-2 人员岗位信息'!Q:Q,'1-2 人员岗位信息'!$C:$C,"劳务派遣",'1-2 人员岗位信息'!$B:$B,$D76) -> 0
B77: 是 | C77: 1.1.1.3.2.8 | D77: 道路清扫员工 | E77: 适用于城市服务项目道路清扫岗位员工 | G77: 按月编制，汇总成年总量 | H77: =AB77 -> 0 | I77: 岗位数量 | J77: =SUM(AD77,AG77,AJ77,AM77,AP77,AS77,AV77,AY77,BB77,BE77,BH77,BK77)/N77 -> #DIV/0! | K77: 岗 | L77: =H77/N77/J77 -> #DIV/0! | M77: 元/㎡/月 | N77: =COUNTIF(AD77,">0")+COUNTIF(AG77,">0")+COUNTIF(AJ77,">0")+COUNTIF(AM77,">0")+COUNTIF(AP77,">0")+COUNTIF(AS77,">0")+COUNTIF(AV77,">0")+COUNTIF(AY77,">0")+COUNTIF(BB77,">0")+COUNTIF(BE77,">0")+COUNTIF(BH77,">0")+COUNTIF(BK77,">0") -> 0 | AB77: =SUM(AC77,AF77,AI77,AL77,AO77,AR77,AU77,AX77,BA77,BD77,BG77,BJ77) -> 0 | AC77: =AD77*AE77 -> 0 | AD77: =SUMIFS('1-2 人员岗位信息'!F:F,'1-2 人员岗位信息'!$C:$C,"劳务派遣",'1-2 人员岗位信息'!$B:$B,$D77) -> 0 | AF77: =AG77*AH77 -> 0 | AG77: =SUMIFS('1-2 人员岗位信息'!G:G,'1-2 人员岗位信息'!$C:$C,"劳务派遣",'1-2 人员岗位信息'!$B:$B,$D77) -> 0 | AI77: =AJ77*AK77 -> 0 | AJ77: =SUMIFS('1-2 人员岗位信息'!H:H,'1-2 人员岗位信息'!$C:$C,"劳务派遣",'1-2 人员岗位信息'!$B:$B,$D77) -> 0 | AL77: =AM77*AN77 -> 0 | AM77: =SUMIFS('1-2 人员岗位信息'!I:I,'1-2 人员岗位信息'!$C:$C,"劳务派遣",'1-2 人员岗位信息'!$B:$B,$D77) -> 0 | AO77: =AP77*AQ77 -> 0 | AP77: =SUMIFS('1-2 人员岗位信息'!J:J,'1-2 人员岗位信息'!$C:$C,"劳务派遣",'1-2 人员岗位信息'!$B:$B,$D77) -> 0 | AR77: =AS77*AT77 -> 0 | AS77: =SUMIFS('1-2 人员岗位信息'!K:K,'1-2 人员岗位信息'!$C:$C,"劳务派遣",'1-2 人员岗位信息'!$B:$B,$D77) -> 0 | AU77: =AV77*AW77 -> 0 | AV77: =SUMIFS('1-2 人员岗位信息'!L:L,'1-2 人员岗位信息'!$C:$C,"劳务派遣",'1-2 人员岗位信息'!$B:$B,$D77) -> 0 | AX77: =AY77*AZ77 -> 0 | AY77: =SUMIFS('1-2 人员岗位信息'!M:M,'1-2 人员岗位信息'!$C:$C,"劳务派遣",'1-2 人员岗位信息'!$B:$B,$D77) -> 0 | BA77: =BB77*BC77 -> 0 | BB77: =SUMIFS('1-2 人员岗位信息'!N:N,'1-2 人员岗位信息'!$C:$C,"劳务派遣",'1-2 人员岗位信息'!$B:$B,$D77) -> 0 | BD77: =BE77*BF77 -> 0 | BE77: =SUMIFS('1-2 人员岗位信息'!O:O,'1-2 人员岗位信息'!$C:$C,"劳务派遣",'1-2 人员岗位信息'!$B:$B,$D77) -> 0 | BG77: =BH77*BI77 -> 0 | BH77: =SUMIFS('1-2 人员岗位信息'!P:P,'1-2 人员岗位信息'!$C:$C,"劳务派遣",'1-2 人员岗位信息'!$B:$B,$D77) -> 0 | BJ77: =BK77*BL77 -> 0 | BK77: =SUMIFS('1-2 人员岗位信息'!Q:Q,'1-2 人员岗位信息'!$C:$C,"劳务派遣",'1-2 人员岗位信息'!$B:$B,$D77) -> 0
B78: 是 | C78: 1.1.1.3.2.9 | D78: 卫生间保洁员工 | E78: 适用于写字楼、商业等非住业态的卫生间专岗 | G78: 按月编制，汇总成年总量 | H78: =AB78 -> 0 | I78: 岗位数量 | J78: =SUM(AD78,AG78,AJ78,AM78,AP78,AS78,AV78,AY78,BB78,BE78,BH78,BK78)/N78 -> #DIV/0! | K78: 岗 | L78: =H78/N78/J78 -> #DIV/0! | M78: 元/㎡/月 | N78: =COUNTIF(AD78,">0")+COUNTIF(AG78,">0")+COUNTIF(AJ78,">0")+COUNTIF(AM78,">0")+COUNTIF(AP78,">0")+COUNTIF(AS78,">0")+COUNTIF(AV78,">0")+COUNTIF(AY78,">0")+COUNTIF(BB78,">0")+COUNTIF(BE78,">0")+COUNTIF(BH78,">0")+COUNTIF(BK78,">0") -> 0 | AB78: =SUM(AC78,AF78,AI78,AL78,AO78,AR78,AU78,AX78,BA78,BD78,BG78,BJ78) -> 0 | AC78: =AD78*AE78 -> 0 | AD78: =SUMIFS('1-2 人员岗位信息'!F:F,'1-2 人员岗位信息'!$C:$C,"劳务派遣",'1-2 人员岗位信息'!$B:$B,$D78) -> 0 | AF78: =AG78*AH78 -> 0 | AG78: =SUMIFS('1-2 人员岗位信息'!G:G,'1-2 人员岗位信息'!$C:$C,"劳务派遣",'1-2 人员岗位信息'!$B:$B,$D78) -> 0 | AI78: =AJ78*AK78 -> 0 | AJ78: =SUMIFS('1-2 人员岗位信息'!H:H,'1-2 人员岗位信息'!$C:$C,"劳务派遣",'1-2 人员岗位信息'!$B:$B,$D78) -> 0 | AL78: =AM78*AN78 -> 0 | AM78: =SUMIFS('1-2 人员岗位信息'!I:I,'1-2 人员岗位信息'!$C:$C,"劳务派遣",'1-2 人员岗位信息'!$B:$B,$D78) -> 0 | AO78: =AP78*AQ78 -> 0 | AP78: =SUMIFS('1-2 人员岗位信息'!J:J,'1-2 人员岗位信息'!$C:$C,"劳务派遣",'1-2 人员岗位信息'!$B:$B,$D78) -> 0 | AR78: =AS78*AT78 -> 0 | AS78: =SUMIFS('1-2 人员岗位信息'!K:K,'1-2 人员岗位信息'!$C:$C,"劳务派遣",'1-2 人员岗位信息'!$B:$B,$D78) -> 0 | AU78: =AV78*AW78 -> 0 | AV78: =SUMIFS('1-2 人员岗位信息'!L:L,'1-2 人员岗位信息'!$C:$C,"劳务派遣",'1-2 人员岗位信息'!$B:$B,$D78) -> 0 | AX78: =AY78*AZ78 -> 0 | AY78: =SUMIFS('1-2 人员岗位信息'!M:M,'1-2 人员岗位信息'!$C:$C,"劳务派遣",'1-2 人员岗位信息'!$B:$B,$D78) -> 0 | BA78: =BB78*BC78 -> 0 | BB78: =SUMIFS('1-2 人员岗位信息'!N:N,'1-2 人员岗位信息'!$C:$C,"劳务派遣",'1-2 人员岗位信息'!$B:$B,$D78) -> 0 | BD78: =BE78*BF78 -> 0 | BE78: =SUMIFS('1-2 人员岗位信息'!O:O,'1-2 人员岗位信息'!$C:$C,"劳务派遣",'1-2 人员岗位信息'!$B:$B,$D78) -> 0 | BG78: =BH78*BI78 -> 0 | BH78: =SUMIFS('1-2 人员岗位信息'!P:P,'1-2 人员岗位信息'!$C:$C,"劳务派遣",'1-2 人员岗位信息'!$B:$B,$D78) -> 0 | BJ78: =BK78*BL78 -> 0 | BK78: =SUMIFS('1-2 人员岗位信息'!Q:Q,'1-2 人员岗位信息'!$C:$C,"劳务派遣",'1-2 人员岗位信息'!$B:$B,$D78) -> 0
B79: 是 | C79: 1.1.1.3.2.10 | D79: 其他保洁员工 | E79: 上述不包含的保洁岗位可适用此项 | G79: 按月编制，汇总成年总量 | H79: =AB79 -> 0 | I79: 岗位数量 | J79: =SUM(AD79,AG79,AJ79,AM79,AP79,AS79,AV79,AY79,BB79,BE79,BH79,BK79)/N79 -> #DIV/0! | K79: 岗 | L79: =H79/N79/J79 -> #DIV/0! | M79: 元/㎡/月 | N79: =COUNTIF(AD79,">0")+COUNTIF(AG79,">0")+COUNTIF(AJ79,">0")+COUNTIF(AM79,">0")+COUNTIF(AP79,">0")+COUNTIF(AS79,">0")+COUNTIF(AV79,">0")+COUNTIF(AY79,">0")+COUNTIF(BB79,">0")+COUNTIF(BE79,">0")+COUNTIF(BH79,">0")+COUNTIF(BK79,">0") -> 0 | AB79: =SUM(AC79,AF79,AI79,AL79,AO79,AR79,AU79,AX79,BA79,BD79,BG79,BJ79) -> 0 | AC79: =AD79*AE79 -> 0 | AD79: =SUMIFS('1-2 人员岗位信息'!F:F,'1-2 人员岗位信息'!$C:$C,"劳务派遣",'1-2 人员岗位信息'!$B:$B,$D79) -> 0 | AF79: =AG79*AH79 -> 0 | AG79: =SUMIFS('1-2 人员岗位信息'!G:G,'1-2 人员岗位信息'!$C:$C,"劳务派遣",'1-2 人员岗位信息'!$B:$B,$D79) -> 0 | AI79: =AJ79*AK79 -> 0 | AJ79: =SUMIFS('1-2 人员岗位信息'!H:H,'1-2 人员岗位信息'!$C:$C,"劳务派遣",'1-2 人员岗位信息'!$B:$B,$D79) -> 0 | AL79: =AM79*AN79 -> 0 | AM79: =SUMIFS('1-2 人员岗位信息'!I:I,'1-2 人员岗位信息'!$C:$C,"劳务派遣",'1-2 人员岗位信息'!$B:$B,$D79) -> 0 | AO79: =AP79*AQ79 -> 0 | AP79: =SUMIFS('1-2 人员岗位信息'!J:J,'1-2 人员岗位信息'!$C:$C,"劳务派遣",'1-2 人员岗位信息'!$B:$B,$D79) -> 0 | AR79: =AS79*AT79 -> 0 | AS79: =SUMIFS('1-2 人员岗位信息'!K:K,'1-2 人员岗位信息'!$C:$C,"劳务派遣",'1-2 人员岗位信息'!$B:$B,$D79) -> 0 | AU79: =AV79*AW79 -> 0 | AV79: =SUMIFS('1-2 人员岗位信息'!L:L,'1-2 人员岗位信息'!$C:$C,"劳务派遣",'1-2 人员岗位信息'!$B:$B,$D79) -> 0 | AX79: =AY79*AZ79 -> 0 | AY79: =SUMIFS('1-2 人员岗位信息'!M:M,'1-2 人员岗位信息'!$C:$C,"劳务派遣",'1-2 人员岗位信息'!$B:$B,$D79) -> 0 | BA79: =BB79*BC79 -> 0 | BB79: =SUMIFS('1-2 人员岗位信息'!N:N,'1-2 人员岗位信息'!$C:$C,"劳务派遣",'1-2 人员岗位信息'!$B:$B,$D79) -> 0 | BD79: =BE79*BF79 -> 0 | BE79: =SUMIFS('1-2 人员岗位信息'!O:O,'1-2 人员岗位信息'!$C:$C,"劳务派遣",'1-2 人员岗位信息'!$B:$B,$D79) -> 0 | BG79: =BH79*BI79 -> 0 | BH79: =SUMIFS('1-2 人员岗位信息'!P:P,'1-2 人员岗位信息'!$C:$C,"劳务派遣",'1-2 人员岗位信息'!$B:$B,$D79) -> 0 | BJ79: =BK79*BL79 -> 0 | BK79: =SUMIFS('1-2 人员岗位信息'!Q:Q,'1-2 人员岗位信息'!$C:$C,"劳务派遣",'1-2 人员岗位信息'!$B:$B,$D79) -> 0
B80: 否 | C80: 1.1.1.3.3 | D80: 专业外包（人员） | H80: =SUM(H81:H90) -> 1255991.3 | AB80: =SUM(AB81:AB90) -> 1255991.3 | AC80: =SUM(AC81:AC90) -> 104665.94 | AF80: =SUM(AF81:AF90) -> 104665.94 | AI80: =SUM(AI81:AI90) -> 104665.94 | AL80: =SUM(AL81:AL90) -> 104665.94 | AO80: =SUM(AO81:AO90) -> 104665.94 | AR80: =SUM(AR81:AR90) -> 104665.94 | AU80: =SUM(AU81:AU90) -> 104665.94 | AX80: =SUM(AX81:AX90) -> 104665.94 | BA80: =SUM(BA81:BA90) -> 104665.94 | BD80: =SUM(BD81:BD90) -> 104665.94 | BG80: =SUM(BG81:BG90) -> 104665.94 | BJ80: =SUM(BJ81:BJ90) -> 104665.94
B81: 是 | C81: 1.1.1.3.3.1 | D81: 保洁经理 | E81: 指外包保洁经理 | G81: 按月编制，汇总成年总量 | H81: =AB81 -> 1255991.3 | I81: 岗位数量 | J81: =SUM(AD81,AG81,AJ81,AM81,AP81,AS81,AV81,AY81,BB81,BE81,BH81,BK81)/N81 -> 24 | K81: 岗 | L81: =H81/N81/J81 -> 4361.081 | M81: 元/㎡/月 | N81: =COUNTIF(AD81,">0")+COUNTIF(AG81,">0")+COUNTIF(AJ81,">0")+COUNTIF(AM81,">0")+COUNTIF(AP81,">0")+COUNTIF(AS81,">0")+COUNTIF(AV81,">0")+COUNTIF(AY81,">0")+COUNTIF(BB81,">0")+COUNTIF(BE81,">0")+COUNTIF(BH81,">0")+COUNTIF(BK81,">0") -> 12 | AB81: =SUM(AC81,AF81,AI81,AL81,AO81,AR81,AU81,AX81,BA81,BD81,BG81,BJ81) -> 1255991.3 | AC81: =AD81*AE81 -> 104665.94 | AD81: =SUMIFS('1-2 人员岗位信息'!J:J,'1-2 人员岗位信息'!$C:$C,"专业外包",'1-2 人员岗位信息'!$B:$B,$D81) -> 24 | AE81: =预算主表!P79/(12*AD81) -> 4361.081 | AF81: =AG81*AH81 -> 104665.94 | AG81: =SUMIFS('1-2 人员岗位信息'!J:J,'1-2 人员岗位信息'!$C:$C,"专业外包",'1-2 人员岗位信息'!$B:$B,$D81) -> 24 | AH81: =AE81 -> 4361.081 | AI81: =AJ81*AK81 -> 104665.94 | AJ81: =SUMIFS('1-2 人员岗位信息'!J:J,'1-2 人员岗位信息'!$C:$C,"专业外包",'1-2 人员岗位信息'!$B:$B,$D81) -> 24 | AK81: =AE81 -> 4361.081 | AL81: =AM81*AN81 -> 104665.94 | AM81: =SUMIFS('1-2 人员岗位信息'!I:I,'1-2 人员岗位信息'!$C:$C,"专业外包",'1-2 人员岗位信息'!$B:$B,$D81) -> 24 | AN81: =AE81 -> 4361.081 | AO81: =AP81*AQ81 -> 104665.94 | AP81: =SUMIFS('1-2 人员岗位信息'!J:J,'1-2 人员岗位信息'!$C:$C,"专业外包",'1-2 人员岗位信息'!$B:$B,$D81) -> 24 | AQ81: =AE81 -> 4361.081 | AR81: =AS81*AT81 -> 104665.94 | AS81: =SUMIFS('1-2 人员岗位信息'!K:K,'1-2 人员岗位信息'!$C:$C,"专业外包",'1-2 人员岗位信息'!$B:$B,$D81) -> 24 | AT81: =AE81 -> 4361.081 | AU81: =AV81*AW81 -> 104665.94 | AV81: =SUMIFS('1-2 人员岗位信息'!L:L,'1-2 人员岗位信息'!$C:$C,"专业外包",'1-2 人员岗位信息'!$B:$B,$D81) -> 24 | AW81: =AE81 -> 4361.081 | AX81: =AY81*AZ81 -> 104665.94 | AY81: =SUMIFS('1-2 人员岗位信息'!M:M,'1-2 人员岗位信息'!$C:$C,"专业外包",'1-2 人员岗位信息'!$B:$B,$D81) -> 24 | AZ81: =AE81 -> 4361.081 | BA81: =BB81*BC81 -> 104665.94 | BB81: =SUMIFS('1-2 人员岗位信息'!N:N,'1-2 人员岗位信息'!$C:$C,"专业外包",'1-2 人员岗位信息'!$B:$B,$D81) -> 24 | BC81: =AE81 -> 4361.081 | BD81: =BE81*BF81 -> 104665.94 | BE81: =SUMIFS('1-2 人员岗位信息'!O:O,'1-2 人员岗位信息'!$C:$C,"专业外包",'1-2 人员岗位信息'!$B:$B,$D81) -> 24 | BF81: =AE81 -> 4361.081 | BG81: =BH81*BI81 -> 104665.94 | BH81: =SUMIFS('1-2 人员岗位信息'!P:P,'1-2 人员岗位信息'!$C:$C,"专业外包",'1-2 人员岗位信息'!$B:$B,$D81) -> 24 | BI81: =AE81 -> 4361.081 | BJ81: =BK81*BL81 -> 104665.94 | BK81: =SUMIFS('1-2 人员岗位信息'!Q:Q,'1-2 人员岗位信息'!$C:$C,"专业外包",'1-2 人员岗位信息'!$B:$B,$D81) -> 24 | BL81: =AE81 -> 4361.081
B82: 是 | C82: 1.1.1.3.3.2 | D82: 保洁主管 | E82: 指外包保洁主管 | G82: 按月编制，汇总成年总量 | H82: =AB82 -> 0 | I82: 岗位数量 | J82: =SUM(AD82,AG82,AJ82,AM82,AP82,AS82,AV82,AY82,BB82,BE82,BH82,BK82)/N82 -> #DIV/0! | K82: 岗 | L82: =H82/N82/J82 -> #DIV/0! | M82: 元/㎡/月 | N82: =COUNTIF(AD82,">0")+COUNTIF(AG82,">0")+COUNTIF(AJ82,">0")+COUNTIF(AM82,">0")+COUNTIF(AP82,">0")+COUNTIF(AS82,">0")+COUNTIF(AV82,">0")+COUNTIF(AY82,">0")+COUNTIF(BB82,">0")+COUNTIF(BE82,">0")+COUNTIF(BH82,">0")+COUNTIF(BK82,">0") -> 0 | AB82: =SUM(AC82,AF82,AI82,AL82,AO82,AR82,AU82,AX82,BA82,BD82,BG82,BJ82) -> 0 | AC82: =AD82*AE82 -> 0 | AD82: =SUMIFS('1-2 人员岗位信息'!F:F,'1-2 人员岗位信息'!$C:$C,"专业外包",'1-2 人员岗位信息'!$B:$B,$D82) -> 0 | AF82: =AG82*AH82 -> 0 | AG82: =SUMIFS('1-2 人员岗位信息'!G:G,'1-2 人员岗位信息'!$C:$C,"专业外包",'1-2 人员岗位信息'!$B:$B,$D82) -> 0 | AI82: =AJ82*AK82 -> 0 | AJ82: =SUMIFS('1-2 人员岗位信息'!H:H,'1-2 人员岗位信息'!$C:$C,"专业外包",'1-2 人员岗位信息'!$B:$B,$D82) -> 0 | AL82: =AM82*AN82 -> 0 | AM82: =SUMIFS('1-2 人员岗位信息'!I:I,'1-2 人员岗位信息'!$C:$C,"专业外包",'1-2 人员岗位信息'!$B:$B,$D82) -> 0 | AO82: =AP82*AQ82 -> 0 | AP82: =SUMIFS('1-2 人员岗位信息'!J:J,'1-2 人员岗位信息'!$C:$C,"专业外包",'1-2 人员岗位信息'!$B:$B,$D82) -> 0 | AR82: =AS82*AT82 -> 0 | AS82: =SUMIFS('1-2 人员岗位信息'!K:K,'1-2 人员岗位信息'!$C:$C,"专业外包",'1-2 人员岗位信息'!$B:$B,$D82) -> 0 | AU82: =AV82*AW82 -> 0 | AV82: =SUMIFS('1-2 人员岗位信息'!L:L,'1-2 人员岗位信息'!$C:$C,"专业外包",'1-2 人员岗位信息'!$B:$B,$D82) -> 0 | AX82: =AY82*AZ82 -> 0 | AY82: =SUMIFS('1-2 人员岗位信息'!M:M,'1-2 人员岗位信息'!$C:$C,"专业外包",'1-2 人员岗位信息'!$B:$B,$D82) -> 0 | BA82: =BB82*BC82 -> 0 | BB82: =SUMIFS('1-2 人员岗位信息'!N:N,'1-2 人员岗位信息'!$C:$C,"专业外包",'1-2 人员岗位信息'!$B:$B,$D82) -> 0 | BD82: =BE82*BF82 -> 0 | BE82: =SUMIFS('1-2 人员岗位信息'!O:O,'1-2 人员岗位信息'!$C:$C,"专业外包",'1-2 人员岗位信息'!$B:$B,$D82) -> 0 | BG82: =BH82*BI82 -> 0 | BH82: =SUMIFS('1-2 人员岗位信息'!P:P,'1-2 人员岗位信息'!$C:$C,"专业外包",'1-2 人员岗位信息'!$B:$B,$D82) -> 0 | BJ82: =BK82*BL82 -> 0 | BK82: =SUMIFS('1-2 人员岗位信息'!Q:Q,'1-2 人员岗位信息'!$C:$C,"专业外包",'1-2 人员岗位信息'!$B:$B,$D82) -> 0
B83: 是 | C83: 1.1.1.3.3.3 | D83: 楼内保洁员工 | E83: 住宅或非住项目的楼内公共区域保洁员工 | G83: 按月编制，汇总成年总量 | H83: =AB83 -> 0 | I83: 岗位数量 | J83: =SUM(AD83,AG83,AJ83,AM83,AP83,AS83,AV83,AY83,BB83,BE83,BH83,BK83)/N83 -> #DIV/0! | K83: 岗 | L83: =H83/N83/J83 -> #DIV/0! | M83: 元/㎡/月 | N83: =COUNTIF(AD83,">0")+COUNTIF(AG83,">0")+COUNTIF(AJ83,">0")+COUNTIF(AM83,">0")+COUNTIF(AP83,">0")+COUNTIF(AS83,">0")+COUNTIF(AV83,">0")+COUNTIF(AY83,">0")+COUNTIF(BB83,">0")+COUNTIF(BE83,">0")+COUNTIF(BH83,">0")+COUNTIF(BK83,">0") -> 0 | AB83: =SUM(AC83,AF83,AI83,AL83,AO83,AR83,AU83,AX83,BA83,BD83,BG83,BJ83) -> 0 | AC83: =AD83*AE83 -> 0 | AD83: =SUMIFS('1-2 人员岗位信息'!F:F,'1-2 人员岗位信息'!$C:$C,"专业外包",'1-2 人员岗位信息'!$B:$B,$D83) -> 0 | AF83: =AG83*AH83 -> 0 | AG83: =SUMIFS('1-2 人员岗位信息'!G:G,'1-2 人员岗位信息'!$C:$C,"专业外包",'1-2 人员岗位信息'!$B:$B,$D83) -> 0 | AI83: =AJ83*AK83 -> 0 | AJ83: =SUMIFS('1-2 人员岗位信息'!H:H,'1-2 人员岗位信息'!$C:$C,"专业外包",'1-2 人员岗位信息'!$B:$B,$D83) -> 0 | AL83: =AM83*AN83 -> 0 | AM83: =SUMIFS('1-2 人员岗位信息'!I:I,'1-2 人员岗位信息'!$C:$C,"专业外包",'1-2 人员岗位信息'!$B:$B,$D83) -> 0 | AO83: =AP83*AQ83 -> 0 | AP83: =SUMIFS('1-2 人员岗位信息'!J:J,'1-2 人员岗位信息'!$C:$C,"专业外包",'1-2 人员岗位信息'!$B:$B,$D83) -> 0 | AR83: =AS83*AT83 -> 0 | AS83: =SUMIFS('1-2 人员岗位信息'!K:K,'1-2 人员岗位信息'!$C:$C,"专业外包",'1-2 人员岗位信息'!$B:$B,$D83) -> 0 | AU83: =AV83*AW83 -> 0 | AV83: =SUMIFS('1-2 人员岗位信息'!L:L,'1-2 人员岗位信息'!$C:$C,"专业外包",'1-2 人员岗位信息'!$B:$B,$D83) -> 0 | AX83: =AY83*AZ83 -> 0 | AY83: =SUMIFS('1-2 人员岗位信息'!M:M,'1-2 人员岗位信息'!$C:$C,"专业外包",'1-2 人员岗位信息'!$B:$B,$D83) -> 0 | BA83: =BB83*BC83 -> 0 | BB83: =SUMIFS('1-2 人员岗位信息'!N:N,'1-2 人员岗位信息'!$C:$C,"专业外包",'1-2 人员岗位信息'!$B:$B,$D83) -> 0 | BD83: =BE83*BF83 -> 0 | BE83: =SUMIFS('1-2 人员岗位信息'!O:O,'1-2 人员岗位信息'!$C:$C,"专业外包",'1-2 人员岗位信息'!$B:$B,$D83) -> 0 | BG83: =BH83*BI83 -> 0 | BH83: =SUMIFS('1-2 人员岗位信息'!P:P,'1-2 人员岗位信息'!$C:$C,"专业外包",'1-2 人员岗位信息'!$B:$B,$D83) -> 0 | BJ83: =BK83*BL83 -> 0 | BK83: =SUMIFS('1-2 人员岗位信息'!Q:Q,'1-2 人员岗位信息'!$C:$C,"专业外包",'1-2 人员岗位信息'!$B:$B,$D83) -> 0
B84: 是 | C84: 1.1.1.3.3.4 | D84: 园区保洁员工 | E84: 住宅或非住项目的园区保洁员工 | G84: 按月编制，汇总成年总量 | H84: =AB84 -> 0 | I84: 岗位数量 | J84: =SUM(AD84,AG84,AJ84,AM84,AP84,AS84,AV84,AY84,BB84,BE84,BH84,BK84)/N84 -> #DIV/0! | K84: 岗 | L84: =H84/N84/J84 -> #DIV/0! | M84: 元/㎡/月 | N84: =COUNTIF(AD84,">0")+COUNTIF(AG84,">0")+COUNTIF(AJ84,">0")+COUNTIF(AM84,">0")+COUNTIF(AP84,">0")+COUNTIF(AS84,">0")+COUNTIF(AV84,">0")+COUNTIF(AY84,">0")+COUNTIF(BB84,">0")+COUNTIF(BE84,">0")+COUNTIF(BH84,">0")+COUNTIF(BK84,">0") -> 0 | AB84: =SUM(AC84,AF84,AI84,AL84,AO84,AR84,AU84,AX84,BA84,BD84,BG84,BJ84) -> 0 | AC84: =AD84*AE84 -> 0 | AD84: =SUMIFS('1-2 人员岗位信息'!F:F,'1-2 人员岗位信息'!$C:$C,"专业外包",'1-2 人员岗位信息'!$B:$B,$D84) -> 0 | AF84: =AG84*AH84 -> 0 | AG84: =SUMIFS('1-2 人员岗位信息'!G:G,'1-2 人员岗位信息'!$C:$C,"专业外包",'1-2 人员岗位信息'!$B:$B,$D84) -> 0 | AI84: =AJ84*AK84 -> 0 | AJ84: =SUMIFS('1-2 人员岗位信息'!H:H,'1-2 人员岗位信息'!$C:$C,"专业外包",'1-2 人员岗位信息'!$B:$B,$D84) -> 0 | AL84: =AM84*AN84 -> 0 | AM84: =SUMIFS('1-2 人员岗位信息'!I:I,'1-2 人员岗位信息'!$C:$C,"专业外包",'1-2 人员岗位信息'!$B:$B,$D84) -> 0 | AO84: =AP84*AQ84 -> 0 | AP84: =SUMIFS('1-2 人员岗位信息'!J:J,'1-2 人员岗位信息'!$C:$C,"专业外包",'1-2 人员岗位信息'!$B:$B,$D84) -> 0 | AR84: =AS84*AT84 -> 0 | AS84: =SUMIFS('1-2 人员岗位信息'!K:K,'1-2 人员岗位信息'!$C:$C,"专业外包",'1-2 人员岗位信息'!$B:$B,$D84) -> 0 | AU84: =AV84*AW84 -> 0 | AV84: =SUMIFS('1-2 人员岗位信息'!L:L,'1-2 人员岗位信息'!$C:$C,"专业外包",'1-2 人员岗位信息'!$B:$B,$D84) -> 0 | AX84: =AY84*AZ84 -> 0 | AY84: =SUMIFS('1-2 人员岗位信息'!M:M,'1-2 人员岗位信息'!$C:$C,"专业外包",'1-2 人员岗位信息'!$B:$B,$D84) -> 0 | BA84: =BB84*BC84 -> 0 | BB84: =SUMIFS('1-2 人员岗位信息'!N:N,'1-2 人员岗位信息'!$C:$C,"专业外包",'1-2 人员岗位信息'!$B:$B,$D84) -> 0 | BD84: =BE84*BF84 -> 0 | BE84: =SUMIFS('1-2 人员岗位信息'!O:O,'1-2 人员岗位信息'!$C:$C,"专业外包",'1-2 人员岗位信息'!$B:$B,$D84) -> 0 | BG84: =BH84*BI84 -> 0 | BH84: =SUMIFS('1-2 人员岗位信息'!P:P,'1-2 人员岗位信息'!$C:$C,"专业外包",'1-2 人员岗位信息'!$B:$B,$D84) -> 0 | BJ84: =BK84*BL84 -> 0 | BK84: =SUMIFS('1-2 人员岗位信息'!Q:Q,'1-2 人员岗位信息'!$C:$C,"专业外包",'1-2 人员岗位信息'!$B:$B,$D84) -> 0
B85: 是 | C85: 1.1.1.3.3.5 | D85: 地库保洁员工 | E85: 住宅或非住项目的地库保洁员工 | G85: 按月编制，汇总成年总量 | H85: =AB85 -> 0 | I85: 岗位数量 | J85: =SUM(AD85,AG85,AJ85,AM85,AP85,AS85,AV85,AY85,BB85,BE85,BH85,BK85)/N85 -> #DIV/0! | K85: 岗 | L85: =H85/N85/J85 -> #DIV/0! | M85: 元/㎡/月 | N85: =COUNTIF(AD85,">0")+COUNTIF(AG85,">0")+COUNTIF(AJ85,">0")+COUNTIF(AM85,">0")+COUNTIF(AP85,">0")+COUNTIF(AS85,">0")+COUNTIF(AV85,">0")+COUNTIF(AY85,">0")+COUNTIF(BB85,">0")+COUNTIF(BE85,">0")+COUNTIF(BH85,">0")+COUNTIF(BK85,">0") -> 0 | AB85: =SUM(AC85,AF85,AI85,AL85,AO85,AR85,AU85,AX85,BA85,BD85,BG85,BJ85) -> 0 | AC85: =AD85*AE85 -> 0 | AD85: =SUMIFS('1-2 人员岗位信息'!F:F,'1-2 人员岗位信息'!$C:$C,"专业外包",'1-2 人员岗位信息'!$B:$B,$D85) -> 0 | AF85: =AG85*AH85 -> 0 | AG85: =SUMIFS('1-2 人员岗位信息'!G:G,'1-2 人员岗位信息'!$C:$C,"专业外包",'1-2 人员岗位信息'!$B:$B,$D85) -> 0 | AI85: =AJ85*AK85 -> 0 | AJ85: =SUMIFS('1-2 人员岗位信息'!H:H,'1-2 人员岗位信息'!$C:$C,"专业外包",'1-2 人员岗位信息'!$B:$B,$D85) -> 0 | AL85: =AM85*AN85 -> 0 | AM85: =SUMIFS('1-2 人员岗位信息'!I:I,'1-2 人员岗位信息'!$C:$C,"专业外包",'1-2 人员岗位信息'!$B:$B,$D85) -> 0 | AO85: =AP85*AQ85 -> 0 | AP85: =SUMIFS('1-2 人员岗位信息'!J:J,'1-2 人员岗位信息'!$C:$C,"专业外包",'1-2 人员岗位信息'!$B:$B,$D85) -> 0 | AR85: =AS85*AT85 -> 0 | AS85: =SUMIFS('1-2 人员岗位信息'!K:K,'1-2 人员岗位信息'!$C:$C,"专业外包",'1-2 人员岗位信息'!$B:$B,$D85) -> 0 | AU85: =AV85*AW85 -> 0 | AV85: =SUMIFS('1-2 人员岗位信息'!L:L,'1-2 人员岗位信息'!$C:$C,"专业外包",'1-2 人员岗位信息'!$B:$B,$D85) -> 0 | AX85: =AY85*AZ85 -> 0 | AY85: =SUMIFS('1-2 人员岗位信息'!M:M,'1-2 人员岗位信息'!$C:$C,"专业外包",'1-2 人员岗位信息'!$B:$B,$D85) -> 0 | BA85: =BB85*BC85 -> 0 | BB85: =SUMIFS('1-2 人员岗位信息'!N:N,'1-2 人员岗位信息'!$C:$C,"专业外包",'1-2 人员岗位信息'!$B:$B,$D85) -> 0 | BD85: =BE85*BF85 -> 0 | BE85: =SUMIFS('1-2 人员岗位信息'!O:O,'1-2 人员岗位信息'!$C:$C,"专业外包",'1-2 人员岗位信息'!$B:$B,$D85) -> 0 | BG85: =BH85*BI85 -> 0 | BH85: =SUMIFS('1-2 人员岗位信息'!P:P,'1-2 人员岗位信息'!$C:$C,"专业外包",'1-2 人员岗位信息'!$B:$B,$D85) -> 0 | BJ85: =BK85*BL85 -> 0 | BK85: =SUMIFS('1-2 人员岗位信息'!Q:Q,'1-2 人员岗位信息'!$C:$C,"专业外包",'1-2 人员岗位信息'!$B:$B,$D85) -> 0
B86: 是 | C86: 1.1.1.3.3.6 | D86: 外围保洁员工 | E86: 住宅或非住项目的园区外围保洁员工 | G86: 按月编制，汇总成年总量 | H86: =AB86 -> 0 | I86: 岗位数量 | J86: =SUM(AD86,AG86,AJ86,AM86,AP86,AS86,AV86,AY86,BB86,BE86,BH86,BK86)/N86 -> #DIV/0! | K86: 岗 | L86: =H86/N86/J86 -> #DIV/0! | M86: 元/㎡/月 | N86: =COUNTIF(AD86,">0")+COUNTIF(AG86,">0")+COUNTIF(AJ86,">0")+COUNTIF(AM86,">0")+COUNTIF(AP86,">0")+COUNTIF(AS86,">0")+COUNTIF(AV86,">0")+COUNTIF(AY86,">0")+COUNTIF(BB86,">0")+COUNTIF(BE86,">0")+COUNTIF(BH86,">0")+COUNTIF(BK86,">0") -> 0 | AB86: =SUM(AC86,AF86,AI86,AL86,AO86,AR86,AU86,AX86,BA86,BD86,BG86,BJ86) -> 0 | AC86: =AD86*AE86 -> 0 | AD86: =SUMIFS('1-2 人员岗位信息'!F:F,'1-2 人员岗位信息'!$C:$C,"专业外包",'1-2 人员岗位信息'!$B:$B,$D86) -> 0 | AF86: =AG86*AH86 -> 0 | AG86: =SUMIFS('1-2 人员岗位信息'!G:G,'1-2 人员岗位信息'!$C:$C,"专业外包",'1-2 人员岗位信息'!$B:$B,$D86) -> 0 | AI86: =AJ86*AK86 -> 0 | AJ86: =SUMIFS('1-2 人员岗位信息'!H:H,'1-2 人员岗位信息'!$C:$C,"专业外包",'1-2 人员岗位信息'!$B:$B,$D86) -> 0 | AL86: =AM86*AN86 -> 0 | AM86: =SUMIFS('1-2 人员岗位信息'!I:I,'1-2 人员岗位信息'!$C:$C,"专业外包",'1-2 人员岗位信息'!$B:$B,$D86) -> 0 | AO86: =AP86*AQ86 -> 0 | AP86: =SUMIFS('1-2 人员岗位信息'!J:J,'1-2 人员岗位信息'!$C:$C,"专业外包",'1-2 人员岗位信息'!$B:$B,$D86) -> 0 | AR86: =AS86*AT86 -> 0 | AS86: =SUMIFS('1-2 人员岗位信息'!K:K,'1-2 人员岗位信息'!$C:$C,"专业外包",'1-2 人员岗位信息'!$B:$B,$D86) -> 0 | AU86: =AV86*AW86 -> 0 | AV86: =SUMIFS('1-2 人员岗位信息'!L:L,'1-2 人员岗位信息'!$C:$C,"专业外包",'1-2 人员岗位信息'!$B:$B,$D86) -> 0 | AX86: =AY86*AZ86 -> 0 | AY86: =SUMIFS('1-2 人员岗位信息'!M:M,'1-2 人员岗位信息'!$C:$C,"专业外包",'1-2 人员岗位信息'!$B:$B,$D86) -> 0 | BA86: =BB86*BC86 -> 0 | BB86: =SUMIFS('1-2 人员岗位信息'!N:N,'1-2 人员岗位信息'!$C:$C,"专业外包",'1-2 人员岗位信息'!$B:$B,$D86) -> 0 | BD86: =BE86*BF86 -> 0 | BE86: =SUMIFS('1-2 人员岗位信息'!O:O,'1-2 人员岗位信息'!$C:$C,"专业外包",'1-2 人员岗位信息'!$B:$B,$D86) -> 0 | BG86: =BH86*BI86 -> 0 | BH86: =SUMIFS('1-2 人员岗位信息'!P:P,'1-2 人员岗位信息'!$C:$C,"专业外包",'1-2 人员岗位信息'!$B:$B,$D86) -> 0 | BJ86: =BK86*BL86 -> 0 | BK86: =SUMIFS('1-2 人员岗位信息'!Q:Q,'1-2 人员岗位信息'!$C:$C,"专业外包",'1-2 人员岗位信息'!$B:$B,$D86) -> 0
B87: 是 | C87: 1.1.1.3.3.7 | D87: 垃圾分拣员工 | E87: 住宅或非住项目需进行垃圾分类而设置的垃圾分拣专岗保洁员工 | G87: 按月编制，汇总成年总量 | H87: =AB87 -> 0 | I87: 岗位数量 | J87: =SUM(AD87,AG87,AJ87,AM87,AP87,AS87,AV87,AY87,BB87,BE87,BH87,BK87)/N87 -> #DIV/0! | K87: 岗 | L87: =H87/N87/J87 -> #DIV/0! | M87: 元/㎡/月 | N87: =COUNTIF(AD87,">0")+COUNTIF(AG87,">0")+COUNTIF(AJ87,">0")+COUNTIF(AM87,">0")+COUNTIF(AP87,">0")+COUNTIF(AS87,">0")+COUNTIF(AV87,">0")+COUNTIF(AY87,">0")+COUNTIF(BB87,">0")+COUNTIF(BE87,">0")+COUNTIF(BH87,">0")+COUNTIF(BK87,">0") -> 0 | AB87: =SUM(AC87,AF87,AI87,AL87,AO87,AR87,AU87,AX87,BA87,BD87,BG87,BJ87) -> 0 | AC87: =AD87*AE87 -> 0 | AD87: =SUMIFS('1-2 人员岗位信息'!F:F,'1-2 人员岗位信息'!$C:$C,"专业外包",'1-2 人员岗位信息'!$B:$B,$D87) -> 0 | AF87: =AG87*AH87 -> 0 | AG87: =SUMIFS('1-2 人员岗位信息'!G:G,'1-2 人员岗位信息'!$C:$C,"专业外包",'1-2 人员岗位信息'!$B:$B,$D87) -> 0 | AI87: =AJ87*AK87 -> 0 | AJ87: =SUMIFS('1-2 人员岗位信息'!H:H,'1-2 人员岗位信息'!$C:$C,"专业外包",'1-2 人员岗位信息'!$B:$B,$D87) -> 0 | AL87: =AM87*AN87 -> 0 | AM87: =SUMIFS('1-2 人员岗位信息'!I:I,'1-2 人员岗位信息'!$C:$C,"专业外包",'1-2 人员岗位信息'!$B:$B,$D87) -> 0 | AO87: =AP87*AQ87 -> 0 | AP87: =SUMIFS('1-2 人员岗位信息'!J:J,'1-2 人员岗位信息'!$C:$C,"专业外包",'1-2 人员岗位信息'!$B:$B,$D87) -> 0 | AR87: =AS87*AT87 -> 0 | AS87: =SUMIFS('1-2 人员岗位信息'!K:K,'1-2 人员岗位信息'!$C:$C,"专业外包",'1-2 人员岗位信息'!$B:$B,$D87) -> 0 | AU87: =AV87*AW87 -> 0 | AV87: =SUMIFS('1-2 人员岗位信息'!L:L,'1-2 人员岗位信息'!$C:$C,"专业外包",'1-2 人员岗位信息'!$B:$B,$D87) -> 0 | AX87: =AY87*AZ87 -> 0 | AY87: =SUMIFS('1-2 人员岗位信息'!M:M,'1-2 人员岗位信息'!$C:$C,"专业外包",'1-2 人员岗位信息'!$B:$B,$D87) -> 0 | BA87: =BB87*BC87 -> 0 | BB87: =SUMIFS('1-2 人员岗位信息'!N:N,'1-2 人员岗位信息'!$C:$C,"专业外包",'1-2 人员岗位信息'!$B:$B,$D87) -> 0 | BD87: =BE87*BF87 -> 0 | BE87: =SUMIFS('1-2 人员岗位信息'!O:O,'1-2 人员岗位信息'!$C:$C,"专业外包",'1-2 人员岗位信息'!$B:$B,$D87) -> 0 | BG87: =BH87*BI87 -> 0 | BH87: =SUMIFS('1-2 人员岗位信息'!P:P,'1-2 人员岗位信息'!$C:$C,"专业外包",'1-2 人员岗位信息'!$B:$B,$D87) -> 0 | BJ87: =BK87*BL87 -> 0 | BK87: =SUMIFS('1-2 人员岗位信息'!Q:Q,'1-2 人员岗位信息'!$C:$C,"专业外包",'1-2 人员岗位信息'!$B:$B,$D87) -> 0
B88: 是 | C88: 1.1.1.3.3.8 | D88: 道路清扫员工 | E88: 适用于城市服务项目道路清扫岗位员工 | G88: 按月编制，汇总成年总量 | H88: =AB88 -> 0 | I88: 岗位数量 | J88: =SUM(AD88,AG88,AJ88,AM88,AP88,AS88,AV88,AY88,BB88,BE88,BH88,BK88)/N88 -> #DIV/0! | K88: 岗 | L88: =H88/N88/J88 -> #DIV/0! | M88: 元/㎡/月 | N88: =COUNTIF(AD88,">0")+COUNTIF(AG88,">0")+COUNTIF(AJ88,">0")+COUNTIF(AM88,">0")+COUNTIF(AP88,">0")+COUNTIF(AS88,">0")+COUNTIF(AV88,">0")+COUNTIF(AY88,">0")+COUNTIF(BB88,">0")+COUNTIF(BE88,">0")+COUNTIF(BH88,">0")+COUNTIF(BK88,">0") -> 0 | AB88: =SUM(AC88,AF88,AI88,AL88,AO88,AR88,AU88,AX88,BA88,BD88,BG88,BJ88) -> 0 | AC88: =AD88*AE88 -> 0 | AD88: =SUMIFS('1-2 人员岗位信息'!F:F,'1-2 人员岗位信息'!$C:$C,"专业外包",'1-2 人员岗位信息'!$B:$B,$D88) -> 0 | AF88: =AG88*AH88 -> 0 | AG88: =SUMIFS('1-2 人员岗位信息'!G:G,'1-2 人员岗位信息'!$C:$C,"专业外包",'1-2 人员岗位信息'!$B:$B,$D88) -> 0 | AI88: =AJ88*AK88 -> 0 | AJ88: =SUMIFS('1-2 人员岗位信息'!H:H,'1-2 人员岗位信息'!$C:$C,"专业外包",'1-2 人员岗位信息'!$B:$B,$D88) -> 0 | AL88: =AM88*AN88 -> 0 | AM88: =SUMIFS('1-2 人员岗位信息'!I:I,'1-2 人员岗位信息'!$C:$C,"专业外包",'1-2 人员岗位信息'!$B:$B,$D88) -> 0 | AO88: =AP88*AQ88 -> 0 | AP88: =SUMIFS('1-2 人员岗位信息'!J:J,'1-2 人员岗位信息'!$C:$C,"专业外包",'1-2 人员岗位信息'!$B:$B,$D88) -> 0 | AR88: =AS88*AT88 -> 0 | AS88: =SUMIFS('1-2 人员岗位信息'!K:K,'1-2 人员岗位信息'!$C:$C,"专业外包",'1-2 人员岗位信息'!$B:$B,$D88) -> 0 | AU88: =AV88*AW88 -> 0 | AV88: =SUMIFS('1-2 人员岗位信息'!L:L,'1-2 人员岗位信息'!$C:$C,"专业外包",'1-2 人员岗位信息'!$B:$B,$D88) -> 0 | AX88: =AY88*AZ88 -> 0 | AY88: =SUMIFS('1-2 人员岗位信息'!M:M,'1-2 人员岗位信息'!$C:$C,"专业外包",'1-2 人员岗位信息'!$B:$B,$D88) -> 0 | BA88: =BB88*BC88 -> 0 | BB88: =SUMIFS('1-2 人员岗位信息'!N:N,'1-2 人员岗位信息'!$C:$C,"专业外包",'1-2 人员岗位信息'!$B:$B,$D88) -> 0 | BD88: =BE88*BF88 -> 0 | BE88: =SUMIFS('1-2 人员岗位信息'!O:O,'1-2 人员岗位信息'!$C:$C,"专业外包",'1-2 人员岗位信息'!$B:$B,$D88) -> 0 | BG88: =BH88*BI88 -> 0 | BH88: =SUMIFS('1-2 人员岗位信息'!P:P,'1-2 人员岗位信息'!$C:$C,"专业外包",'1-2 人员岗位信息'!$B:$B,$D88) -> 0 | BJ88: =BK88*BL88 -> 0 | BK88: =SUMIFS('1-2 人员岗位信息'!Q:Q,'1-2 人员岗位信息'!$C:$C,"专业外包",'1-2 人员岗位信息'!$B:$B,$D88) -> 0
B89: 是 | C89: 1.1.1.3.3.9 | D89: 卫生间保洁员工 | E89: 适用于写字楼、商业等非住业态的卫生间专岗 | G89: 按月编制，汇总成年总量 | H89: =AB89 -> 0 | I89: 岗位数量 | J89: =SUM(AD89,AG89,AJ89,AM89,AP89,AS89,AV89,AY89,BB89,BE89,BH89,BK89)/N89 -> #DIV/0! | K89: 岗 | L89: =H89/N89/J89 -> #DIV/0! | M89: 元/㎡/月 | N89: =COUNTIF(AD89,">0")+COUNTIF(AG89,">0")+COUNTIF(AJ89,">0")+COUNTIF(AM89,">0")+COUNTIF(AP89,">0")+COUNTIF(AS89,">0")+COUNTIF(AV89,">0")+COUNTIF(AY89,">0")+COUNTIF(BB89,">0")+COUNTIF(BE89,">0")+COUNTIF(BH89,">0")+COUNTIF(BK89,">0") -> 0 | AB89: =SUM(AC89,AF89,AI89,AL89,AO89,AR89,AU89,AX89,BA89,BD89,BG89,BJ89) -> 0 | AC89: =AD89*AE89 -> 0 | AD89: =SUMIFS('1-2 人员岗位信息'!F:F,'1-2 人员岗位信息'!$C:$C,"专业外包",'1-2 人员岗位信息'!$B:$B,$D89) -> 0 | AF89: =AG89*AH89 -> 0 | AG89: =SUMIFS('1-2 人员岗位信息'!G:G,'1-2 人员岗位信息'!$C:$C,"专业外包",'1-2 人员岗位信息'!$B:$B,$D89) -> 0 | AI89: =AJ89*AK89 -> 0 | AJ89: =SUMIFS('1-2 人员岗位信息'!H:H,'1-2 人员岗位信息'!$C:$C,"专业外包",'1-2 人员岗位信息'!$B:$B,$D89) -> 0 | AL89: =AM89*AN89 -> 0 | AM89: =SUMIFS('1-2 人员岗位信息'!I:I,'1-2 人员岗位信息'!$C:$C,"专业外包",'1-2 人员岗位信息'!$B:$B,$D89) -> 0 | AO89: =AP89*AQ89 -> 0 | AP89: =SUMIFS('1-2 人员岗位信息'!J:J,'1-2 人员岗位信息'!$C:$C,"专业外包",'1-2 人员岗位信息'!$B:$B,$D89) -> 0 | AR89: =AS89*AT89 -> 0 | AS89: =SUMIFS('1-2 人员岗位信息'!K:K,'1-2 人员岗位信息'!$C:$C,"专业外包",'1-2 人员岗位信息'!$B:$B,$D89) -> 0 | AU89: =AV89*AW89 -> 0 | AV89: =SUMIFS('1-2 人员岗位信息'!L:L,'1-2 人员岗位信息'!$C:$C,"专业外包",'1-2 人员岗位信息'!$B:$B,$D89) -> 0 | AX89: =AY89*AZ89 -> 0 | AY89: =SUMIFS('1-2 人员岗位信息'!M:M,'1-2 人员岗位信息'!$C:$C,"专业外包",'1-2 人员岗位信息'!$B:$B,$D89) -> 0 | BA89: =BB89*BC89 -> 0 | BB89: =SUMIFS('1-2 人员岗位信息'!N:N,'1-2 人员岗位信息'!$C:$C,"专业外包",'1-2 人员岗位信息'!$B:$B,$D89) -> 0 | BD89: =BE89*BF89 -> 0 | BE89: =SUMIFS('1-2 人员岗位信息'!O:O,'1-2 人员岗位信息'!$C:$C,"专业外包",'1-2 人员岗位信息'!$B:$B,$D89) -> 0 | BG89: =BH89*BI89 -> 0 | BH89: =SUMIFS('1-2 人员岗位信息'!P:P,'1-2 人员岗位信息'!$C:$C,"专业外包",'1-2 人员岗位信息'!$B:$B,$D89) -> 0 | BJ89: =BK89*BL89 -> 0 | BK89: =SUMIFS('1-2 人员岗位信息'!Q:Q,'1-2 人员岗位信息'!$C:$C,"专业外包",'1-2 人员岗位信息'!$B:$B,$D89) -> 0
